Workbook

Sheet WALMART_weekly_reporting_2026-B
A1: WALMART - DATA SOURCES: https://seller.walmart.com/analytics/overview/item-sale; https://seller.walmart.com/analytics/reports; And Intentwise
C2: WEEKLY PERFORMANCE | Y2: =(#REF!+#REF!+#REF!+#REF!)-(monthly_reporting_2021!E17+monthly_reporting_2021!E23+monthly_reporting_2021!E29+monthly_reporting_2021!E35) -> #REF! | Z2: =((#REF!+#REF!+#REF!+#REF!)-(monthly_reporting_2021!F17+monthly_reporting_2021!F23+monthly_reporting_2021!F29+monthly_reporting_2021!F35))/(#REF!+#REF!+#REF!+#REF!) -> #REF!
C3: Total Sales | G3: Total Orders | L3: Total Units Sold
C4: =VLOOKUP("Current Week",$B$11:$Y$255,match("SALES",$B$11:$Y$11,0),FALSE) -> 24957.31 | G4: =VLOOKUP("Current Week",$B$11:$Y$255,match("Units Sold",$B$11:$Y$11,0),FALSE) -> 202 | L4: =VLOOKUP("Current Week",$B$11:$Y$255,match("Ordered Items",$B$11:$Y$11,0),FALSE) -> 220
C5: =(C4-(VLOOKUP("Previous Week",$B$11:$Y$260,match("SALES",$B$11:$Y$11,0),FALSE)))/C4 -> 0.10970293 | G5: =(G4-(VLOOKUP("Previous Week",$B$11:$Y$260,match("Units Sold",$B$11:$Y$11,0),FALSE)))/G4 -> -0.14356436 | L5: =(L4-(VLOOKUP("Previous Week",$B$11:$Y$260,match("Ordered Items",$B$11:$Y$11,0),FALSE)))/L4 -> -0.095454545
C7: Advertising Sales | G7: Advertising Spend | L7: ACoS
C8: =VLOOKUP("Current Week",$B$11:$Y$255,match("AD SALES",$B$11:$Y$11,0),FALSE) -> 11089.94 | G8: =VLOOKUP("Current Week",$B$11:$Y$255,match("SP AD SPEND",$B$11:$Y$11,0),FALSE) -> 3174.03 | L8: =G8/C8 -> 0.28620804
C9: =(C8-(VLOOKUP("Previous Week",$B$11:$Y$260,match("AD SALES",$B$11:$Y$11,0),FALSE)))/C8 -> 0.42563891 | G9: =(G8-(VLOOKUP("Previous Week",$B$11:$Y$260,match("SP AD SPEND",$B$11:$Y$11,0),FALSE)))/G8 -> 0.14245927 | L9: =(L8-(VLOOKUP("Previous Week",$B$11:$Y$260,match("ACOS",$B$11:$Y$11,0),FALSE)))/L8 -> -0.49303417
D10: SALES METRICS | M10: ADVERTISING PERFORMANCE | W10: MoM | Y10: YoY
A11: Month-Code | B11: DATE | C11: BRAND | D11: SALES | E11: Average Sales Price by Brand | F11: UNITS SOLD | G11: ORDERED ITEMS | H11: UNITS PER ORDER | I11: SALES PER ORDER | J11: ASP | K11: SP AD SPEND | L11: IMPRESSIONS | M11: UNIT SALES | N11: AD SALES | O11: ACoS | P11: ROAS (return on ad send) | Q11: TACoS (Total Advertsing Cost of Sales) | R11: REVENUE PERCENTAGE OF AD SALES | S11: ORGANIC SALES | T11: CPO | U11: SALES | V11: UNITS | W11: SALES | X11: UNITS
B13: 46012 | C13: AirDoctor | D13: 7936.51 | F13: 30 | G13: 30 | H13: =F13/G13 -> 1 | I13: =D13/F13 -> 264.55033 | J13: =I13/H13 -> 264.55033 | K13: 1654.24 | L13: 263207 | M13: 16 | N13: 4466.73 | O13: =K13/N13 -> 0.37034699 | P13: =N13/K13 -> 2.7001705 | Q13: =K13/D13 -> 0.20843419 | R13: =N13/D13 -> 0.56280783 | S13: =D13-N13 -> 3469.78 | T13: =K13/M13 -> 103.39
C14: AquaTru | D14: 19206.39 | F14: 104 | G14: 119 | H14: =F14/G14 -> 0.87394958 | I14: =D14/F14 -> 184.67683 | J14: =I14/H14 -> 211.31291 | K14: 1288.08 | L14: 442713 | M14: 37 | N14: 6713.65 | O14: =K14/N14 -> 0.19185987 | P14: =N14/K14 -> 5.2121374 | Q14: =K14/D14 -> 0.06706518 | R14: =N14/D14 -> 0.34955294 | S14: =D14-N14 -> 12492.74 | T14: =K14/M14 -> 34.812973
C15: Beflexible | D15: 0 | F15: 0 | G15: 0 | H15: =F15/G15 -> #DIV/0! | I15: =D15/F15 -> #DIV/0! | J15: =I15/H15 -> #DIV/0! | K15: 7.5 | L15: 288 | M15: 0 | N15: 0 | O15: =(K15/N15) -> #DIV/0! | P15: =N15/K15 -> 0 | Q15: =K15/D15 -> #DIV/0! | R15: =N15/D15 -> #DIV/0! | S15: =D15-N15 -> 0 | T15: =K15/M15 -> #DIV/0!
C16: Better Bladder | D16: 545.55 | F16: 9 | G16: 10 | H16: =F16/G16 -> 0.9 | I16: =D16/F16 -> 60.616667 | J16: =I16/H16 -> 67.351852 | K16: 184.21 | L16: 16259 | M16: 1 | N16: 59.95 | O16: =K16/N16 -> 3.0727273 | P16: =N16/K16 -> 0.32544379 | Q16: =K16/D16 -> 0.33765924 | R16: =N16/D16 -> 0.1098891 | S16: =D16-N16 -> 485.6 | T16: =K16/M16 -> 184.21
C17: Ideal Prostate | D17: 589.55 | F17: 9 | G17: 9 | H17: =F17/G17 -> 1 | I17: =D17/F17 -> 65.505556 | J17: =I17/H17 -> 65.505556 | K17: 52.21 | L17: 18056 | M17: 7 | N17: 479.65 | O17: =K17/N17 -> 0.1088502 | P17: =N17/K17 -> 9.1869374 | Q17: =K17/D17 -> 0.08855907 | R17: =N17/D17 -> 0.81358663 | S17: =D17-N17 -> 109.9 | T17: =K17/M17 -> 7.4585714
B18: to | C18: Miracle Blade | D18: -70.63 | F18: -2 | G18: 1 | H18: =F18/G18 -> -2 | I18: =D18/F18 -> 35.315 | J18: =I18/H18 -> -17.6575 | K18: 8.48 | L18: 697 | M18: 0 | N18: 0 | O18: =K18/N18 -> #DIV/0! | P18: =N18/K18 -> 0 | Q18: =K18/D18 -> -0.1200623 | R18: =N18/D18 -> 0 | S18: =D18-N18 -> -70.63 | T18: =K18/M18 -> #DIV/0!
C19: Paint Zoom | D19: 0 | F19: 0 | G19: 0 | H19: =F19/G19 -> #DIV/0! | I19: =D19/F19 -> #DIV/0! | J19: =I19/H19 -> #DIV/0! | K19: 0 | L19: 0 | M19: 0 | N19: 0 | O19: =K19/N19 -> #DIV/0! | P19: =N19/K19 -> #DIV/0! | Q19: =K19/D19 -> #DIV/0! | R19: =N19/D19 -> #DIV/0! | S19: =D19-N19 -> 0 | T19: =K19/M19 -> #DIV/0!
C20: Profemin | D20: 0 | F20: 0 | G20: 0 | H20: =F20/G20 -> #DIV/0! | I20: =D20/F20 -> #DIV/0! | J20: =I20/H20 -> #DIV/0! | K20: 0 | L20: 0 | M20: 0 | N20: 0 | O20: =K20/N20 -> #DIV/0! | P20: =N20/K20 -> #DIV/0! | Q20: =K20/D20 -> #DIV/0! | R20: =N20/D20 -> #DIV/0! | S20: =D20-N20 -> 0 | T20: =K20/M20 -> #DIV/0!
C21: Prosvent | D21: 2629.8 | F21: 29 | G21: 28 | H21: =F21/G21 -> 1.0357143 | I21: =D21/F21 -> 90.682759 | J21: =I21/H21 -> 87.555767 | K21: 668.15 | L21: 36463 | M21: 17 | N21: 1466.87 | O21: =K21/N21 -> 0.45549367 | P21: =N21/K21 -> 2.1954202 | Q21: =K21/D21 -> 0.25406875 | R21: =N21/D21 -> 0.55778766 | S21: =D21-N21 -> 1162.93 | T21: =K21/M21 -> 39.302941
C22: SaniTru | D22: 59.97 | F22: 3 | G22: 4 | H22: =F22/G22 -> 0.75 | I22: =D22/F22 -> 19.99 | J22: =I22/H22 -> 26.653333 | K22: 136.24 | L22: 47577 | M22: 2 | N22: 39.98 | O22: =K22/N22 -> 3.4077039 | P22: =N22/K22 -> 0.29345273 | Q22: =K22/D22 -> 2.2718026 | R22: =N22/D22 -> 0.66666667 | S22: =D22-N22 -> 19.99 | T22: =K22/M22 -> 68.12
C23: Rotorazer Saw | D23: 78.59 | F23: 0 | G23: 2 | H23: =F23/G23 -> 0 | I23: =D23/F23 -> #DIV/0! | J23: =I23/H23 -> #DIV/0! | K23: 36.36 | L23: 10972 | M23: 1 | N23: 154.46 | O23: =K23/N23 -> 0.23540075 | P23: =N23/K23 -> 4.2480748 | Q23: =K23/D23 -> 0.46265428 | R23: =N23/D23 -> 1.96539 | S23: =D23-N23 -> -75.87 | T23: =K23/M23 -> 36.36
C24: Superthotics | D24: 190.8 | F24: 4 | G24: 4 | H24: =F24/G24 -> 1 | I24: =D24/F24 -> 47.7 | J24: =I24/H24 -> 47.7 | K24: 80.52 | L24: 40401 | M24: 3 | N24: 134.85 | O24: =K24/N24 -> 0.5971079 | P24: =N24/K24 -> 1.6747392 | Q24: =K24/D24 -> 0.42201258 | R24: =N24/D24 -> 0.70676101 | S24: =D24-N24 -> 55.95 | T24: =K24/M24 -> 26.84
C25: Therabotanics | D25: 0 | F25: 0 | G25: 0 | H25: =F25/G25 -> #DIV/0! | I25: =D25/F25 -> #DIV/0! | J25: =I25/H25 -> #DIV/0! | K25: 0 | L25: 0 | M25: 0 | N25: 0 | O25: =K25/N25 -> #DIV/0! | P25: =N25/K25 -> #DIV/0! | Q25: =K25/D25 -> #DIV/0! | R25: =N25/D25 -> #DIV/0! | S25: =D25-N25 -> 0 | T25: =K25/M25 -> #DIV/0!
C26: WALKFIT | D26: 1312.67 | F26: 34 | G26: 31 | H26: =F26/G26 -> 1.0967742 | I26: =D26/F26 -> 38.607941 | J26: =I26/H26 -> 35.201358 | K26: 269.35 | L26: 50705 | M26: 13 | N26: 403.73 | O26: =K26/N26 -> 0.66715379 | P26: =N26/K26 -> 1.4989048 | Q26: =K26/D26 -> 0.20519247 | R26: =N26/D26 -> 0.30756397 | S26: =D26-N26 -> 908.94 | T26: =K26/M26 -> 20.719231
C27: Ultmax | D27: -29.95 | F27: -1 | G27: 0 | H27: =F27/G27 -> #DIV/0! | I27: =D27/F27 -> 29.95 | J27: =I27/H27 -> #DIV/0! | K27: 0 | L27: 0 | M27: 0 | N27: 0 | O27: =K27/N27 -> #DIV/0! | P27: =N27/K27 -> #DIV/0! | Q27: =K27/D27 -> 0 | R27: =N27/D27 -> 0 | S27: =D27-N27 -> -29.95 | T27: =K27/M27 -> #DIV/0!
C28: Ionic Pro | D28: 4625.06 | F28: 26 | G28: 28 | H28: =F28/G28 -> 0.92857143 | I28: =D28/F28 -> 177.88692 | J28: =I28/H28 -> 191.57053 | K28: 692.49 | L28: 44157 | M28: 11 | N28: 1670.89 | O28: =K28/N28 -> 0.4144438 | P28: =N28/K28 -> 2.4128724 | Q28: =K28/D28 -> 0.14972563 | R28: =N28/D28 -> 0.36126883 | S28: =D28-N28 -> 2954.17 | T28: =K28/M28 -> 62.953636
A29: =iferror(if(B29>0,month(B29)&"-"&year(B29),B29),) -> 12-2025 | B29: 46018 | C29: AromaTru | D29: 0 | F29: 0 | G29: 0 | H29: =F29/G29 -> #DIV/0! | I29: =D29/F29 -> #DIV/0! | J29: =I29/H29 -> #DIV/0! | K29: 16.97 | L29: 17393 | M29: 0 | N29: 0 | O29: =K29/N29 -> #DIV/0! | P29: =N29/K29 -> 0 | Q29: =K29/D29 -> #DIV/0! | R29: =N29/D29 -> #DIV/0! | S29: =D29-N29 -> 0 | T29: =K29/M29 -> #DIV/0!
A30: =iferror(if(B30>0,month(B30)&"-"&year(B30),B30),) | B30: 2025 - Week 52 | D30: =SUM(D13:D29) -> 37074.31 | F30: =SUM(F13:F29) -> 245 | G30: =SUM(G13:G29) -> 266 | H30: =F30/G30 -> 0.92105263 | I30: =D30/F30 -> 151.32371 | J30: =I30/H30 -> 164.29432 | K30: =SUM(K13:K29) -> 5094.8 | L30: =SUM(L13:L29) -> 988888 | M30: =SUM(M13:M29) -> 108 | N30: =SUM(N13:N29) -> 15590.76 | O30: =K30/N30 -> 0.3267833 | P30: =N30/K30 -> 3.0601319 | Q30: =K30/D30 -> 0.1374213 | R30: =N30/D30 -> 0.42052731 | S30: =SUM(S13:S29) -> 21483.55 | T30: =K30/M30 -> 47.174074 | U30: =IFERROR((D30-#REF!)/D30,) | V30: =IFERROR((F30-#REF!)/F30,) | W30: =IFERROR((D30-#REF!)/D30, ) | X30: =IFERROR((F30-#REF!)/F30, )
B31: 46019 | C31: AirDoctor | D31: 13519.5 | F31: 57 | G31: 57 | H31: =F31/G31 -> 1 | I31: =D31/F31 -> 237.18421 | J31: =I31/H31 -> 237.18421 | K31: 1867.63 | L31: 249548 | M31: 23 | N31: 5019.44 | O31: =K31/N31 -> 0.37207936 | P31: =N31/K31 -> 2.6875987 | Q31: =K31/D31 -> 0.13814342 | R31: =N31/D31 -> 0.37127409 | S31: =D31-N31 -> 8500.06 | T31: =K31/M31 -> 81.201304
C32: AquaTru | D32: 18767.79 | F32: 145 | G32: 161 | H32: =F32/G32 -> 0.90062112 | I32: =D32/F32 -> 129.43303 | J32: =I32/H32 -> 143.7153 | K32: 1072.07 | L32: 465644 | M32: 32 | N32: 3923.85 | O32: =K32/N32 -> 0.2732189 | P32: =N32/K32 -> 3.6600688 | Q32: =K32/D32 -> 0.057122868 | R32: =N32/D32 -> 0.20907363 | S32: =D32-N32 -> 14843.94 | T32: =K32/M32 -> 33.502187
C33: Beflexible | D33: 0 | F33: 0 | G33: 0 | H33: =F33/G33 -> #DIV/0! | I33: =D33/F33 -> #DIV/0! | J33: =I33/H33 -> #DIV/0! | K33: 0 | L33: 376 | M33: 0 | N33: 0 | O33: =(K33/N33) -> #DIV/0! | P33: =N33/K33 -> #DIV/0! | Q33: =K33/D33 -> #DIV/0! | R33: =N33/D33 -> #DIV/0! | S33: =D33-N33 -> 0 | T33: =K33/M33 -> #DIV/0!
C34: Better Bladder | D34: 125.9 | F34: 2 | G34: 2 | H34: =F34/G34 -> 1 | I34: =D34/F34 -> 62.95 | J34: =I34/H34 -> 62.95 | K34: 298.8 | L34: 26455 | M34: 5 | N34: 299.75 | O34: =K34/N34 -> 0.99683069 | P34: =N34/K34 -> 1.0031794 | Q34: =K34/D34 -> 2.3733122 | R34: =N34/D34 -> 2.3808578 | S34: =D34-N34 -> -173.85 | T34: =K34/M34 -> 59.76
C35: Ideal Prostate | D35: 359.7 | F35: 6 | G35: 6 | H35: =F35/G35 -> 1 | I35: =D35/F35 -> 59.95 | J35: =I35/H35 -> 59.95 | K35: 105.72 | L35: 27117 | M35: 2 | N35: 129.9 | O35: =K35/N35 -> 0.81385681 | P35: =N35/K35 -> 1.2287174 | Q35: =K35/D35 -> 0.29391159 | R35: =N35/D35 -> 0.36113428 | S35: =D35-N35 -> 229.8 | T35: =K35/M35 -> 52.86
B36: to | C36: Miracle Blade | D36: -60.73 | F36: 0 | G36: 1 | H36: =F36/G36 -> 0 | I36: =D36/F36 -> #DIV/0! | J36: =I36/H36 -> #DIV/0! | K36: 83.88 | L36: 253679 | M36: 0 | N36: 0 | O36: =K36/N36 -> #DIV/0! | P36: =N36/K36 -> 0 | Q36: =K36/D36 -> -1.3811955 | R36: =N36/D36 -> 0 | S36: =D36-N36 -> -60.73 | T36: =K36/M36 -> #DIV/0!
C37: Paint Zoom | D37: 0 | F37: 0 | G37: 0 | H37: =F37/G37 -> #DIV/0! | I37: =D37/F37 -> #DIV/0! | J37: =I37/H37 -> #DIV/0! | K37: 0 | L37: 0 | M37: 0 | N37: 0 | O37: =K37/N37 -> #DIV/0! | P37: =N37/K37 -> #DIV/0! | Q37: =K37/D37 -> #DIV/0! | R37: =N37/D37 -> #DIV/0! | S37: =D37-N37 -> 0 | T37: =K37/M37 -> #DIV/0!
C38: Profemin | D38: 0 | F38: 0 | G38: 0 | H38: =F38/G38 -> #DIV/0! | I38: =D38/F38 -> #DIV/0! | J38: =I38/H38 -> #DIV/0! | K38: 0 | L38: 0 | M38: 0 | N38: 0 | O38: =K38/N38 -> #DIV/0! | P38: =N38/K38 -> #DIV/0! | Q38: =K38/D38 -> #DIV/0! | R38: =N38/D38 -> #DIV/0! | S38: =D38-N38 -> 0 | T38: =K38/M38 -> #DIV/0!
C39: Prosvent | D39: 3534.27 | F39: 49 | G39: 51 | H39: =F39/G39 -> 0.96078431 | I39: =D39/F39 -> 72.127959 | J39: =I39/H39 -> 75.071958 | K39: 799.06 | L39: 59789 | M39: 14 | N39: 877.86 | O39: =K39/N39 -> 0.91023626 | P39: =N39/K39 -> 1.0986159 | Q39: =K39/D39 -> 0.22608912 | R39: =N39/D39 -> 0.2483851 | S39: =D39-N39 -> 2656.41 | T39: =K39/M39 -> 57.075714
C40: SaniTru | D40: 59.97 | F40: 3 | G40: 3 | H40: =F40/G40 -> 1 | I40: =D40/F40 -> 19.99 | J40: =I40/H40 -> 19.99 | K40: 356.37 | L40: 105893 | M40: 2 | N40: 39.98 | O40: =K40/N40 -> 8.9137069 | P40: =N40/K40 -> 0.11218677 | Q40: =K40/D40 -> 5.9424712 | R40: =N40/D40 -> 0.66666667 | S40: =D40-N40 -> 19.99 | T40: =K40/M40 -> 178.185
C41: Rotorazer Saw | D41: 1547.97 | F41: 13 | G41: 13 | H41: =F41/G41 -> 1 | I41: =D41/F41 -> 119.07462 | J41: =I41/H41 -> 119.07462 | K41: 74.14 | L41: 10788 | M41: 1 | N41: 0 | O41: =K41/N41 -> #DIV/0! | P41: =N41/K41 -> 0 | Q41: =K41/D41 -> 0.047894985 | R41: =N41/D41 -> 0 | S41: =D41-N41 -> 1547.97 | T41: =K41/M41 -> 74.14
C42: Superthotics | D42: 209.8 | F42: 4 | G42: 4 | H42: =F42/G42 -> 1 | I42: =D42/F42 -> 52.45 | J42: =I42/H42 -> 52.45 | K42: 72.7 | L42: 40190 | M42: 3 | N42: 164.85 | O42: =K42/N42 -> 0.44100698 | P42: =N42/K42 -> 2.2675378 | Q42: =K42/D42 -> 0.3465205 | R42: =N42/D42 -> 0.78574833 | S42: =D42-N42 -> 44.95 | T42: =K42/M42 -> 24.233333
C43: Therabotanics | D43: 0 | F43: 0 | G43: 0 | H43: =F43/G43 -> #DIV/0! | I43: =D43/F43 -> #DIV/0! | J43: =I43/H43 -> #DIV/0! | K43: 0 | L43: 0 | M43: 0 | N43: 0 | O43: =K43/N43 -> #DIV/0! | P43: =N43/K43 -> #DIV/0! | Q43: =K43/D43 -> #DIV/0! | R43: =N43/D43 -> #DIV/0! | S43: =D43-N43 -> 0 | T43: =K43/M43 -> #DIV/0!
C44: WALKFIT | D44: 1218.39 | F44: 31 | G44: 31 | H44: =F44/G44 -> 1 | I44: =D44/F44 -> 39.302903 | J44: =I44/H44 -> 39.302903 | K44: 258.05 | L44: 66414 | M44: 25 | N44: 985.26 | O44: =K44/N44 -> 0.26191056 | P44: =N44/K44 -> 3.8180973 | Q44: =K44/D44 -> 0.21179589 | R44: =N44/D44 -> 0.80865733 | S44: =D44-N44 -> 233.13 | T44: =K44/M44 -> 10.322
C45: Ultmax | D45: 59.9 | F45: 2 | G45: 2 | H45: =F45/G45 -> 1 | I45: =D45/F45 -> 29.95 | J45: =I45/H45 -> 29.95 | K45: 0 | L45: 0 | M45: 0 | N45: 0 | O45: =K45/N45 -> #DIV/0! | P45: =N45/K45 -> #DIV/0! | Q45: =K45/D45 -> 0 | R45: =N45/D45 -> 0 | S45: =D45-N45 -> 59.9 | T45: =K45/M45 -> #DIV/0!
C46: Ionic Pro | D46: 6535.42 | F46: 31 | G46: 31 | H46: =F46/G46 -> 1 | I46: =D46/F46 -> 210.82 | J46: =I46/H46 -> 210.82 | K46: 807.83 | L46: 55281 | M46: 15 | N46: 2922.51 | O46: =K46/N46 -> 0.2764165 | P46: =N46/K46 -> 3.617729 | Q46: =K46/D46 -> 0.12360797 | R46: =N46/D46 -> 0.44718014 | S46: =D46-N46 -> 3612.91 | T46: =K46/M46 -> 53.855333
A47: =iferror(if(B47>0,month(B47)&"-"&year(B47),B47),) -> 1-2026 | B47: 46025 | C47: AromaTru | D47: -27 | F47: -1 | G47: 0 | H47: =F47/G47 -> #DIV/0! | I47: =D47/F47 -> 27 | J47: =I47/H47 -> #DIV/0! | K47: 10.46 | L47: 14576 | M47: 0 | N47: 0 | O47: =K47/N47 -> #DIV/0! | P47: =N47/K47 -> 0 | Q47: =K47/D47 -> -0.38740741 | R47: =N47/D47 -> 0 | S47: =D47-N47 -> -27 | T47: =K47/M47 -> #DIV/0!
A48: =iferror(if(B48>0,month(B48)&"-"&year(B48),B48),) | B48: 2026 - Week 1 | D48: =SUM(D31:D47) -> 45850.88 | F48: =SUM(F31:F47) -> 342 | G48: =SUM(G31:G47) -> 362 | H48: =F48/G48 -> 0.94475138 | I48: =D48/F48 -> 134.0669 | J48: =I48/H48 -> 141.90707 | K48: =SUM(K31:K47) -> 5806.71 | L48: =SUM(L31:L47) -> 1375750 | M48: =SUM(M31:M47) -> 122 | N48: =SUM(N31:N47) -> 14363.4 | O48: =K48/N48 -> 0.40427127 | P48: =N48/K48 -> 2.4735866 | Q48: =K48/D48 -> 0.12664337 | R48: =N48/D48 -> 0.31326334 | S48: =SUM(S31:S47) -> 31487.48 | T48: =K48/M48 -> 47.595984 | U48: =IFERROR((D48-#REF!)/D48,) | V48: =IFERROR((F48-#REF!)/F48,) | W48: =IFERROR((D48-#REF!)/D48, ) | X48: =IFERROR((F48-#REF!)/F48, )
B49: 46026 | C49: AirDoctor | D49: 4193.34 | F49: 31 | G49: 31 | H49: =F49/G49 -> 1 | I49: =D49/F49 -> 135.26903 | J49: =I49/H49 -> 135.26903 | K49: 1013.35 | L49: 165235 | M49: 6 | N49: 925.9 | O49: =K49/N49 -> 1.0944486 | P49: =N49/K49 -> 0.91370208 | Q49: =K49/D49 -> 0.24165701 | R49: =N49/D49 -> 0.22080251 | S49: =D49-N49 -> 3267.44 | T49: =K49/M49 -> 168.89167
C50: AquaTru | D50: 7722.36 | F50: 94 | G50: 105 | H50: =F50/G50 -> 0.8952381 | I50: =D50/F50 -> 82.152766 | J50: =I50/H50 -> 91.766388 | K50: 759.35 | L50: 402437 | M50: 21 | N50: 2698.5 | O50: =K50/N50 -> 0.28139707 | P50: =N50/K50 -> 3.5536972 | Q50: =K50/D50 -> 0.098331339 | R50: =N50/D50 -> 0.34943981 | S50: =D50-N50 -> 5023.86 | T50: =K50/M50 -> 36.159524
C51: Beflexible | D51: 279.8 | F51: 4 | G51: 2 | H51: =F51/G51 -> 2 | I51: =D51/F51 -> 69.95 | J51: =I51/H51 -> 34.975 | K51: 7.22 | L51: 413 | M51: 0 | N51: 0 | O51: =(K51/N51) -> #DIV/0! | P51: =N51/K51 -> 0 | Q51: =K51/D51 -> 0.025804146 | R51: =N51/D51 -> 0 | S51: =D51-N51 -> 279.8 | T51: =K51/M51 -> #DIV/0!
C52: Better Bladder | D52: 1085.11 | F52: 18 | G52: 22 | H52: =F52/G52 -> 0.81818182 | I52: =D52/F52 -> 60.283889 | J52: =I52/H52 -> 73.680309 | K52: 317.55 | L52: 27416 | M52: 12 | N52: 659.45 | O52: =K52/N52 -> 0.48153765 | P52: =N52/K52 -> 2.0766808 | Q52: =K52/D52 -> 0.29264314 | R52: =N52/D52 -> 0.60772641 | S52: =D52-N52 -> 425.66 | T52: =K52/M52 -> 26.4625
C53: Ideal Prostate | D53: 974.25 | F53: 15 | G53: 16 | H53: =F53/G53 -> 0.9375 | I53: =D53/F53 -> 64.95 | J53: =I53/H53 -> 69.28 | K53: 78.8 | L53: 26820 | M53: 1 | N53: 69.95 | O53: =K53/N53 -> 1.1265189 | P53: =N53/K53 -> 0.88769036 | Q53: =K53/D53 -> 0.08088273 | R53: =N53/D53 -> 0.07179882 | S53: =D53-N53 -> 904.3 | T53: =K53/M53 -> 78.8
B54: to | C54: Miracle Blade | D54: 114.85 | F54: 3 | G54: 3 | H54: =F54/G54 -> 1 | I54: =D54/F54 -> 38.283333 | J54: =I54/H54 -> 38.283333 | K54: 40.77 | L54: 241677 | M54: 0 | N54: 0 | O54: =K54/N54 -> #DIV/0! | P54: =N54/K54 -> 0 | Q54: =K54/D54 -> 0.35498476 | R54: =N54/D54 -> 0 | S54: =D54-N54 -> 114.85 | T54: =K54/M54 -> #DIV/0!
C55: Paint Zoom | D55: 0 | F55: 0 | G55: 0 | H55: =F55/G55 -> #DIV/0! | I55: =D55/F55 -> #DIV/0! | J55: =I55/H55 -> #DIV/0! | K55: 0 | L55: 0 | M55: 0 | N55: 0 | O55: =K55/N55 -> #DIV/0! | P55: =N55/K55 -> #DIV/0! | Q55: =K55/D55 -> #DIV/0! | R55: =N55/D55 -> #DIV/0! | S55: =D55-N55 -> 0 | T55: =K55/M55 -> #DIV/0!
C56: Profemin | D56: 0 | F56: 0 | G56: 0 | H56: =F56/G56 -> #DIV/0! | I56: =D56/F56 -> #DIV/0! | J56: =I56/H56 -> #DIV/0! | K56: 0 | L56: 0 | M56: 0 | N56: 0 | O56: =K56/N56 -> #DIV/0! | P56: =N56/K56 -> #DIV/0! | Q56: =K56/D56 -> #DIV/0! | R56: =N56/D56 -> #DIV/0! | S56: =D56-N56 -> 0 | T56: =K56/M56 -> #DIV/0!
C57: Prosvent | D57: 2607.66 | F57: 38 | G57: 37 | H57: =F57/G57 -> 1.027027 | I57: =D57/F57 -> 68.622632 | J57: =I57/H57 -> 66.816773 | K57: 582.07 | L57: 53074 | M57: 14 | N57: 1068.9 | O57: =K57/N57 -> 0.54455047 | P57: =N57/K57 -> 1.8363771 | Q57: =K57/D57 -> 0.22321545 | R57: =N57/D57 -> 0.40990773 | S57: =D57-N57 -> 1538.76 | T57: =K57/M57 -> 41.576429
C58: SaniTru | D58: 39.98 | F58: 2 | G58: 5 | H58: =F58/G58 -> 0.4 | I58: =D58/F58 -> 19.99 | J58: =I58/H58 -> 49.975 | K58: 390.2 | L58: 90636 | M58: 5 | N58: 99.95 | O58: =K58/N58 -> 3.903952 | P58: =N58/K58 -> 0.25615069 | Q58: =K58/D58 -> 9.7598799 | R58: =N58/D58 -> 2.5 | S58: =D58-N58 -> -59.97 | T58: =K58/M58 -> 78.04
C59: Rotorazer Saw | D59: 1285.59 | F59: 10 | G59: 10 | H59: =F59/G59 -> 1 | I59: =D59/F59 -> 128.559 | J59: =I59/H59 -> 128.559 | K59: 70.1 | L59: 8798 | M59: 1 | N59: 0 | O59: =K59/N59 -> #DIV/0! | P59: =N59/K59 -> 0 | Q59: =K59/D59 -> 0.054527493 | R59: =N59/D59 -> 0 | S59: =D59-N59 -> 1285.59 | T59: =K59/M59 -> 70.1
C60: Superthotics | D60: 134.9 | F60: 2 | G60: 3 | H60: =F60/G60 -> 0.66666667 | I60: =D60/F60 -> 67.45 | J60: =I60/H60 -> 101.175 | K60: 79.11 | L60: 52026 | M60: 2 | N60: 119.9 | O60: =K60/N60 -> 0.65979983 | P60: =N60/K60 -> 1.5156112 | Q60: =K60/D60 -> 0.5864344 | R60: =N60/D60 -> 0.88880652 | S60: =D60-N60 -> 15 | T60: =K60/M60 -> 39.555
C61: Therabotanics | D61: 49.9 | F61: 2 | G61: 3 | H61: =F61/G61 -> 0.66666667 | I61: =D61/F61 -> 24.95 | J61: =I61/H61 -> 37.425 | K61: 0 | L61: 0 | M61: 0 | N61: 0 | O61: =K61/N61 -> #DIV/0! | P61: =N61/K61 -> #DIV/0! | Q61: =K61/D61 -> 0 | R61: =N61/D61 -> 0 | S61: =D61-N61 -> 49.9 | T61: =K61/M61 -> #DIV/0!
C62: WALKFIT | D62: 922.7 | F62: 21 | G62: 25 | H62: =F62/G62 -> 0.84 | I62: =D62/F62 -> 43.938095 | J62: =I62/H62 -> 52.307256 | K62: 240.22 | L62: 70753 | M62: 9 | N62: 306.65 | O62: =K62/N62 -> 0.78336866 | P62: =N62/K62 -> 1.2765382 | Q62: =K62/D62 -> 0.26034464 | R62: =N62/D62 -> 0.33233987 | S62: =D62-N62 -> 616.05 | T62: =K62/M62 -> 26.691111
C63: Ultmax | D63: 99.25 | F63: 5 | G63: 3 | H63: =F63/G63 -> 1.6666667 | I63: =D63/F63 -> 19.85 | J63: =I63/H63 -> 11.91 | K63: 0 | L63: 0 | M63: 0 | N63: 0 | O63: =K63/N63 -> #DIV/0! | P63: =N63/K63 -> #DIV/0! | Q63: =K63/D63 -> 0 | R63: =N63/D63 -> 0 | S63: =D63-N63 -> 99.25 | T63: =K63/M63 -> #DIV/0!
C64: Ionic Pro | D64: 4039.1 | F64: 18 | G64: 18 | H64: =F64/G64 -> 1 | I64: =D64/F64 -> 224.39444 | J64: =I64/H64 -> 224.39444 | K64: 573.49 | L64: 48071 | M64: 8 | N64: 1459.65 | O64: =K64/N64 -> 0.39289556 | P64: =N64/K64 -> 2.5452057 | Q64: =K64/D64 -> 0.1419846 | R64: =N64/D64 -> 0.36138001 | S64: =D64-N64 -> 2579.45 | T64: =K64/M64 -> 71.68625
A65: =iferror(if(B65>0,month(B65)&"-"&year(B65),B65),) -> 1-2026 | B65: 46032 | C65: AromaTru | D65: 0 | F65: 0 | G65: 0 | H65: =F65/G65 -> #DIV/0! | I65: =D65/F65 -> #DIV/0! | J65: =I65/H65 -> #DIV/0! | K65: 16.26 | L65: 10972 | M65: 0 | N65: 0 | O65: =K65/N65 -> #DIV/0! | P65: =N65/K65 -> 0 | Q65: =K65/D65 -> #DIV/0! | R65: =N65/D65 -> #DIV/0! | S65: =D65-N65 -> 0 | T65: =K65/M65 -> #DIV/0!
A66: =iferror(if(B66>0,month(B66)&"-"&year(B66),B66),) | B66: 2026 - Week 2 | D66: =SUM(D49:D65) -> 23548.79 | F66: =SUM(F49:F65) -> 263 | G66: =SUM(G49:G65) -> 283 | H66: =F66/G66 -> 0.92932862 | I66: =D66/F66 -> 89.539125 | J66: =I66/H66 -> 96.348184 | K66: =SUM(K49:K65) -> 4168.49 | L66: =SUM(L49:L65) -> 1198328 | M66: =SUM(M49:M65) -> 79 | N66: =SUM(N49:N65) -> 7408.85 | O66: =K66/N66 -> 0.56263658 | P66: =N66/K66 -> 1.7773462 | Q66: =K66/D66 -> 0.17701504 | R66: =N66/D66 -> 0.31461701 | S66: =SUM(S49:S65) -> 16139.94 | T66: =K66/M66 -> 52.765696 | U66: =IFERROR((D66-#REF!)/D66,) | V66: =IFERROR((F66-#REF!)/F66,) | W66: =IFERROR((D66-#REF!)/D66, ) | X66: =IFERROR((F66-#REF!)/F66, )
B67: 46033 | C67: AirDoctor | D67: 2300.92 | F67: 23 | G67: 28 | H67: =F67/G67 -> 0.82142857 | I67: =D67/F67 -> 100.04 | J67: =I67/H67 -> 121.78783 | K67: 623.32 | L67: 111636 | M67: 6 | N67: 204.9 | O67: =K67/N67 -> 3.0420693 | P67: =N67/K67 -> 0.32872361 | Q67: =K67/D67 -> 0.27090034 | R67: =N67/D67 -> 0.089051336 | S67: =D67-N67 -> 2096.02 | T67: =K67/M67 -> 103.88667
C68: AquaTru | D68: 4373.42 | F68: 63 | G68: 82 | H68: =F68/G68 -> 0.76829268 | I68: =D68/F68 -> 69.419365 | J68: =I68/H68 -> 90.355364 | K68: 822.42 | L68: 169878 | M68: 29 | N68: 2624.25 | O68: =K68/N68 -> 0.3133924 | P68: =N68/K68 -> 3.1908879 | Q68: =K68/D68 -> 0.18804963 | R68: =N68/D68 -> 0.60004527 | S68: =D68-N68 -> 1749.17 | T68: =K68/M68 -> 28.35931
C69: Beflexible | D69: 419.7 | F69: 6 | G69: 3 | H69: =F69/G69 -> 2 | I69: =D69/F69 -> 69.95 | J69: =I69/H69 -> 34.975 | K69: 7.22 | L69: 318 | M69: 0 | N69: 0 | O69: =(K69/N69) -> #DIV/0! | P69: =N69/K69 -> 0 | Q69: =K69/D69 -> 0.017202764 | R69: =N69/D69 -> 0 | S69: =D69-N69 -> 419.7 | T69: =K69/M69 -> #DIV/0!
C70: Better Bladder | D70: 188.85 | F70: 3 | G70: 3 | H70: =F70/G70 -> 1 | I70: =D70/F70 -> 62.95 | J70: =I70/H70 -> 62.95 | K70: 313.22 | L70: 27042 | M70: 7 | N70: 419.65 | O70: =K70/N70 -> 0.74638389 | P70: =N70/K70 -> 1.3397931 | Q70: =K70/D70 -> 1.658565 | R70: =N70/D70 -> 2.222134 | S70: =D70-N70 -> -230.8 | T70: =K70/M70 -> 44.745714
C71: Ideal Prostate | D71: 1139.1 | F71: 18 | G71: 17 | H71: =F71/G71 -> 1.0588235 | I71: =D71/F71 -> 63.283333 | J71: =I71/H71 -> 59.767593 | K71: 73.93 | L71: 23474 | M71: 6 | N71: 389.7 | O71: =K71/N71 -> 0.18971003 | P71: =N71/K71 -> 5.2712025 | Q71: =K71/D71 -> 0.064902116 | R71: =N71/D71 -> 0.34211219 | S71: =D71-N71 -> 749.4 | T71: =K71/M71 -> 12.321667
B72: to | C72: Miracle Blade | D72: 0 | F72: 0 | G72: 0 | H72: =F72/G72 -> #DIV/0! | I72: =D72/F72 -> #DIV/0! | J72: =I72/H72 -> #DIV/0! | K72: 24.92 | L72: 189436 | M72: 0 | N72: 0 | O72: =K72/N72 -> #DIV/0! | P72: =N72/K72 -> 0 | Q72: =K72/D72 -> #DIV/0! | R72: =N72/D72 -> #DIV/0! | S72: =D72-N72 -> 0 | T72: =K72/M72 -> #DIV/0!
C73: Paint Zoom | D73: 0 | F73: 0 | G73: 0 | H73: =F73/G73 -> #DIV/0! | I73: =D73/F73 -> #DIV/0! | J73: =I73/H73 -> #DIV/0! | K73: 0 | L73: 0 | M73: 0 | N73: 0 | O73: =K73/N73 -> #DIV/0! | P73: =N73/K73 -> #DIV/0! | Q73: =K73/D73 -> #DIV/0! | R73: =N73/D73 -> #DIV/0! | S73: =D73-N73 -> 0 | T73: =K73/M73 -> #DIV/0!
C74: Profemin | D74: 0 | F74: 0 | G74: 0 | H74: =F74/G74 -> #DIV/0! | I74: =D74/F74 -> #DIV/0! | J74: =I74/H74 -> #DIV/0! | K74: 0 | L74: 0 | M74: 0 | N74: 0 | O74: =K74/N74 -> #DIV/0! | P74: =N74/K74 -> #DIV/0! | Q74: =K74/D74 -> #DIV/0! | R74: =N74/D74 -> #DIV/0! | S74: =D74-N74 -> 0 | T74: =K74/M74 -> #DIV/0!
C75: Prosvent | D75: 2585.66 | F75: 38 | G75: 37 | H75: =F75/G75 -> 1.027027 | I75: =D75/F75 -> 68.043684 | J75: =I75/H75 -> 66.253061 | K75: 439.15 | L75: 48219 | M75: 11 | N75: 718.93 | O75: =K75/N75 -> 0.61083833 | P75: =N75/K75 -> 1.6370944 | Q75: =K75/D75 -> 0.16984058 | R75: =N75/D75 -> 0.27804506 | S75: =D75-N75 -> 1866.73 | T75: =K75/M75 -> 39.922727
C76: SaniTru | D76: 39.98 | F76: 2 | G76: 3 | H76: =F76/G76 -> 0.66666667 | I76: =D76/F76 -> 19.99 | J76: =I76/H76 -> 29.985 | K76: 315.74 | L76: 83987 | M76: 1 | N76: 19.99 | O76: =K76/N76 -> 15.794897 | P76: =N76/K76 -> 0.063311585 | Q76: =K76/D76 -> 7.8974487 | R76: =N76/D76 -> 0.5 | S76: =D76-N76 -> 19.99 | T76: =K76/M76 -> 315.74
C77: Rotorazer Saw | D77: 599.8 | F77: 5 | G77: 6 | H77: =F77/G77 -> 0.83333333 | I77: =D77/F77 -> 119.96 | J77: =I77/H77 -> 143.952 | K77: 78.62 | L77: 6710 | M77: 1 | N77: 0 | O77: =K77/N77 -> #DIV/0! | P77: =N77/K77 -> 0 | Q77: =K77/D77 -> 0.13107703 | R77: =N77/D77 -> 0 | S77: =D77-N77 -> 599.8 | T77: =K77/M77 -> 78.62
C78: Superthotics | D78: 183.85 | F78: 3 | G78: 5 | H78: =F78/G78 -> 0.6 | I78: =D78/F78 -> 61.283333 | J78: =I78/H78 -> 102.13889 | K78: 97.43 | L78: 54420 | M78: 4 | N78: 239.8 | O78: =K78/N78 -> 0.40629691 | P78: =N78/K78 -> 2.4612542 | Q78: =K78/D78 -> 0.52994289 | R78: =N78/D78 -> 1.3043242 | S78: =D78-N78 -> -55.95 | T78: =K78/M78 -> 24.3575
C79: Therabotanics | D79: 29.95 | F79: 1 | G79: 1 | H79: =F79/G79 -> 1 | I79: =D79/F79 -> 29.95 | J79: =I79/H79 -> 29.95 | K79: 0 | L79: 0 | M79: 0 | N79: 0 | O79: =K79/N79 -> #DIV/0! | P79: =N79/K79 -> #DIV/0! | Q79: =K79/D79 -> 0 | R79: =N79/D79 -> 0 | S79: =D79-N79 -> 29.95 | T79: =K79/M79 -> #DIV/0!
C80: WALKFIT | D80: 873 | F80: 20 | G80: 23 | H80: =F80/G80 -> 0.86956522 | I80: =D80/F80 -> 43.65 | J80: =I80/H80 -> 50.1975 | K80: 223.97 | L80: 52080 | M80: 7 | N80: 216.75 | O80: =K80/N80 -> 1.0333103 | P80: =N80/K80 -> 0.96776354 | Q80: =K80/D80 -> 0.25655212 | R80: =N80/D80 -> 0.24828179 | S80: =D80-N80 -> 656.25 | T80: =K80/M80 -> 31.995714
C81: Ultmax | D81: 0 | F81: 0 | G81: 0 | H81: =F81/G81 -> #DIV/0! | I81: =D81/F81 -> #DIV/0! | J81: =I81/H81 -> #DIV/0! | K81: 0 | L81: 0 | M81: 0 | N81: 0 | O81: =K81/N81 -> #DIV/0! | P81: =N81/K81 -> #DIV/0! | Q81: =K81/D81 -> #DIV/0! | R81: =N81/D81 -> #DIV/0! | S81: =D81-N81 -> 0 | T81: =K81/M81 -> #DIV/0!
C82: Ionic Pro | D82: 3625.99 | F82: 16 | G82: 19 | H82: =F82/G82 -> 0.84210526 | I82: =D82/F82 -> 226.62437 | J82: =I82/H82 -> 269.11645 | K82: 562.12 | L82: 46453 | M82: 9 | N82: 1839.6 | O82: =K82/N82 -> 0.30556643 | P82: =N82/K82 -> 3.2726108 | Q82: =K82/D82 -> 0.15502525 | R82: =N82/D82 -> 0.50733731 | S82: =D82-N82 -> 1786.39 | T82: =K82/M82 -> 62.457778
A83: =iferror(if(B83>0,month(B83)&"-"&year(B83),B83),) -> 1-2026 | B83: 46039 | C83: AromaTru | D83: 156 | F83: 3 | G83: 3 | H83: =F83/G83 -> 1 | I83: =D83/F83 -> 52 | J83: =I83/H83 -> 52 | K83: 9.36 | L83: 9962 | M83: 2 | N83: 0 | O83: =K83/N83 -> #DIV/0! | P83: =N83/K83 -> 0 | Q83: =K83/D83 -> 0.06 | R83: =N83/D83 -> 0 | S83: =D83-N83 -> 156 | T83: =K83/M83 -> 4.68
A84: =iferror(if(B84>0,month(B84)&"-"&year(B84),B84),) | B84: 2026 - Week 3 | D84: =SUM(D67:D83) -> 16516.22 | F84: =SUM(F67:F83) -> 201 | G84: =SUM(G67:G83) -> 230 | H84: =F84/G84 -> 0.87391304 | I84: =D84/F84 -> 82.170249 | J84: =I84/H84 -> 94.025658 | K84: =SUM(K67:K83) -> 3591.42 | L84: =SUM(L67:L83) -> 823615 | M84: =SUM(M67:M83) -> 83 | N84: =SUM(N67:N83) -> 6673.57 | O84: =K84/N84 -> 0.53815574 | P84: =N84/K84 -> 1.8581981 | Q84: =K84/D84 -> 0.21744806 | R84: =N84/D84 -> 0.40406158 | S84: =SUM(S67:S83) -> 9842.65 | T84: =K84/M84 -> 43.27012 | U84: =IFERROR((D84-#REF!)/D84,) | V84: =IFERROR((F84-#REF!)/F84,) | W84: =IFERROR((D84-#REF!)/D84, ) | X84: =IFERROR((F84-#REF!)/F84, )
B85: 46040 | C85: AirDoctor | D85: 4732.63 | F85: 44 | G85: 36 | H85: =F85/G85 -> 1.2222222 | I85: =D85/F85 -> 107.55977 | J85: =I85/H85 -> 88.00345 | K85: 718.79 | L85: 125856 | M85: 12 | N85: 1088.84 | O85: =K85/N85 -> 0.6601429 | P85: =N85/K85 -> 1.5148235 | Q85: =K85/D85 -> 0.15187961 | R85: =N85/D85 -> 0.23007081 | S85: =D85-N85 -> 3643.79 | T85: =K85/M85 -> 59.899167
C86: AquaTru | D86: 6276.96 | F86: 90 | G86: 109 | H86: =F86/G86 -> 0.82568807 | I86: =D86/F86 -> 69.744 | J86: =I86/H86 -> 84.467733 | K86: 752.9 | L86: 151124 | M86: 30 | N86: 2897.8 | O86: =K86/N86 -> 0.25981779 | P86: =N86/K86 -> 3.8488511 | Q86: =K86/D86 -> 0.1199466 | R86: =N86/D86 -> 0.4616566 | S86: =D86-N86 -> 3379.16 | T86: =K86/M86 -> 25.096667
C87: Beflexible | D87: 209.85 | F87: 3 | G87: 2 | H87: =F87/G87 -> 1.5 | I87: =D87/F87 -> 69.95 | J87: =I87/H87 -> 46.633333 | K87: 0 | L87: 295 | M87: 0 | N87: 0 | O87: =(K87/N87) -> #DIV/0! | P87: =N87/K87 -> #DIV/0! | Q87: =K87/D87 -> 0 | R87: =N87/D87 -> 0 | S87: =D87-N87 -> 209.85 | T87: =K87/M87 -> #DIV/0!
C88: Better Bladder | D88: 0 | F88: 0 | G88: 1 | H88: =F88/G88 -> 0 | I88: =D88/F88 -> #DIV/0! | J88: =I88/H88 -> #DIV/0! | K88: 398.73 | L88: 26769 | M88: 2 | N88: 119.9 | O88: =K88/N88 -> 3.3255213 | P88: =N88/K88 -> 0.30070474 | Q88: =K88/D88 -> #DIV/0! | R88: =N88/D88 -> #DIV/0! | S88: =D88-N88 -> -119.9 | T88: =K88/M88 -> 199.365
C89: Ideal Prostate | D89: 139.9 | F89: 2 | G89: 2 | H89: =F89/G89 -> 1 | I89: =D89/F89 -> 69.95 | J89: =I89/H89 -> 69.95 | K89: 62.63 | L89: 21148 | M89: 3 | N89: 179.85 | O89: =K89/N89 -> 0.34823464 | P89: =N89/K89 -> 2.871627 | Q89: =K89/D89 -> 0.44767691 | R89: =N89/D89 -> 1.2855611 | S89: =D89-N89 -> -39.95 | T89: =K89/M89 -> 20.876667
B90: to | C90: Miracle Blade | D90: 0 | F90: 0 | G90: 0 | H90: =F90/G90 -> #DIV/0! | I90: =D90/F90 -> #DIV/0! | J90: =I90/H90 -> #DIV/0! | K90: 21.15 | L90: 38434 | M90: 0 | N90: 0 | O90: =K90/N90 -> #DIV/0! | P90: =N90/K90 -> 0 | Q90: =K90/D90 -> #DIV/0! | R90: =N90/D90 -> #DIV/0! | S90: =D90-N90 -> 0 | T90: =K90/M90 -> #DIV/0!
C91: Paint Zoom | D91: 0 | F91: 0 | G91: 0 | H91: =F91/G91 -> #DIV/0! | I91: =D91/F91 -> #DIV/0! | J91: =I91/H91 -> #DIV/0! | K91: 0 | L91: 0 | M91: 0 | N91: 0 | O91: =K91/N91 -> #DIV/0! | P91: =N91/K91 -> #DIV/0! | Q91: =K91/D91 -> #DIV/0! | R91: =N91/D91 -> #DIV/0! | S91: =D91-N91 -> 0 | T91: =K91/M91 -> #DIV/0!
C92: Profemin | D92: 0 | F92: 0 | G92: 0 | H92: =F92/G92 -> #DIV/0! | I92: =D92/F92 -> #DIV/0! | J92: =I92/H92 -> #DIV/0! | K92: 0 | L92: 0 | M92: 0 | N92: 0 | O92: =K92/N92 -> #DIV/0! | P92: =N92/K92 -> #DIV/0! | Q92: =K92/D92 -> #DIV/0! | R92: =N92/D92 -> #DIV/0! | S92: =D92-N92 -> 0 | T92: =K92/M92 -> #DIV/0!
C93: Prosvent | D93: 2291.4 | F93: 33 | G93: 33 | H93: =F93/G93 -> 1 | I93: =D93/F93 -> 69.436364 | J93: =I93/H93 -> 69.436364 | K93: 421.66 | L93: 40683 | M93: 14 | N93: 829.86 | O93: =K93/N93 -> 0.5081098 | P93: =N93/K93 -> 1.9680785 | Q93: =K93/D93 -> 0.1840185 | R93: =N93/D93 -> 0.36216287 | S93: =D93-N93 -> 1461.54 | T93: =K93/M93 -> 30.118571
C94: SaniTru | D94: 159.92 | F94: 8 | G94: 3 | H94: =F94/G94 -> 2.6666667 | I94: =D94/F94 -> 19.99 | J94: =I94/H94 -> 7.49625 | K94: 367.68 | L94: 80649 | M94: 2 | N94: 39.98 | O94: =K94/N94 -> 9.1965983 | P94: =N94/K94 -> 0.10873586 | Q94: =K94/D94 -> 2.2991496 | R94: =N94/D94 -> 0.25 | S94: =D94-N94 -> 119.94 | T94: =K94/M94 -> 183.84
C95: Rotorazer Saw | D95: 1245.6 | F95: 10 | G95: 11 | H95: =F95/G95 -> 0.90909091 | I95: =D95/F95 -> 124.56 | J95: =I95/H95 -> 137.016 | K95: 46.96 | L95: 7099 | M95: 4 | N95: 205.95 | O95: =K95/N95 -> 0.22801651 | P95: =N95/K95 -> 4.3856474 | Q95: =K95/D95 -> 0.037700706 | R95: =N95/D95 -> 0.165342 | S95: =D95-N95 -> 1039.65 | T95: =K95/M95 -> 11.74
C96: Superthotics | D96: 179.85 | F96: 3 | G96: 4 | H96: =F96/G96 -> 0.75 | I96: =D96/F96 -> 59.95 | J96: =I96/H96 -> 79.933333 | K96: 66.07 | L96: 45813 | M96: 1 | N96: 59.95 | O96: =K96/N96 -> 1.1020851 | P96: =N96/K96 -> 0.90737097 | Q96: =K96/D96 -> 0.36736169 | R96: =N96/D96 -> 0.33333333 | S96: =D96-N96 -> 119.9 | T96: =K96/M96 -> 66.07
C97: Therabotanics | D97: 0 | F97: 0 | G97: 0 | H97: =F97/G97 -> #DIV/0! | I97: =D97/F97 -> #DIV/0! | J97: =I97/H97 -> #DIV/0! | K97: 0 | L97: 0 | M97: 0 | N97: 0 | O97: =K97/N97 -> #DIV/0! | P97: =N97/K97 -> #DIV/0! | Q97: =K97/D97 -> #DIV/0! | R97: =N97/D97 -> #DIV/0! | S97: =D97-N97 -> 0 | T97: =K97/M97 -> #DIV/0!
C98: WALKFIT | D98: 1186.24 | F98: 27 | G98: 29 | H98: =F98/G98 -> 0.93103448 | I98: =D98/F98 -> 43.934815 | J98: =I98/H98 -> 47.189246 | K98: 179.59 | L98: 48414 | M98: 8 | N98: 259.7 | O98: =K98/N98 -> 0.69152869 | P98: =N98/K98 -> 1.4460716 | Q98: =K98/D98 -> 0.15139432 | R98: =N98/D98 -> 0.21892703 | S98: =D98-N98 -> 926.54 | T98: =K98/M98 -> 22.44875
C99: Ultmax | D99: -29.95 | F99: -1 | G99: 0 | H99: =F99/G99 -> #DIV/0! | I99: =D99/F99 -> 29.95 | J99: =I99/H99 -> #DIV/0! | K99: 0 | L99: 0 | M99: 0 | N99: 0 | O99: =K99/N99 -> #DIV/0! | P99: =N99/K99 -> #DIV/0! | Q99: =K99/D99 -> 0 | R99: =N99/D99 -> 0 | S99: =D99-N99 -> -29.95 | T99: =K99/M99 -> #DIV/0!
C100: Ionic Pro | D100: 3931.94 | F100: 17 | G100: 20 | H100: =F100/G100 -> 0.85 | I100: =D100/F100 -> 231.29059 | J100: =I100/H100 -> 272.10657 | K100: 494 | L100: 42767 | M100: 7 | N100: 1659.65 | O100: =K100/N100 -> 0.29765312 | P100: =N100/K100 -> 3.3596154 | Q100: =K100/D100 -> 0.12563773 | R100: =N100/D100 -> 0.42209444 | S100: =D100-N100 -> 2272.29 | T100: =K100/M100 -> 70.571429
A101: =iferror(if(B101>0,month(B101)&"-"&year(B101),B101),) -> 1-2026 | B101: 46046 | C101: AromaTru | D101: 0 | F101: 0 | G101: 0 | H101: =F101/G101 -> #DIV/0! | I101: =D101/F101 -> #DIV/0! | J101: =I101/H101 -> #DIV/0! | K101: 7.9 | L101: 10033 | M101: 0 | N101: 0 | O101: =K101/N101 -> #DIV/0! | P101: =N101/K101 -> 0 | Q101: =K101/D101 -> #DIV/0! | R101: =N101/D101 -> #DIV/0! | S101: =D101-N101 -> 0 | T101: =K101/M101 -> #DIV/0!
A102: =iferror(if(B102>0,month(B102)&"-"&year(B102),B102),) | B102: 2026 - Week 4 | D102: =SUM(D85:D101) -> 20324.34 | F102: =SUM(F85:F101) -> 236 | G102: =SUM(G85:G101) -> 250 | H102: =F102/G102 -> 0.944 | I102: =D102/F102 -> 86.120085 | J102: =I102/H102 -> 91.228903 | K102: =SUM(K85:K101) -> 3538.06 | L102: =SUM(L85:L101) -> 639084 | M102: =SUM(M85:M101) -> 83 | N102: =SUM(N85:N101) -> 7341.48 | O102: =K102/N102 -> 0.48192735 | P102: =N102/K102 -> 2.0750016 | Q102: =K102/D102 -> 0.17407995 | R102: =N102/D102 -> 0.36121616 | S102: =SUM(S85:S101) -> 12982.86 | T102: =K102/M102 -> 42.627229 | U102: =IFERROR((D102-#REF!)/D102,) | V102: =IFERROR((F102-#REF!)/F102,) | W102: =IFERROR((D102-#REF!)/D102, ) | X102: =IFERROR((F102-#REF!)/F102, )
...

Sheet SEM campaigns summary + total f
A1: WALMART - DATA SOURCES: https://seller.walmart.com/analytics/overview/item-sale; https://seller.walmart.com/analytics/reports; And Intentwise
C2: WEEKLY PERFORMANCE | X2: =(#REF!+#REF!+#REF!+#REF!)-(monthly_reporting_2021!D17+monthly_reporting_2021!D23+monthly_reporting_2021!D29+monthly_reporting_2021!D35) -> #REF! | Y2: =((#REF!+#REF!+#REF!+#REF!)-(monthly_reporting_2021!E17+monthly_reporting_2021!E23+monthly_reporting_2021!E29+monthly_reporting_2021!E35))/(#REF!+#REF!+#REF!+#REF!) -> #REF!
C3: Total Sales | F3: Total Orders | K3: Total Units Sold
C4: =VLOOKUP("Current Week",$B$11:$X$268,match("SALES",$B$11:$X$11,0),FALSE) -> 24957.31 | F4: =VLOOKUP("Current Week",$B$11:$X$268,match("Units Sold",$B$11:$X$11,0),FALSE) -> 202 | K4: =VLOOKUP("Current Week",$B$11:$X$268,match("Ordered Items",$B$11:$X$11,0),FALSE) -> 220
C5: =(C4-(VLOOKUP("Previous Week",$B$11:$X$273,match("SALES",$B$11:$X$11,0),FALSE)))/C4 -> 0.10970293 | F5: =(F4-(VLOOKUP("Previous Week",$B$11:$X$273,match("Units Sold",$B$11:$X$11,0),FALSE)))/F4 -> -0.14356436 | K5: =(K4-(VLOOKUP("Previous Week",$B$11:$X$273,match("Ordered Items",$B$11:$X$11,0),FALSE)))/K4 -> -0.095454545
C7: Advertising Sales | F7: Advertising Spend | K7: ACoS
C8: =VLOOKUP("Current Week",$B$11:$X$268,match("AD SALES",$B$11:$X$11,0),FALSE) -> 21577.88 | F8: =VLOOKUP("Current Week",$B$11:$X$268,match("SP AD SPEND",$B$11:$X$11,0),FALSE) -> 8091.58 | K8: =F8/C8 -> 0.37499421
C9: =(C8-(VLOOKUP("Previous Week",$B$11:$X$273,match("AD SALES",$B$11:$X$11,0),FALSE)))/C8 -> 0.286435 | F9: =(F8-(VLOOKUP("Previous Week",$B$11:$X$273,match("SP AD SPEND",$B$11:$X$11,0),FALSE)))/F8 -> -0.0089401575 | K9: =(K8-(VLOOKUP("Previous Week",$B$11:$X$273,match("ACOS",$B$11:$X$11,0),FALSE)))/K8 -> -0.41394288
D10: SALES METRICS | L10: ADVERTISING PERFORMANCE | V10: MoM | X10: YoY
A11: Month-Code | B11: DATE | C11: BRAND | D11: SALES | E11: UNITS SOLD | F11: ORDERED ITEMS | G11: UNITS PER ORDER | H11: SALES PER ORDER | I11: ASP | J11: SP AD SPEND | K11: IMPRESSIONS | L11: UNIT SALES | M11: AD SALES | N11: ACoS | O11: ROAS (return on ad send) | P11: TACoS (Total Advertsing Cost of Sales) | Q11: REVENUE PERCENTAGE OF AD SALES | R11: ORGANIC SALES | S11: CPO | T11: SALES | U11: UNITS | V11: SALES | W11: UNITS
B13: 46012 | C13: AirDoctor | D13: 7936.51 | E13: 30 | F13: 30 | G13: =E13/F13 -> 1 | H13: =D13/E13 -> 264.55033 | I13: =H13/G13 -> 264.55033 | J13: 1654.24 | K13: 263207 | L13: 16 | M13: 4466.73 | N13: =J13/M13 -> 0.37034699 | O13: =M13/J13 -> 2.7001705 | P13: =J13/D13 -> 0.20843419 | Q13: =M13/D13 -> 0.56280783 | R13: =D13-M13 -> 3469.78 | S13: =J13/L13 -> 103.39
C14: AquaTru | D14: 19206.39 | E14: 104 | F14: 119 | G14: =E14/F14 -> 0.87394958 | H14: =D14/E14 -> 184.67683 | I14: =H14/G14 -> 211.31291 | J14: 1288.08 | K14: 442713 | L14: 37 | M14: 6713.65 | N14: =J14/M14 -> 0.19185987 | O14: =M14/J14 -> 5.2121374 | P14: =J14/D14 -> 0.06706518 | Q14: =M14/D14 -> 0.34955294 | R14: =D14-M14 -> 12492.74 | S14: =J14/L14 -> 34.812973
C15: Beflexible | D15: 0 | E15: 0 | F15: 0 | G15: =E15/F15 -> #DIV/0! | H15: =D15/E15 -> #DIV/0! | I15: =H15/G15 -> #DIV/0! | J15: 7.5 | K15: 288 | L15: 0 | M15: 0 | N15: =(J15/M15) -> #DIV/0! | O15: =M15/J15 -> 0 | P15: =J15/D15 -> #DIV/0! | Q15: =M15/D15 -> #DIV/0! | R15: =D15-M15 -> 0 | S15: =J15/L15 -> #DIV/0!
C16: Better Bladder | D16: 545.55 | E16: 9 | F16: 10 | G16: =E16/F16 -> 0.9 | H16: =D16/E16 -> 60.616667 | I16: =H16/G16 -> 67.351852 | J16: 184.21 | K16: 16259 | L16: 1 | M16: 59.95 | N16: =J16/M16 -> 3.0727273 | O16: =M16/J16 -> 0.32544379 | P16: =J16/D16 -> 0.33765924 | Q16: =M16/D16 -> 0.1098891 | R16: =D16-M16 -> 485.6 | S16: =J16/L16 -> 184.21
C17: Ideal Prostate | D17: 589.55 | E17: 9 | F17: 9 | G17: =E17/F17 -> 1 | H17: =D17/E17 -> 65.505556 | I17: =H17/G17 -> 65.505556 | J17: 52.21 | K17: 18056 | L17: 7 | M17: 479.65 | N17: =J17/M17 -> 0.1088502 | O17: =M17/J17 -> 9.1869374 | P17: =J17/D17 -> 0.08855907 | Q17: =M17/D17 -> 0.81358663 | R17: =D17-M17 -> 109.9 | S17: =J17/L17 -> 7.4585714
B18: to | C18: Miracle Blade | D18: -70.63 | E18: -2 | F18: 1 | G18: =E18/F18 -> -2 | H18: =D18/E18 -> 35.315 | I18: =H18/G18 -> -17.6575 | J18: 8.48 | K18: 697 | L18: 0 | M18: 0 | N18: =J18/M18 -> #DIV/0! | O18: =M18/J18 -> 0 | P18: =J18/D18 -> -0.1200623 | Q18: =M18/D18 -> 0 | R18: =D18-M18 -> -70.63 | S18: =J18/L18 -> #DIV/0!
C19: Paint Zoom | D19: 0 | E19: 0 | F19: 0 | G19: =E19/F19 -> #DIV/0! | H19: =D19/E19 -> #DIV/0! | I19: =H19/G19 -> #DIV/0! | J19: 0 | K19: 0 | L19: 0 | M19: 0 | N19: =J19/M19 -> #DIV/0! | O19: =M19/J19 -> #DIV/0! | P19: =J19/D19 -> #DIV/0! | Q19: =M19/D19 -> #DIV/0! | R19: =D19-M19 -> 0 | S19: =J19/L19 -> #DIV/0!
C20: Profemin | D20: 0 | E20: 0 | F20: 0 | G20: =E20/F20 -> #DIV/0! | H20: =D20/E20 -> #DIV/0! | I20: =H20/G20 -> #DIV/0! | J20: 0 | K20: 0 | L20: 0 | M20: 0 | N20: =J20/M20 -> #DIV/0! | O20: =M20/J20 -> #DIV/0! | P20: =J20/D20 -> #DIV/0! | Q20: =M20/D20 -> #DIV/0! | R20: =D20-M20 -> 0 | S20: =J20/L20 -> #DIV/0!
C21: Prosvent | D21: 2629.8 | E21: 29 | F21: 28 | G21: =E21/F21 -> 1.0357143 | H21: =D21/E21 -> 90.682759 | I21: =H21/G21 -> 87.555767 | J21: 668.15 | K21: 36463 | L21: 17 | M21: 1466.87 | N21: =J21/M21 -> 0.45549367 | O21: =M21/J21 -> 2.1954202 | P21: =J21/D21 -> 0.25406875 | Q21: =M21/D21 -> 0.55778766 | R21: =D21-M21 -> 1162.93 | S21: =J21/L21 -> 39.302941
C22: SaniTru | D22: 59.97 | E22: 3 | F22: 4 | G22: =E22/F22 -> 0.75 | H22: =D22/E22 -> 19.99 | I22: =H22/G22 -> 26.653333 | J22: 136.24 | K22: 47577 | L22: 2 | M22: 39.98 | N22: =J22/M22 -> 3.4077039 | O22: =M22/J22 -> 0.29345273 | P22: =J22/D22 -> 2.2718026 | Q22: =M22/D22 -> 0.66666667 | R22: =D22-M22 -> 19.99 | S22: =J22/L22 -> 68.12
C23: Rotorazer Saw | D23: 78.59 | E23: 0 | F23: 2 | G23: =E23/F23 -> 0 | H23: =D23/E23 -> #DIV/0! | I23: =H23/G23 -> #DIV/0! | J23: 36.36 | K23: 10972 | L23: 1 | M23: 154.46 | N23: =J23/M23 -> 0.23540075 | O23: =M23/J23 -> 4.2480748 | P23: =J23/D23 -> 0.46265428 | Q23: =M23/D23 -> 1.96539 | R23: =D23-M23 -> -75.87 | S23: =J23/L23 -> 36.36
C24: Superthotics | D24: 190.8 | E24: 4 | F24: 4 | G24: =E24/F24 -> 1 | H24: =D24/E24 -> 47.7 | I24: =H24/G24 -> 47.7 | J24: 80.52 | K24: 40401 | L24: 3 | M24: 134.85 | N24: =J24/M24 -> 0.5971079 | O24: =M24/J24 -> 1.6747392 | P24: =J24/D24 -> 0.42201258 | Q24: =M24/D24 -> 0.70676101 | R24: =D24-M24 -> 55.95 | S24: =J24/L24 -> 26.84
C25: Therabotanics | D25: 0 | E25: 0 | F25: 0 | G25: =E25/F25 -> #DIV/0! | H25: =D25/E25 -> #DIV/0! | I25: =H25/G25 -> #DIV/0! | J25: 0 | K25: 0 | L25: 0 | M25: 0 | N25: =J25/M25 -> #DIV/0! | O25: =M25/J25 -> #DIV/0! | P25: =J25/D25 -> #DIV/0! | Q25: =M25/D25 -> #DIV/0! | R25: =D25-M25 -> 0 | S25: =J25/L25 -> #DIV/0!
C26: WALKFIT | D26: 1312.67 | E26: 34 | F26: 31 | G26: =E26/F26 -> 1.0967742 | H26: =D26/E26 -> 38.607941 | I26: =H26/G26 -> 35.201358 | J26: 269.35 | K26: 50705 | L26: 13 | M26: 403.73 | N26: =J26/M26 -> 0.66715379 | O26: =M26/J26 -> 1.4989048 | P26: =J26/D26 -> 0.20519247 | Q26: =M26/D26 -> 0.30756397 | R26: =D26-M26 -> 908.94 | S26: =J26/L26 -> 20.719231
C27: Ultmax | D27: -29.95 | E27: -1 | F27: 0 | G27: =E27/F27 -> #DIV/0! | H27: =D27/E27 -> 29.95 | I27: =H27/G27 -> #DIV/0! | J27: 0 | K27: 0 | L27: 0 | M27: 0 | N27: =J27/M27 -> #DIV/0! | O27: =M27/J27 -> #DIV/0! | P27: =J27/D27 -> 0 | Q27: =M27/D27 -> 0 | R27: =D27-M27 -> -29.95 | S27: =J27/L27 -> #DIV/0!
C28: Ionic Pro | D28: 4625.06 | E28: 26 | F28: 28 | G28: =E28/F28 -> 0.92857143 | H28: =D28/E28 -> 177.88692 | I28: =H28/G28 -> 191.57053 | J28: 692.49 | K28: 44157 | L28: 11 | M28: 1670.89 | N28: =J28/M28 -> 0.4144438 | O28: =M28/J28 -> 2.4128724 | P28: =J28/D28 -> 0.14972563 | Q28: =M28/D28 -> 0.36126883 | R28: =D28-M28 -> 2954.17 | S28: =J28/L28 -> 62.953636
C29: AromaTru | D29: 0 | E29: 0 | F29: 0 | G29: =E29/F29 -> #DIV/0! | H29: =D29/E29 -> #DIV/0! | I29: =H29/G29 -> #DIV/0! | J29: 16.97 | K29: 17393 | L29: 0 | M29: 0 | N29: =J29/M29 -> #DIV/0! | O29: =M29/J29 -> 0 | P29: =J29/D29 -> #DIV/0! | Q29: =M29/D29 -> #DIV/0! | R29: =D29-M29 -> 0 | S29: =J29/L29 -> #DIV/0!
A30: =iferror(if(B30>0,month(B30)&"-"&year(B30),B30),) -> 12-2025 | B30: 46018 | C30: SEM Campaigns | D30: 0 | E30: 0 | F30: 0 | G30: =E30/F30 -> #DIV/0! | H30: =D30/E30 -> #DIV/0! | I30: =H30/G30 -> #DIV/0! | J30: 6654.44 | K30: 465451 | L30: 0 | M30: 18889.62 | N30: =J30/M30 -> 0.35228025 | O30: =M30/J30 -> 2.8386491 | P30: =J30/D30 -> #DIV/0! | Q30: =M30/D30 -> #DIV/0! | R30: =D30-M30 -> -18889.62 | S30: =J30/L30 -> #DIV/0!
A31: =iferror(if(B31>0,month(B31)&"-"&year(B31),B31),) | B31: 2025 - Week 52 | D31: =SUM(D13:D30) -> 37074.31 | E31: =SUM(E13:E30) -> 245 | F31: =SUM(F13:F30) -> 266 | G31: =E31/F31 -> 0.92105263 | H31: =D31/E31 -> 151.32371 | I31: =H31/G31 -> 164.29432 | J31: =SUM(J13:J30) -> 11749.24 | K31: =SUM(K13:K30) -> 1454339 | L31: =SUM(L13:L30) -> 108 | M31: =SUM(M13:M30) -> 34480.38 | N31: =J31/M31 -> 0.34075146 | O31: =M31/J31 -> 2.9346902 | P31: =J31/D31 -> 0.31691055 | Q31: =M31/D31 -> 0.9300343 | R31: =SUM(R13:R30) -> 2593.93 | S31: =J31/L31 -> 108.78926 | T31: =IFERROR((D31-#REF!)/D31,) | U31: =IFERROR((E31-#REF!)/E31,) | V31: =IFERROR((D31-#REF!)/D31, ) | W31: =IFERROR((E31-#REF!)/E31, )
B32: 46019 | C32: AirDoctor | D32: 13519.5 | E32: 57 | F32: 57 | G32: =E32/F32 -> 1 | H32: =D32/E32 -> 237.18421 | I32: =H32/G32 -> 237.18421 | J32: 1867.63 | K32: 249548 | L32: 23 | M32: 5019.44 | N32: =J32/M32 -> 0.37207936 | O32: =M32/J32 -> 2.6875987 | P32: =J32/D32 -> 0.13814342 | Q32: =M32/D32 -> 0.37127409 | R32: =D32-M32 -> 8500.06 | S32: =J32/L32 -> 81.201304
C33: AquaTru | D33: 18767.79 | E33: 145 | F33: 161 | G33: =E33/F33 -> 0.90062112 | H33: =D33/E33 -> 129.43303 | I33: =H33/G33 -> 143.7153 | J33: 1072.07 | K33: 465644 | L33: 32 | M33: 3923.85 | N33: =J33/M33 -> 0.2732189 | O33: =M33/J33 -> 3.6600688 | P33: =J33/D33 -> 0.057122868 | Q33: =M33/D33 -> 0.20907363 | R33: =D33-M33 -> 14843.94 | S33: =J33/L33 -> 33.502187
C34: Beflexible | D34: 0 | E34: 0 | F34: 0 | G34: =E34/F34 -> #DIV/0! | H34: =D34/E34 -> #DIV/0! | I34: =H34/G34 -> #DIV/0! | J34: 0 | K34: 376 | L34: 0 | M34: 0 | N34: =(J34/M34) -> #DIV/0! | O34: =M34/J34 -> #DIV/0! | P34: =J34/D34 -> #DIV/0! | Q34: =M34/D34 -> #DIV/0! | R34: =D34-M34 -> 0 | S34: =J34/L34 -> #DIV/0!
C35: Better Bladder | D35: 125.9 | E35: 2 | F35: 2 | G35: =E35/F35 -> 1 | H35: =D35/E35 -> 62.95 | I35: =H35/G35 -> 62.95 | J35: 298.8 | K35: 26455 | L35: 5 | M35: 299.75 | N35: =J35/M35 -> 0.99683069 | O35: =M35/J35 -> 1.0031794 | P35: =J35/D35 -> 2.3733122 | Q35: =M35/D35 -> 2.3808578 | R35: =D35-M35 -> -173.85 | S35: =J35/L35 -> 59.76
C36: Ideal Prostate | D36: 359.7 | E36: 6 | F36: 6 | G36: =E36/F36 -> 1 | H36: =D36/E36 -> 59.95 | I36: =H36/G36 -> 59.95 | J36: 105.72 | K36: 27117 | L36: 2 | M36: 129.9 | N36: =J36/M36 -> 0.81385681 | O36: =M36/J36 -> 1.2287174 | P36: =J36/D36 -> 0.29391159 | Q36: =M36/D36 -> 0.36113428 | R36: =D36-M36 -> 229.8 | S36: =J36/L36 -> 52.86
B37: to | C37: Miracle Blade | D37: -60.73 | E37: 0 | F37: 1 | G37: =E37/F37 -> 0 | H37: =D37/E37 -> #DIV/0! | I37: =H37/G37 -> #DIV/0! | J37: 83.88 | K37: 253679 | L37: 0 | M37: 0 | N37: =J37/M37 -> #DIV/0! | O37: =M37/J37 -> 0 | P37: =J37/D37 -> -1.3811955 | Q37: =M37/D37 -> 0 | R37: =D37-M37 -> -60.73 | S37: =J37/L37 -> #DIV/0!
C38: Paint Zoom | D38: 0 | E38: 0 | F38: 0 | G38: =E38/F38 -> #DIV/0! | H38: =D38/E38 -> #DIV/0! | I38: =H38/G38 -> #DIV/0! | J38: 0 | K38: 0 | L38: 0 | M38: 0 | N38: =J38/M38 -> #DIV/0! | O38: =M38/J38 -> #DIV/0! | P38: =J38/D38 -> #DIV/0! | Q38: =M38/D38 -> #DIV/0! | R38: =D38-M38 -> 0 | S38: =J38/L38 -> #DIV/0!
C39: Profemin | D39: 0 | E39: 0 | F39: 0 | G39: =E39/F39 -> #DIV/0! | H39: =D39/E39 -> #DIV/0! | I39: =H39/G39 -> #DIV/0! | J39: 0 | K39: 0 | L39: 0 | M39: 0 | N39: =J39/M39 -> #DIV/0! | O39: =M39/J39 -> #DIV/0! | P39: =J39/D39 -> #DIV/0! | Q39: =M39/D39 -> #DIV/0! | R39: =D39-M39 -> 0 | S39: =J39/L39 -> #DIV/0!
C40: Prosvent | D40: 3534.27 | E40: 49 | F40: 51 | G40: =E40/F40 -> 0.96078431 | H40: =D40/E40 -> 72.127959 | I40: =H40/G40 -> 75.071958 | J40: 799.06 | K40: 59789 | L40: 14 | M40: 877.86 | N40: =J40/M40 -> 0.91023626 | O40: =M40/J40 -> 1.0986159 | P40: =J40/D40 -> 0.22608912 | Q40: =M40/D40 -> 0.2483851 | R40: =D40-M40 -> 2656.41 | S40: =J40/L40 -> 57.075714
C41: SaniTru | D41: 59.97 | E41: 3 | F41: 3 | G41: =E41/F41 -> 1 | H41: =D41/E41 -> 19.99 | I41: =H41/G41 -> 19.99 | J41: 356.37 | K41: 105893 | L41: 2 | M41: 39.98 | N41: =J41/M41 -> 8.9137069 | O41: =M41/J41 -> 0.11218677 | P41: =J41/D41 -> 5.9424712 | Q41: =M41/D41 -> 0.66666667 | R41: =D41-M41 -> 19.99 | S41: =J41/L41 -> 178.185
C42: Rotorazer Saw | D42: 1547.97 | E42: 13 | F42: 13 | G42: =E42/F42 -> 1 | H42: =D42/E42 -> 119.07462 | I42: =H42/G42 -> 119.07462 | J42: 74.14 | K42: 10788 | L42: 1 | M42: 0 | N42: =J42/M42 -> #DIV/0! | O42: =M42/J42 -> 0 | P42: =J42/D42 -> 0.047894985 | Q42: =M42/D42 -> 0 | R42: =D42-M42 -> 1547.97 | S42: =J42/L42 -> 74.14
C43: Superthotics | D43: 209.8 | E43: 4 | F43: 4 | G43: =E43/F43 -> 1 | H43: =D43/E43 -> 52.45 | I43: =H43/G43 -> 52.45 | J43: 72.7 | K43: 40190 | L43: 3 | M43: 164.85 | N43: =J43/M43 -> 0.44100698 | O43: =M43/J43 -> 2.2675378 | P43: =J43/D43 -> 0.3465205 | Q43: =M43/D43 -> 0.78574833 | R43: =D43-M43 -> 44.95 | S43: =J43/L43 -> 24.233333
C44: Therabotanics | D44: 0 | E44: 0 | F44: 0 | G44: =E44/F44 -> #DIV/0! | H44: =D44/E44 -> #DIV/0! | I44: =H44/G44 -> #DIV/0! | J44: 0 | K44: 0 | L44: 0 | M44: 0 | N44: =J44/M44 -> #DIV/0! | O44: =M44/J44 -> #DIV/0! | P44: =J44/D44 -> #DIV/0! | Q44: =M44/D44 -> #DIV/0! | R44: =D44-M44 -> 0 | S44: =J44/L44 -> #DIV/0!
C45: WALKFIT | D45: 1218.39 | E45: 31 | F45: 31 | G45: =E45/F45 -> 1 | H45: =D45/E45 -> 39.302903 | I45: =H45/G45 -> 39.302903 | J45: 258.05 | K45: 66414 | L45: 25 | M45: 985.26 | N45: =J45/M45 -> 0.26191056 | O45: =M45/J45 -> 3.8180973 | P45: =J45/D45 -> 0.21179589 | Q45: =M45/D45 -> 0.80865733 | R45: =D45-M45 -> 233.13 | S45: =J45/L45 -> 10.322
C46: Ultmax | D46: 59.9 | E46: 2 | F46: 2 | G46: =E46/F46 -> 1 | H46: =D46/E46 -> 29.95 | I46: =H46/G46 -> 29.95 | J46: 0 | K46: 0 | L46: 0 | M46: 0 | N46: =J46/M46 -> #DIV/0! | O46: =M46/J46 -> #DIV/0! | P46: =J46/D46 -> 0 | Q46: =M46/D46 -> 0 | R46: =D46-M46 -> 59.9 | S46: =J46/L46 -> #DIV/0!
C47: Ionic Pro | D47: 6535.42 | E47: 31 | F47: 31 | G47: =E47/F47 -> 1 | H47: =D47/E47 -> 210.82 | I47: =H47/G47 -> 210.82 | J47: 807.83 | K47: 55281 | L47: 15 | M47: 2922.51 | N47: =J47/M47 -> 0.2764165 | O47: =M47/J47 -> 3.617729 | P47: =J47/D47 -> 0.12360797 | Q47: =M47/D47 -> 0.44718014 | R47: =D47-M47 -> 3612.91 | S47: =J47/L47 -> 53.855333
C48: AromaTru | D48: -27 | E48: -1 | F48: 0 | G48: =E48/F48 -> #DIV/0! | H48: =D48/E48 -> 27 | I48: =H48/G48 -> #DIV/0! | J48: 10.46 | K48: 14576 | L48: 0 | M48: 0 | N48: =J48/M48 -> #DIV/0! | O48: =M48/J48 -> 0 | P48: =J48/D48 -> -0.38740741 | Q48: =M48/D48 -> 0 | R48: =D48-M48 -> -27 | S48: =J48/L48 -> #DIV/0!
A49: =iferror(if(B49>0,month(B49)&"-"&year(B49),B49),) -> 1-2026 | B49: 46025 | C49: SEM Campaigns | D49: 0 | E49: 0 | F49: 0 | G49: =E49/F49 -> #DIV/0! | H49: =D49/E49 -> #DIV/0! | I49: =H49/G49 -> #DIV/0! | J49: 4879.89 | K49: 507182 | L49: 0 | M49: 18214 | N49: =J49/M49 -> 0.26791973 | O49: =M49/J49 -> 3.7324612 | P49: =J49/D49 -> #DIV/0! | Q49: =M49/D49 -> #DIV/0! | R49: =D49-M49 -> -18214 | S49: =J49/L49 -> #DIV/0!
A50: =iferror(if(B50>0,month(B50)&"-"&year(B50),B50),) | B50: 2026 - Week 1 | D50: =SUM(D32:D49) -> 45850.88 | E50: =SUM(E32:E49) -> 342 | F50: =SUM(F32:F49) -> 362 | G50: =E50/F50 -> 0.94475138 | H50: =D50/E50 -> 134.0669 | I50: =H50/G50 -> 141.90707 | J50: =SUM(J32:J49) -> 10686.6 | K50: =SUM(K32:K49) -> 1882932 | L50: =SUM(L32:L49) -> 122 | M50: =SUM(M32:M49) -> 32577.4 | N50: =J50/M50 -> 0.32803723 | O50: =M50/J50 -> 3.0484345 | P50: =J50/D50 -> 0.23307295 | Q50: =M50/D50 -> 0.71050763 | R50: =SUM(R32:R49) -> 13273.48 | S50: =J50/L50 -> 87.595082 | T50: =IFERROR((D50-#REF!)/D50,) | U50: =IFERROR((E50-#REF!)/E50,) | V50: =IFERROR((D50-#REF!)/D50, ) | W50: =IFERROR((E50-#REF!)/E50, )
B51: 46026 | C51: AirDoctor | D51: 4193.34 | E51: 31 | F51: 31 | G51: =E51/F51 -> 1 | H51: =D51/E51 -> 135.26903 | I51: =H51/G51 -> 135.26903 | J51: 1013.35 | K51: 165235 | L51: 6 | M51: 925.9 | N51: =J51/M51 -> 1.0944486 | O51: =M51/J51 -> 0.91370208 | P51: =J51/D51 -> 0.24165701 | Q51: =M51/D51 -> 0.22080251 | R51: =D51-M51 -> 3267.44 | S51: =J51/L51 -> 168.89167
C52: AquaTru | D52: 7722.36 | E52: 94 | F52: 105 | G52: =E52/F52 -> 0.8952381 | H52: =D52/E52 -> 82.152766 | I52: =H52/G52 -> 91.766388 | J52: 759.35 | K52: 402437 | L52: 21 | M52: 2698.5 | N52: =J52/M52 -> 0.28139707 | O52: =M52/J52 -> 3.5536972 | P52: =J52/D52 -> 0.098331339 | Q52: =M52/D52 -> 0.34943981 | R52: =D52-M52 -> 5023.86 | S52: =J52/L52 -> 36.159524
C53: Beflexible | D53: 279.8 | E53: 4 | F53: 2 | G53: =E53/F53 -> 2 | H53: =D53/E53 -> 69.95 | I53: =H53/G53 -> 34.975 | J53: 7.22 | K53: 413 | L53: 0 | M53: 0 | N53: =(J53/M53) -> #DIV/0! | O53: =M53/J53 -> 0 | P53: =J53/D53 -> 0.025804146 | Q53: =M53/D53 -> 0 | R53: =D53-M53 -> 279.8 | S53: =J53/L53 -> #DIV/0!
C54: Better Bladder | D54: 1085.11 | E54: 18 | F54: 22 | G54: =E54/F54 -> 0.81818182 | H54: =D54/E54 -> 60.283889 | I54: =H54/G54 -> 73.680309 | J54: 317.55 | K54: 27416 | L54: 12 | M54: 659.45 | N54: =J54/M54 -> 0.48153765 | O54: =M54/J54 -> 2.0766808 | P54: =J54/D54 -> 0.29264314 | Q54: =M54/D54 -> 0.60772641 | R54: =D54-M54 -> 425.66 | S54: =J54/L54 -> 26.4625
C55: Ideal Prostate | D55: 974.25 | E55: 15 | F55: 16 | G55: =E55/F55 -> 0.9375 | H55: =D55/E55 -> 64.95 | I55: =H55/G55 -> 69.28 | J55: 78.8 | K55: 26820 | L55: 1 | M55: 69.95 | N55: =J55/M55 -> 1.1265189 | O55: =M55/J55 -> 0.88769036 | P55: =J55/D55 -> 0.08088273 | Q55: =M55/D55 -> 0.07179882 | R55: =D55-M55 -> 904.3 | S55: =J55/L55 -> 78.8
B56: to | C56: Miracle Blade | D56: 114.85 | E56: 3 | F56: 3 | G56: =E56/F56 -> 1 | H56: =D56/E56 -> 38.283333 | I56: =H56/G56 -> 38.283333 | J56: 40.77 | K56: 241677 | L56: 0 | M56: 0 | N56: =J56/M56 -> #DIV/0! | O56: =M56/J56 -> 0 | P56: =J56/D56 -> 0.35498476 | Q56: =M56/D56 -> 0 | R56: =D56-M56 -> 114.85 | S56: =J56/L56 -> #DIV/0!
C57: Paint Zoom | D57: 0 | E57: 0 | F57: 0 | G57: =E57/F57 -> #DIV/0! | H57: =D57/E57 -> #DIV/0! | I57: =H57/G57 -> #DIV/0! | J57: 0 | K57: 0 | L57: 0 | M57: 0 | N57: =J57/M57 -> #DIV/0! | O57: =M57/J57 -> #DIV/0! | P57: =J57/D57 -> #DIV/0! | Q57: =M57/D57 -> #DIV/0! | R57: =D57-M57 -> 0 | S57: =J57/L57 -> #DIV/0!
C58: Profemin | D58: 0 | E58: 0 | F58: 0 | G58: =E58/F58 -> #DIV/0! | H58: =D58/E58 -> #DIV/0! | I58: =H58/G58 -> #DIV/0! | J58: 0 | K58: 0 | L58: 0 | M58: 0 | N58: =J58/M58 -> #DIV/0! | O58: =M58/J58 -> #DIV/0! | P58: =J58/D58 -> #DIV/0! | Q58: =M58/D58 -> #DIV/0! | R58: =D58-M58 -> 0 | S58: =J58/L58 -> #DIV/0!
C59: Prosvent | D59: 2607.66 | E59: 38 | F59: 37 | G59: =E59/F59 -> 1.027027 | H59: =D59/E59 -> 68.622632 | I59: =H59/G59 -> 66.816773 | J59: 582.07 | K59: 53074 | L59: 14 | M59: 1068.9 | N59: =J59/M59 -> 0.54455047 | O59: =M59/J59 -> 1.8363771 | P59: =J59/D59 -> 0.22321545 | Q59: =M59/D59 -> 0.40990773 | R59: =D59-M59 -> 1538.76 | S59: =J59/L59 -> 41.576429
C60: SaniTru | D60: 39.98 | E60: 2 | F60: 5 | G60: =E60/F60 -> 0.4 | H60: =D60/E60 -> 19.99 | I60: =H60/G60 -> 49.975 | J60: 390.2 | K60: 90636 | L60: 5 | M60: 99.95 | N60: =J60/M60 -> 3.903952 | O60: =M60/J60 -> 0.25615069 | P60: =J60/D60 -> 9.7598799 | Q60: =M60/D60 -> 2.5 | R60: =D60-M60 -> -59.97 | S60: =J60/L60 -> 78.04
C61: Rotorazer Saw | D61: 1285.59 | E61: 10 | F61: 10 | G61: =E61/F61 -> 1 | H61: =D61/E61 -> 128.559 | I61: =H61/G61 -> 128.559 | J61: 70.1 | K61: 8798 | L61: 1 | M61: 0 | N61: =J61/M61 -> #DIV/0! | O61: =M61/J61 -> 0 | P61: =J61/D61 -> 0.054527493 | Q61: =M61/D61 -> 0 | R61: =D61-M61 -> 1285.59 | S61: =J61/L61 -> 70.1
C62: Superthotics | D62: 134.9 | E62: 2 | F62: 3 | G62: =E62/F62 -> 0.66666667 | H62: =D62/E62 -> 67.45 | I62: =H62/G62 -> 101.175 | J62: 79.11 | K62: 52026 | L62: 2 | M62: 119.9 | N62: =J62/M62 -> 0.65979983 | O62: =M62/J62 -> 1.5156112 | P62: =J62/D62 -> 0.5864344 | Q62: =M62/D62 -> 0.88880652 | R62: =D62-M62 -> 15 | S62: =J62/L62 -> 39.555
C63: Therabotanics | D63: 49.9 | E63: 2 | F63: 3 | G63: =E63/F63 -> 0.66666667 | H63: =D63/E63 -> 24.95 | I63: =H63/G63 -> 37.425 | J63: 0 | K63: 0 | L63: 0 | M63: 0 | N63: =J63/M63 -> #DIV/0! | O63: =M63/J63 -> #DIV/0! | P63: =J63/D63 -> 0 | Q63: =M63/D63 -> 0 | R63: =D63-M63 -> 49.9 | S63: =J63/L63 -> #DIV/0!
C64: WALKFIT | D64: 922.7 | E64: 21 | F64: 25 | G64: =E64/F64 -> 0.84 | H64: =D64/E64 -> 43.938095 | I64: =H64/G64 -> 52.307256 | J64: 240.22 | K64: 70753 | L64: 9 | M64: 306.65 | N64: =J64/M64 -> 0.78336866 | O64: =M64/J64 -> 1.2765382 | P64: =J64/D64 -> 0.26034464 | Q64: =M64/D64 -> 0.33233987 | R64: =D64-M64 -> 616.05 | S64: =J64/L64 -> 26.691111
C65: Ultmax | D65: 99.25 | E65: 5 | F65: 3 | G65: =E65/F65 -> 1.6666667 | H65: =D65/E65 -> 19.85 | I65: =H65/G65 -> 11.91 | J65: 0 | K65: 0 | L65: 0 | M65: 0 | N65: =J65/M65 -> #DIV/0! | O65: =M65/J65 -> #DIV/0! | P65: =J65/D65 -> 0 | Q65: =M65/D65 -> 0 | R65: =D65-M65 -> 99.25 | S65: =J65/L65 -> #DIV/0!
C66: Ionic Pro | D66: 4039.1 | E66: 18 | F66: 18 | G66: =E66/F66 -> 1 | H66: =D66/E66 -> 224.39444 | I66: =H66/G66 -> 224.39444 | J66: 573.49 | K66: 48071 | L66: 8 | M66: 1459.65 | N66: =J66/M66 -> 0.39289556 | O66: =M66/J66 -> 2.5452057 | P66: =J66/D66 -> 0.1419846 | Q66: =M66/D66 -> 0.36138001 | R66: =D66-M66 -> 2579.45 | S66: =J66/L66 -> 71.68625
C67: AromaTru | D67: 0 | E67: 0 | F67: 0 | G67: =E67/F67 -> #DIV/0! | H67: =D67/E67 -> #DIV/0! | I67: =H67/G67 -> #DIV/0! | J67: 16.26 | K67: 10972 | L67: 0 | M67: 0 | N67: =J67/M67 -> #DIV/0! | O67: =M67/J67 -> 0 | P67: =J67/D67 -> #DIV/0! | Q67: =M67/D67 -> #DIV/0! | R67: =D67-M67 -> 0 | S67: =J67/L67 -> #DIV/0!
A68: =iferror(if(B68>0,month(B68)&"-"&year(B68),B68),) -> 1-2026 | B68: 46032 | C68: SEM Campaigns | D68: 0 | E68: 0 | F68: 0 | G68: =E68/F68 -> #DIV/0! | H68: =D68/E68 -> #DIV/0! | I68: =H68/G68 -> #DIV/0! | J68: 3928.22 | K68: 378860 | L68: 0 | M68: 9667.5 | N68: =J68/M68 -> 0.40633256 | O68: =M68/J68 -> 2.4610383 | P68: =J68/D68 -> #DIV/0! | Q68: =M68/D68 -> #DIV/0! | R68: =D68-M68 -> -9667.5 | S68: =J68/L68 -> #DIV/0!
A69: =iferror(if(B69>0,month(B69)&"-"&year(B69),B69),) | B69: 2026 - Week 2 | D69: =SUM(D51:D68) -> 23548.79 | E69: =SUM(E51:E68) -> 263 | F69: =SUM(F51:F68) -> 283 | G69: =E69/F69 -> 0.92932862 | H69: =D69/E69 -> 89.539125 | I69: =H69/G69 -> 96.348184 | J69: =SUM(J51:J68) -> 8096.71 | K69: =SUM(K51:K68) -> 1577188 | L69: =SUM(L51:L68) -> 79 | M69: =SUM(M51:M68) -> 17076.35 | N69: =J69/M69 -> 0.47414758 | O69: =M69/J69 -> 2.109048 | P69: =J69/D69 -> 0.34382701 | Q69: =M69/D69 -> 0.72514766 | R69: =SUM(R51:R68) -> 6472.44 | S69: =J69/L69 -> 102.49 | T69: =IFERROR((D69-#REF!)/D69,) | U69: =IFERROR((E69-#REF!)/E69,) | V69: =IFERROR((D69-#REF!)/D69, ) | W69: =IFERROR((E69-#REF!)/E69, )
B70: 46033 | C70: AirDoctor | D70: 2300.92 | E70: 23 | F70: 28 | G70: =E70/F70 -> 0.82142857 | H70: =D70/E70 -> 100.04 | I70: =H70/G70 -> 121.78783 | J70: 623.32 | K70: 111636 | L70: 6 | M70: 204.9 | N70: =J70/M70 -> 3.0420693 | O70: =M70/J70 -> 0.32872361 | P70: =J70/D70 -> 0.27090034 | Q70: =M70/D70 -> 0.089051336 | R70: =D70-M70 -> 2096.02 | S70: =J70/L70 -> 103.88667
C71: AquaTru | D71: 4373.42 | E71: 63 | F71: 82 | G71: =E71/F71 -> 0.76829268 | H71: =D71/E71 -> 69.419365 | I71: =H71/G71 -> 90.355364 | J71: 822.42 | K71: 169878 | L71: 29 | M71: 2624.25 | N71: =J71/M71 -> 0.3133924 | O71: =M71/J71 -> 3.1908879 | P71: =J71/D71 -> 0.18804963 | Q71: =M71/D71 -> 0.60004527 | R71: =D71-M71 -> 1749.17 | S71: =J71/L71 -> 28.35931
C72: Beflexible | D72: 419.7 | E72: 6 | F72: 3 | G72: =E72/F72 -> 2 | H72: =D72/E72 -> 69.95 | I72: =H72/G72 -> 34.975 | J72: 7.22 | K72: 318 | L72: 0 | M72: 0 | N72: =(J72/M72) -> #DIV/0! | O72: =M72/J72 -> 0 | P72: =J72/D72 -> 0.017202764 | Q72: =M72/D72 -> 0 | R72: =D72-M72 -> 419.7 | S72: =J72/L72 -> #DIV/0!
C73: Better Bladder | D73: 188.85 | E73: 3 | F73: 3 | G73: =E73/F73 -> 1 | H73: =D73/E73 -> 62.95 | I73: =H73/G73 -> 62.95 | J73: 313.22 | K73: 27042 | L73: 7 | M73: 419.65 | N73: =J73/M73 -> 0.74638389 | O73: =M73/J73 -> 1.3397931 | P73: =J73/D73 -> 1.658565 | Q73: =M73/D73 -> 2.222134 | R73: =D73-M73 -> -230.8 | S73: =J73/L73 -> 44.745714
C74: Ideal Prostate | D74: 1139.1 | E74: 18 | F74: 17 | G74: =E74/F74 -> 1.0588235 | H74: =D74/E74 -> 63.283333 | I74: =H74/G74 -> 59.767593 | J74: 73.93 | K74: 23474 | L74: 6 | M74: 389.7 | N74: =J74/M74 -> 0.18971003 | O74: =M74/J74 -> 5.2712025 | P74: =J74/D74 -> 0.064902116 | Q74: =M74/D74 -> 0.34211219 | R74: =D74-M74 -> 749.4 | S74: =J74/L74 -> 12.321667
B75: to | C75: Miracle Blade | D75: 0 | E75: 0 | F75: 0 | G75: =E75/F75 -> #DIV/0! | H75: =D75/E75 -> #DIV/0! | I75: =H75/G75 -> #DIV/0! | J75: 24.92 | K75: 189436 | L75: 0 | M75: 0 | N75: =J75/M75 -> #DIV/0! | O75: =M75/J75 -> 0 | P75: =J75/D75 -> #DIV/0! | Q75: =M75/D75 -> #DIV/0! | R75: =D75-M75 -> 0 | S75: =J75/L75 -> #DIV/0!
C76: Paint Zoom | D76: 0 | E76: 0 | F76: 0 | G76: =E76/F76 -> #DIV/0! | H76: =D76/E76 -> #DIV/0! | I76: =H76/G76 -> #DIV/0! | J76: 0 | K76: 0 | L76: 0 | M76: 0 | N76: =J76/M76 -> #DIV/0! | O76: =M76/J76 -> #DIV/0! | P76: =J76/D76 -> #DIV/0! | Q76: =M76/D76 -> #DIV/0! | R76: =D76-M76 -> 0 | S76: =J76/L76 -> #DIV/0!
C77: Profemin | D77: 0 | E77: 0 | F77: 0 | G77: =E77/F77 -> #DIV/0! | H77: =D77/E77 -> #DIV/0! | I77: =H77/G77 -> #DIV/0! | J77: 0 | K77: 0 | L77: 0 | M77: 0 | N77: =J77/M77 -> #DIV/0! | O77: =M77/J77 -> #DIV/0! | P77: =J77/D77 -> #DIV/0! | Q77: =M77/D77 -> #DIV/0! | R77: =D77-M77 -> 0 | S77: =J77/L77 -> #DIV/0!
C78: Prosvent | D78: 2585.66 | E78: 38 | F78: 37 | G78: =E78/F78 -> 1.027027 | H78: =D78/E78 -> 68.043684 | I78: =H78/G78 -> 66.253061 | J78: 439.15 | K78: 48219 | L78: 11 | M78: 718.93 | N78: =J78/M78 -> 0.61083833 | O78: =M78/J78 -> 1.6370944 | P78: =J78/D78 -> 0.16984058 | Q78: =M78/D78 -> 0.27804506 | R78: =D78-M78 -> 1866.73 | S78: =J78/L78 -> 39.922727
C79: SaniTru | D79: 39.98 | E79: 2 | F79: 3 | G79: =E79/F79 -> 0.66666667 | H79: =D79/E79 -> 19.99 | I79: =H79/G79 -> 29.985 | J79: 315.74 | K79: 83987 | L79: 1 | M79: 19.99 | N79: =J79/M79 -> 15.794897 | O79: =M79/J79 -> 0.063311585 | P79: =J79/D79 -> 7.8974487 | Q79: =M79/D79 -> 0.5 | R79: =D79-M79 -> 19.99 | S79: =J79/L79 -> 315.74
C80: Rotorazer Saw | D80: 599.8 | E80: 5 | F80: 6 | G80: =E80/F80 -> 0.83333333 | H80: =D80/E80 -> 119.96 | I80: =H80/G80 -> 143.952 | J80: 78.62 | K80: 6710 | L80: 1 | M80: 0 | N80: =J80/M80 -> #DIV/0! | O80: =M80/J80 -> 0 | P80: =J80/D80 -> 0.13107703 | Q80: =M80/D80 -> 0 | R80: =D80-M80 -> 599.8 | S80: =J80/L80 -> 78.62
C81: Superthotics | D81: 183.85 | E81: 3 | F81: 5 | G81: =E81/F81 -> 0.6 | H81: =D81/E81 -> 61.283333 | I81: =H81/G81 -> 102.13889 | J81: 97.43 | K81: 54420 | L81: 4 | M81: 239.8 | N81: =J81/M81 -> 0.40629691 | O81: =M81/J81 -> 2.4612542 | P81: =J81/D81 -> 0.52994289 | Q81: =M81/D81 -> 1.3043242 | R81: =D81-M81 -> -55.95 | S81: =J81/L81 -> 24.3575
C82: Therabotanics | D82: 29.95 | E82: 1 | F82: 1 | G82: =E82/F82 -> 1 | H82: =D82/E82 -> 29.95 | I82: =H82/G82 -> 29.95 | J82: 0 | K82: 0 | L82: 0 | M82: 0 | N82: =J82/M82 -> #DIV/0! | O82: =M82/J82 -> #DIV/0! | P82: =J82/D82 -> 0 | Q82: =M82/D82 -> 0 | R82: =D82-M82 -> 29.95 | S82: =J82/L82 -> #DIV/0!
C83: WALKFIT | D83: 873 | E83: 20 | F83: 23 | G83: =E83/F83 -> 0.86956522 | H83: =D83/E83 -> 43.65 | I83: =H83/G83 -> 50.1975 | J83: 223.97 | K83: 52080 | L83: 7 | M83: 216.75 | N83: =J83/M83 -> 1.0333103 | O83: =M83/J83 -> 0.96776354 | P83: =J83/D83 -> 0.25655212 | Q83: =M83/D83 -> 0.24828179 | R83: =D83-M83 -> 656.25 | S83: =J83/L83 -> 31.995714
C84: Ultmax | D84: 0 | E84: 0 | F84: 0 | G84: =E84/F84 -> #DIV/0! | H84: =D84/E84 -> #DIV/0! | I84: =H84/G84 -> #DIV/0! | J84: 0 | K84: 0 | L84: 0 | M84: 0 | N84: =J84/M84 -> #DIV/0! | O84: =M84/J84 -> #DIV/0! | P84: =J84/D84 -> #DIV/0! | Q84: =M84/D84 -> #DIV/0! | R84: =D84-M84 -> 0 | S84: =J84/L84 -> #DIV/0!
C85: Ionic Pro | D85: 3625.99 | E85: 16 | F85: 19 | G85: =E85/F85 -> 0.84210526 | H85: =D85/E85 -> 226.62437 | I85: =H85/G85 -> 269.11645 | J85: 562.12 | K85: 46453 | L85: 9 | M85: 1839.6 | N85: =J85/M85 -> 0.30556643 | O85: =M85/J85 -> 3.2726108 | P85: =J85/D85 -> 0.15502525 | Q85: =M85/D85 -> 0.50733731 | R85: =D85-M85 -> 1786.39 | S85: =J85/L85 -> 62.457778
C86: AromaTru | D86: 156 | E86: 3 | F86: 3 | G86: =E86/F86 -> 1 | H86: =D86/E86 -> 52 | I86: =H86/G86 -> 52 | J86: 9.36 | K86: 9962 | L86: 2 | M86: 0 | N86: =J86/M86 -> #DIV/0! | O86: =M86/J86 -> 0 | P86: =J86/D86 -> 0.06 | Q86: =M86/D86 -> 0 | R86: =D86-M86 -> 156 | S86: =J86/L86 -> 4.68
A87: =iferror(if(B87>0,month(B87)&"-"&year(B87),B87),) -> 1-2026 | B87: 46039 | C87: SEM Campaigns | D87: 0 | E87: 0 | F87: 0 | G87: =E87/F87 -> #DIV/0! | H87: =D87/E87 -> #DIV/0! | I87: =H87/G87 -> #DIV/0! | J87: 3804.72 | K87: 381864 | L87: 0 | M87: 6712.07 | N87: =J87/M87 -> 0.56684749 | O87: =M87/J87 -> 1.764143 | P87: =J87/D87 -> #DIV/0! | Q87: =M87/D87 -> #DIV/0! | R87: =D87-M87 -> -6712.07 | S87: =J87/L87 -> #DIV/0!
A88: =iferror(if(B88>0,month(B88)&"-"&year(B88),B88),) | B88: 2026 - Week 3 | D88: =SUM(D70:D87) -> 16516.22 | E88: =SUM(E70:E87) -> 201 | F88: =SUM(F70:F87) -> 230 | G88: =E88/F88 -> 0.87391304 | H88: =D88/E88 -> 82.170249 | I88: =H88/G88 -> 94.025658 | J88: =SUM(J70:J87) -> 7396.14 | K88: =SUM(K70:K87) -> 1205479 | L88: =SUM(L70:L87) -> 83 | M88: =SUM(M70:M87) -> 13385.64 | N88: =J88/M88 -> 0.55254287 | O88: =M88/J88 -> 1.8098143 | P88: =J88/D88 -> 0.4478107 | Q88: =M88/D88 -> 0.81045421 | R88: =SUM(R70:R87) -> 3130.58 | S88: =J88/L88 -> 89.11012 | T88: =IFERROR((D88-#REF!)/D88,) | U88: =IFERROR((E88-#REF!)/E88,) | V88: =IFERROR((D88-#REF!)/D88, ) | W88: =IFERROR((E88-#REF!)/E88, )
B89: 46040 | C89: AirDoctor | D89: 4732.63 | E89: 44 | F89: 36 | G89: =E89/F89 -> 1.2222222 | H89: =D89/E89 -> 107.55977 | I89: =H89/G89 -> 88.00345 | J89: 718.79 | K89: 125856 | L89: 12 | M89: 1088.84 | N89: =J89/M89 -> 0.6601429 | O89: =M89/J89 -> 1.5148235 | P89: =J89/D89 -> 0.15187961 | Q89: =M89/D89 -> 0.23007081 | R89: =D89-M89 -> 3643.79 | S89: =J89/L89 -> 59.899167
C90: AquaTru | D90: 6276.96 | E90: 90 | F90: 109 | G90: =E90/F90 -> 0.82568807 | H90: =D90/E90 -> 69.744 | I90: =H90/G90 -> 84.467733 | J90: 752.9 | K90: 151124 | L90: 30 | M90: 2897.8 | N90: =J90/M90 -> 0.25981779 | O90: =M90/J90 -> 3.8488511 | P90: =J90/D90 -> 0.1199466 | Q90: =M90/D90 -> 0.4616566 | R90: =D90-M90 -> 3379.16 | S90: =J90/L90 -> 25.096667
C91: Beflexible | D91: 209.85 | E91: 3 | F91: 2 | G91: =E91/F91 -> 1.5 | H91: =D91/E91 -> 69.95 | I91: =H91/G91 -> 46.633333 | J91: 0 | K91: 295 | L91: 0 | M91: 0 | N91: =(J91/M91) -> #DIV/0! | O91: =M91/J91 -> #DIV/0! | P91: =J91/D91 -> 0 | Q91: =M91/D91 -> 0 | R91: =D91-M91 -> 209.85 | S91: =J91/L91 -> #DIV/0!
C92: Better Bladder | D92: 0 | E92: 0 | F92: 1 | G92: =E92/F92 -> 0 | H92: =D92/E92 -> #DIV/0! | I92: =H92/G92 -> #DIV/0! | J92: 398.73 | K92: 26769 | L92: 2 | M92: 119.9 | N92: =J92/M92 -> 3.3255213 | O92: =M92/J92 -> 0.30070474 | P92: =J92/D92 -> #DIV/0! | Q92: =M92/D92 -> #DIV/0! | R92: =D92-M92 -> -119.9 | S92: =J92/L92 -> 199.365
C93: Ideal Prostate | D93: 139.9 | E93: 2 | F93: 2 | G93: =E93/F93 -> 1 | H93: =D93/E93 -> 69.95 | I93: =H93/G93 -> 69.95 | J93: 62.63 | K93: 21148 | L93: 3 | M93: 179.85 | N93: =J93/M93 -> 0.34823464 | O93: =M93/J93 -> 2.871627 | P93: =J93/D93 -> 0.44767691 | Q93: =M93/D93 -> 1.2855611 | R93: =D93-M93 -> -39.95 | S93: =J93/L93 -> 20.876667
B94: to | C94: Miracle Blade | D94: 0 | E94: 0 | F94: 0 | G94: =E94/F94 -> #DIV/0! | H94: =D94/E94 -> #DIV/0! | I94: =H94/G94 -> #DIV/0! | J94: 21.15 | K94: 38434 | L94: 0 | M94: 0 | N94: =J94/M94 -> #DIV/0! | O94: =M94/J94 -> 0 | P94: =J94/D94 -> #DIV/0! | Q94: =M94/D94 -> #DIV/0! | R94: =D94-M94 -> 0 | S94: =J94/L94 -> #DIV/0!
C95: Paint Zoom | D95: 0 | E95: 0 | F95: 0 | G95: =E95/F95 -> #DIV/0! | H95: =D95/E95 -> #DIV/0! | I95: =H95/G95 -> #DIV/0! | J95: 0 | K95: 0 | L95: 0 | M95: 0 | N95: =J95/M95 -> #DIV/0! | O95: =M95/J95 -> #DIV/0! | P95: =J95/D95 -> #DIV/0! | Q95: =M95/D95 -> #DIV/0! | R95: =D95-M95 -> 0 | S95: =J95/L95 -> #DIV/0!
C96: Profemin | D96: 0 | E96: 0 | F96: 0 | G96: =E96/F96 -> #DIV/0! | H96: =D96/E96 -> #DIV/0! | I96: =H96/G96 -> #DIV/0! | J96: 0 | K96: 0 | L96: 0 | M96: 0 | N96: =J96/M96 -> #DIV/0! | O96: =M96/J96 -> #DIV/0! | P96: =J96/D96 -> #DIV/0! | Q96: =M96/D96 -> #DIV/0! | R96: =D96-M96 -> 0 | S96: =J96/L96 -> #DIV/0!
C97: Prosvent | D97: 2291.4 | E97: 33 | F97: 33 | G97: =E97/F97 -> 1 | H97: =D97/E97 -> 69.436364 | I97: =H97/G97 -> 69.436364 | J97: 421.66 | K97: 40683 | L97: 14 | M97: 829.86 | N97: =J97/M97 -> 0.5081098 | O97: =M97/J97 -> 1.9680785 | P97: =J97/D97 -> 0.1840185 | Q97: =M97/D97 -> 0.36216287 | R97: =D97-M97 -> 1461.54 | S97: =J97/L97 -> 30.118571
C98: SaniTru | D98: 159.92 | E98: 8 | F98: 3 | G98: =E98/F98 -> 2.6666667 | H98: =D98/E98 -> 19.99 | I98: =H98/G98 -> 7.49625 | J98: 367.68 | K98: 80649 | L98: 2 | M98: 39.98 | N98: =J98/M98 -> 9.1965983 | O98: =M98/J98 -> 0.10873586 | P98: =J98/D98 -> 2.2991496 | Q98: =M98/D98 -> 0.25 | R98: =D98-M98 -> 119.94 | S98: =J98/L98 -> 183.84
C99: Rotorazer Saw | D99: 1245.6 | E99: 10 | F99: 11 | G99: =E99/F99 -> 0.90909091 | H99: =D99/E99 -> 124.56 | I99: =H99/G99 -> 137.016 | J99: 46.96 | K99: 7099 | L99: 4 | M99: 205.95 | N99: =J99/M99 -> 0.22801651 | O99: =M99/J99 -> 4.3856474 | P99: =J99/D99 -> 0.037700706 | Q99: =M99/D99 -> 0.165342 | R99: =D99-M99 -> 1039.65 | S99: =J99/L99 -> 11.74
C100: Superthotics | D100: 179.85 | E100: 3 | F100: 4 | G100: =E100/F100 -> 0.75 | H100: =D100/E100 -> 59.95 | I100: =H100/G100 -> 79.933333 | J100: 66.07 | K100: 45813 | L100: 1 | M100: 59.95 | N100: =J100/M100 -> 1.1020851 | O100: =M100/J100 -> 0.90737097 | P100: =J100/D100 -> 0.36736169 | Q100: =M100/D100 -> 0.33333333 | R100: =D100-M100 -> 119.9 | S100: =J100/L100 -> 66.07
C101: Therabotanics | D101: 0 | E101: 0 | F101: 0 | G101: =E101/F101 -> #DIV/0! | H101: =D101/E101 -> #DIV/0! | I101: =H101/G101 -> #DIV/0! | J101: 0 | K101: 0 | L101: 0 | M101: 0 | N101: =J101/M101 -> #DIV/0! | O101: =M101/J101 -> #DIV/0! | P101: =J101/D101 -> #DIV/0! | Q101: =M101/D101 -> #DIV/0! | R101: =D101-M101 -> 0 | S101: =J101/L101 -> #DIV/0!
C102: WALKFIT | D102: 1186.24 | E102: 27 | F102: 29 | G102: =E102/F102 -> 0.93103448 | H102: =D102/E102 -> 43.934815 | I102: =H102/G102 -> 47.189246 | J102: 179.59 | K102: 48414 | L102: 8 | M102: 259.7 | N102: =J102/M102 -> 0.69152869 | O102: =M102/J102 -> 1.4460716 | P102: =J102/D102 -> 0.15139432 | Q102: =M102/D102 -> 0.21892703 | R102: =D102-M102 -> 926.54 | S102: =J102/L102 -> 22.44875
...

Sheet SEM Campaigns Data 2026
A1: WALMART - DATA SOURCES: https://seller.walmart.com/advertising/search-engine-marketing/
C2: WEEKLY PERFORMANCE | X2: =(#REF!+#REF!+#REF!+#REF!)-(monthly_reporting_2021!D17+monthly_reporting_2021!D23+monthly_reporting_2021!D29+monthly_reporting_2021!D35) -> #REF! | Y2: =((#REF!+#REF!+#REF!+#REF!)-(monthly_reporting_2021!E17+monthly_reporting_2021!E23+monthly_reporting_2021!E29+monthly_reporting_2021!E35))/(#REF!+#REF!+#REF!+#REF!) -> #REF!
A3: Total Sales | D3: Total Orders | I3: Total Units Sold
A4: =VLOOKUP("Current Week",$B$11:$X$208,match("SALES",$B$11:$X$11,0),FALSE) -> 0 | D4: =VLOOKUP("Current Week",$B$11:$X$208,match("Units Sold",$B$11:$X$11,0),FALSE) -> 0 | I4: =VLOOKUP("Current Week",$B$11:$X$208,match("Ordered Items",$B$11:$X$11,0),FALSE) -> 0
A5: =(A4-(VLOOKUP("Previous Week",$B$11:$X$213,match("SALES",$B$11:$X$11,0),FALSE)))/A4 -> #DIV/0! | D5: =(D4-(VLOOKUP("Previous Week",$B$11:$X$213,match("Units Sold",$B$11:$X$11,0),FALSE)))/D4 -> #DIV/0! | I5: =(I4-(VLOOKUP("Previous Week",$B$11:$X$213,match("Ordered Items",$B$11:$X$11,0),FALSE)))/I4 -> #DIV/0!
A7: Advertising Sales | D7: Advertising Spend | I7: ACoS
A8: =VLOOKUP("Current Week",$B$11:$X$208,match("AD SALES",$B$11:$X$11,0),FALSE) -> 10487.94 | D8: =VLOOKUP("Current Week",$B$11:$X$208,match("SP AD SPEND",$B$11:$X$11,0),FALSE) -> 4917.55 | I8: =D8/A8 -> 0.46887663
A9: =(A8-(VLOOKUP("Previous Week",$B$11:$X$213,match("AD SALES",$B$11:$X$11,0),FALSE)))/A8 -> 0.13924088 | D9: =(D8-(VLOOKUP("Previous Week",$B$11:$X$213,match("SP AD SPEND",$B$11:$X$11,0),FALSE)))/D8 -> -0.10666084 | I9: =(I8-(VLOOKUP("Previous Week",$B$11:$X$213,match("ACOS",$B$11:$X$11,0),FALSE)))/I8 -> -0.28568006
D10: SALES METRICS | L10: ADVERTISING PERFORMANCE | V10: MoM | X10: YoY
A11: Month-Code | B11: DATE | C11: Campaign Name | D11: SALES | E11: UNITS SOLD | F11: ORDERED ITEMS | G11: UNITS PER ORDER | H11: SALES PER ORDER | I11: ASP | J11: SP AD SPEND | K11: IMPRESSIONS | L11: UNIT SALES | M11: AD SALES | N11: ACoS | O11: ROAS (return on ad send) | P11: TACoS (Total Advertsing Cost of Sales) | Q11: REVENUE PERCENTAGE OF AD SALES | R11: ORGANIC SALES | S11: CPO | T11: SALES | U11: UNITS | V11: SALES | W11: UNITS
B13: 46012 | C13: Dielon - AquaTru - Highly Recommended | G13: =E13/F13 -> #DIV/0! | H13: =D13/E13 -> #DIV/0! | I13: =H13/G13 -> #DIV/0! | J13: 2974.57 | K13: 115078 | M13: 10437.51 | N13: =J13/M13 -> 0.28498847 | O13: =M13/J13 -> 3.5089139 | P13: =J13/D13 -> #DIV/0! | Q13: =M13/D13 -> #DIV/0! | R13: =D13-M13 -> -10437.51 | S13: =J13/L13 -> #DIV/0!
C14: Dielon - Ideal Prostate - Highly Recommended | G14: =E14/F14 -> #DIV/0! | H14: =D14/E14 -> #DIV/0! | I14: =H14/G14 -> #DIV/0! | J14: 145.64 | K14: 19906 | M14: 319.75 | N14: =J14/M14 -> 0.45548084 | O14: =M14/J14 -> 2.195482 | P14: =J14/D14 -> #DIV/0! | Q14: =M14/D14 -> #DIV/0! | R14: =D14-M14 -> -319.75 | S14: =J14/L14 -> #DIV/0!
C15: Dielon - Prosvent - Highly Recommended | G15: =E15/F15 -> #DIV/0! | H15: =D15/E15 -> #DIV/0! | I15: =H15/G15 -> #DIV/0! | J15: 161.15 | K15: 19653 | M15: 993.57 | N15: =(J15/M15) -> 0.1621929 | O15: =M15/J15 -> 6.165498 | P15: =J15/D15 -> #DIV/0! | Q15: =M15/D15 -> #DIV/0! | R15: =D15-M15 -> -993.57 | S15: =J15/L15 -> #DIV/0!
C16: Dielon - Better Bladder - Highly Recommended | G16: =E16/F16 -> #DIV/0! | H16: =D16/E16 -> #DIV/0! | I16: =H16/G16 -> #DIV/0! | J16: 195.37 | K16: 28885 | M16: 359.7 | N16: =J16/M16 -> 0.54314707 | O16: =M16/J16 -> 1.841122 | P16: =J16/D16 -> #DIV/0! | Q16: =M16/D16 -> #DIV/0! | R16: =D16-M16 -> -359.7 | S16: =J16/L16 -> #DIV/0!
C17: Dielon - Rotorazer - Highly Recommended | G17: =E17/F17 -> #DIV/0! | H17: =D17/E17 -> #DIV/0! | I17: =H17/G17 -> #DIV/0! | J17: 11.15 | K17: 1607 | M17: 0 | N17: =J17/M17 -> #DIV/0! | O17: =M17/J17 -> 0 | P17: =J17/D17 -> #DIV/0! | Q17: =M17/D17 -> #DIV/0! | R17: =D17-M17 -> 0 | S17: =J17/L17 -> #DIV/0!
C18: Dielon - Superthotics - Highly Recommended | G18: =E18/F18 -> #DIV/0! | H18: =D18/E18 -> #DIV/0! | I18: =H18/G18 -> #DIV/0! | J18: 215.11 | K18: 27058 | M18: 22.48 | N18: =J18/M18 -> 9.5689502 | O18: =M18/J18 -> 0.10450467 | P18: =J18/D18 -> #DIV/0! | Q18: =M18/D18 -> #DIV/0! | R18: =D18-M18 -> -22.48 | S18: =J18/L18 -> #DIV/0!
C19: Dielon - AirDoctor Filter - Highly Recommended | G19: =E19/F19 -> #DIV/0! | H19: =D19/E19 -> #DIV/0! | I19: =H19/G19 -> #DIV/0! | J19: 452.36 | K19: 16814 | M19: 1418.79 | N19: =J19/M19 -> 0.31883506 | O19: =M19/J19 -> 3.1364179 | P19: =J19/D19 -> #DIV/0! | Q19: =M19/D19 -> #DIV/0! | R19: =D19-M19 -> -1418.79 | S19: =J19/L19 -> #DIV/0!
B20: to | C20: Dielon - AquaTru Filters- Highly Recommended | G20: =E20/F20 -> #DIV/0! | H20: =D20/E20 -> #DIV/0! | I20: =H20/G20 -> #DIV/0! | J20: 147.77 | K20: 6193 | M20: 217.13 | N20: =J20/M20 -> 0.68056003 | O20: =M20/J20 -> 1.4693781 | P20: =J20/D20 -> #DIV/0! | Q20: =M20/D20 -> #DIV/0! | R20: =D20-M20 -> -217.13 | S20: =J20/L20 -> #DIV/0!
C21: Dielon - AirDoctor Main - Highly Recommended | G21: =E21/F21 -> #DIV/0! | H21: =D21/E21 -> #DIV/0! | I21: =H21/G21 -> #DIV/0! | J21: 1782.88 | K21: 165168 | M21: 1677.74 | N21: =J21/M21 -> 1.0626676 | O21: =M21/J21 -> 0.941028 | P21: =J21/D21 -> #DIV/0! | Q21: =M21/D21 -> #DIV/0! | R21: =D21-M21 -> -1677.74 | S21: =J21/L21 -> #DIV/0!
C22: Dielon - Walkfit Platinum - Highly Recommended | G22: =E22/F22 -> #DIV/0! | H22: =D22/E22 -> #DIV/0! | I22: =H22/G22 -> #DIV/0! | J22: 128.2 | K22: 23119 | M22: 427.86 | N22: =J22/M22 -> 0.29963072 | O22: =M22/J22 -> 3.3374415 | P22: =J22/D22 -> #DIV/0! | Q22: =M22/D22 -> #DIV/0! | R22: =D22-M22 -> -427.86 | S22: =J22/L22 -> #DIV/0!
C23: Dielon - Ionic Pro - Highly Suggested | J23: 440.24 | K23: 41970 | M23: 3015.09 | N23: =J23/M23 -> 0.14601223 | O23: =M23/J23 -> 6.8487416 | P23: =J23/D23 -> #DIV/0! | Q23: =M23/D23 -> #DIV/0! | R23: =D23-M23 -> -3015.09 | S23: =J23/L23 -> #DIV/0!
A24: =iferror(if(B24>0,month(B24)&"-"&year(B24),B24),) -> 12-2025 | B24: 46018 | C24: Dielon - Grown American - Highly Recommended | G24: =E24/F24 -> #DIV/0! | H24: =D24/E24 -> #DIV/0! | I24: =H24/G24 -> #DIV/0! | J24: 0 | K24: 0 | M24: 0 | N24: =J24/M24 -> #DIV/0! | O24: =M24/J24 -> #DIV/0! | P24: =J24/D24 -> #DIV/0! | Q24: =M24/D24 -> #DIV/0! | R24: =D24-M24 -> 0 | S24: =J24/L24 -> #DIV/0!
A25: =iferror(if(B25>0,month(B25)&"-"&year(B25),B25),) | B25: 2025 - Week 52 | D25: =SUM(D13:D24) -> 0 | E25: =SUM(E13:E24) -> 0 | F25: =SUM(F13:F24) -> 0 | G25: =E25/F25 -> #DIV/0! | H25: =D25/E25 -> #DIV/0! | I25: =H25/G25 -> #DIV/0! | J25: =SUM(J13:J24) -> 6654.44 | K25: =SUM(K13:K24) -> 465451 | L25: =SUM(L13:L24) -> 0 | M25: =SUM(M13:M24) -> 18889.62 | N25: =J25/M25 -> 0.35228025 | O25: =M25/J25 -> 2.8386491 | P25: =J25/D25 -> #DIV/0! | Q25: =M25/D25 -> #DIV/0! | R25: =SUM(R13:R24) -> -18889.62 | S25: =J25/L25 -> #DIV/0! | T25: =IFERROR((D25-#REF!)/D25,) | U25: =IFERROR((E25-#REF!)/E25,) | V25: =IFERROR((D25-#REF!)/D25, ) | W25: =IFERROR((E25-#REF!)/E25, )
B26: 46019 | C26: Dielon - AquaTru - Highly Recommended | G26: =E26/F26 -> #DIV/0! | H26: =D26/E26 -> #DIV/0! | I26: =H26/G26 -> #DIV/0! | J26: 1881.73 | K26: 105735 | M26: 7796.98 | N26: =J26/M26 -> 0.24134088 | O26: =M26/J26 -> 4.1435169 | P26: =J26/D26 -> #DIV/0! | Q26: =M26/D26 -> #DIV/0! | R26: =D26-M26 -> -7796.98 | S26: =J26/L26 -> #DIV/0!
C27: Dielon - Ideal Prostate - Highly Recommended | G27: =E27/F27 -> #DIV/0! | H27: =D27/E27 -> #DIV/0! | I27: =H27/G27 -> #DIV/0! | J27: 121.46 | K27: 15074 | M27: 509.6 | N27: =J27/M27 -> 0.2383438 | O27: =M27/J27 -> 4.19562 | P27: =J27/D27 -> #DIV/0! | Q27: =M27/D27 -> #DIV/0! | R27: =D27-M27 -> -509.6 | S27: =J27/L27 -> #DIV/0!
C28: Dielon - Prosvent - Highly Recommended | G28: =E28/F28 -> #DIV/0! | H28: =D28/E28 -> #DIV/0! | I28: =H28/G28 -> #DIV/0! | J28: 424.73 | K28: 66686 | M28: 1592.61 | N28: =(J28/M28) -> 0.26668802 | O28: =M28/J28 -> 3.7496998 | P28: =J28/D28 -> #DIV/0! | Q28: =M28/D28 -> #DIV/0! | R28: =D28-M28 -> -1592.61 | S28: =J28/L28 -> #DIV/0!
C29: Dielon - Better Bladder - Highly Recommended | G29: =E29/F29 -> #DIV/0! | H29: =D29/E29 -> #DIV/0! | I29: =H29/G29 -> #DIV/0! | J29: 78.85 | K29: 48745 | M29: 182.85 | N29: =J29/M29 -> 0.43122778 | O29: =M29/J29 -> 2.3189601 | P29: =J29/D29 -> #DIV/0! | Q29: =M29/D29 -> #DIV/0! | R29: =D29-M29 -> -182.85 | S29: =J29/L29 -> #DIV/0!
C30: Dielon - Rotorazer - Highly Recommended | G30: =E30/F30 -> #DIV/0! | H30: =D30/E30 -> #DIV/0! | I30: =H30/G30 -> #DIV/0! | J30: 228.46 | K30: 24816 | M30: 959.68 | N30: =J30/M30 -> 0.23805852 | O30: =M30/J30 -> 4.2006478 | P30: =J30/D30 -> #DIV/0! | Q30: =M30/D30 -> #DIV/0! | R30: =D30-M30 -> -959.68 | S30: =J30/L30 -> #DIV/0!
C31: Dielon - Superthotics - Highly Recommended | G31: =E31/F31 -> #DIV/0! | H31: =D31/E31 -> #DIV/0! | I31: =H31/G31 -> #DIV/0! | J31: 33.91 | K31: 21585 | M31: 22.48 | N31: =J31/M31 -> 1.508452 | O31: =M31/J31 -> 0.66293129 | P31: =J31/D31 -> #DIV/0! | Q31: =M31/D31 -> #DIV/0! | R31: =D31-M31 -> -22.48 | S31: =J31/L31 -> #DIV/0!
C32: Dielon - AirDoctor Filter - Highly Recommended | G32: =E32/F32 -> #DIV/0! | H32: =D32/E32 -> #DIV/0! | I32: =H32/G32 -> #DIV/0! | J32: 651.49 | K32: 29812 | M32: 3259.38 | N32: =J32/M32 -> 0.19988157 | O32: =M32/J32 -> 5.0029624 | P32: =J32/D32 -> #DIV/0! | Q32: =M32/D32 -> #DIV/0! | R32: =D32-M32 -> -3259.38 | S32: =J32/L32 -> #DIV/0!
B33: to | C33: Dielon - AquaTru Filters- Highly Recommended | G33: =E33/F33 -> #DIV/0! | H33: =D33/E33 -> #DIV/0! | I33: =H33/G33 -> #DIV/0! | J33: 29.45 | K33: 10095 | M33: 717.79 | N33: =J33/M33 -> 0.041028713 | O33: =M33/J33 -> 24.373175 | P33: =J33/D33 -> #DIV/0! | Q33: =M33/D33 -> #DIV/0! | R33: =D33-M33 -> -717.79 | S33: =J33/L33 -> #DIV/0!
C34: Dielon - AirDoctor Main - Highly Recommended | G34: =E34/F34 -> #DIV/0! | H34: =D34/E34 -> #DIV/0! | I34: =H34/G34 -> #DIV/0! | J34: 888.27 | K34: 108458 | M34: 662.4 | N34: =J34/M34 -> 1.3409873 | O34: =M34/J34 -> 0.74571921 | P34: =J34/D34 -> #DIV/0! | Q34: =M34/D34 -> #DIV/0! | R34: =D34-M34 -> -662.4 | S34: =J34/L34 -> #DIV/0!
C35: Dielon - Walkfit Platinum - Highly Recommended | G35: =E35/F35 -> #DIV/0! | H35: =D35/E35 -> #DIV/0! | I35: =H35/G35 -> #DIV/0! | J35: 115.71 | K35: 20775 | M35: 404.63 | N35: =J35/M35 -> 0.28596496 | O35: =M35/J35 -> 3.496932 | P35: =J35/D35 -> #DIV/0! | Q35: =M35/D35 -> #DIV/0! | R35: =D35-M35 -> -404.63 | S35: =J35/L35 -> #DIV/0!
C36: Dielon - Ionic Pro - Highly Suggested | J36: 425.83 | K36: 55401 | M36: 2105.6 | N36: =J36/M36 -> 0.20223689 | O36: =M36/J36 -> 4.9446962 | P36: =J36/D36 -> #DIV/0! | Q36: =M36/D36 -> #DIV/0! | R36: =D36-M36 -> -2105.6 | S36: =J36/L36 -> #DIV/0!
A37: =iferror(if(B37>0,month(B37)&"-"&year(B37),B37),) -> 1-2026 | B37: 46025 | C37: Dielon - Grown American - Highly Recommended | G37: =E37/F37 -> #DIV/0! | H37: =D37/E37 -> #DIV/0! | I37: =H37/G37 -> #DIV/0! | J37: 0 | K37: 0 | M37: 0 | N37: =J37/M37 -> #DIV/0! | O37: =M37/J37 -> #DIV/0! | P37: =J37/D37 -> #DIV/0! | Q37: =M37/D37 -> #DIV/0! | R37: =D37-M37 -> 0 | S37: =J37/L37 -> #DIV/0!
A38: =iferror(if(B38>0,month(B38)&"-"&year(B38),B38),) | B38: 2026 - Week 1 | D38: =SUM(D26:D37) -> 0 | E38: =SUM(E26:E37) -> 0 | F38: =SUM(F26:F37) -> 0 | G38: =E38/F38 -> #DIV/0! | H38: =D38/E38 -> #DIV/0! | I38: =H38/G38 -> #DIV/0! | J38: =SUM(J26:J37) -> 4879.89 | K38: =SUM(K26:K37) -> 507182 | L38: =SUM(L26:L37) -> 0 | M38: =SUM(M26:M37) -> 18214 | N38: =J38/M38 -> 0.26791973 | O38: =M38/J38 -> 3.7324612 | P38: =J38/D38 -> #DIV/0! | Q38: =M38/D38 -> #DIV/0! | R38: =SUM(R26:R37) -> -18214 | S38: =J38/L38 -> #DIV/0! | T38: =IFERROR((D38-#REF!)/D38,) | U38: =IFERROR((E38-#REF!)/E38,) | V38: =IFERROR((D38-#REF!)/D38, ) | W38: =IFERROR((E38-#REF!)/E38, )
B39: 46026 | C39: Dielon - AquaTru - Highly Recommended | G39: =E39/F39 -> #DIV/0! | H39: =D39/E39 -> #DIV/0! | I39: =H39/G39 -> #DIV/0! | J39: 924.26 | K39: 92918 | M39: 2364.44 | N39: =J39/M39 -> 0.39090017 | O39: =M39/J39 -> 2.5581979 | P39: =J39/D39 -> #DIV/0! | Q39: =M39/D39 -> #DIV/0! | R39: =D39-M39 -> -2364.44 | S39: =J39/L39 -> #DIV/0!
C40: Dielon - Ideal Prostate - Highly Recommended | G40: =E40/F40 -> #DIV/0! | H40: =D40/E40 -> #DIV/0! | I40: =H40/G40 -> #DIV/0! | J40: 99.21 | K40: 12548 | M40: 289.77 | N40: =J40/M40 -> 0.34237499 | O40: =M40/J40 -> 2.9207741 | P40: =J40/D40 -> #DIV/0! | Q40: =M40/D40 -> #DIV/0! | R40: =D40-M40 -> -289.77 | S40: =J40/L40 -> #DIV/0!
C41: Dielon - Prosvent - Highly Recommended | G41: =E41/F41 -> #DIV/0! | H41: =D41/E41 -> #DIV/0! | I41: =H41/G41 -> #DIV/0! | J41: 408.49 | K41: 66262 | M41: 1174.35 | N41: =(J41/M41) -> 0.34784349 | O41: =M41/J41 -> 2.8748562 | P41: =J41/D41 -> #DIV/0! | Q41: =M41/D41 -> #DIV/0! | R41: =D41-M41 -> -1174.35 | S41: =J41/L41 -> #DIV/0!
C42: Dielon - Better Bladder - Highly Recommended | G42: =E42/F42 -> #DIV/0! | H42: =D42/E42 -> #DIV/0! | I42: =H42/G42 -> #DIV/0! | J42: 199.42 | K42: 37771 | M42: 341.73 | N42: =J42/M42 -> 0.58356012 | O42: =M42/J42 -> 1.7136195 | P42: =J42/D42 -> #DIV/0! | Q42: =M42/D42 -> #DIV/0! | R42: =D42-M42 -> -341.73 | S42: =J42/L42 -> #DIV/0!
C43: Dielon - Rotorazer - Highly Recommended | G43: =E43/F43 -> #DIV/0! | H43: =D43/E43 -> #DIV/0! | I43: =H43/G43 -> #DIV/0! | J43: 177.71 | K43: 12538 | M43: 719.76 | N43: =J43/M43 -> 0.24690175 | O43: =M43/J43 -> 4.0501941 | P43: =J43/D43 -> #DIV/0! | Q43: =M43/D43 -> #DIV/0! | R43: =D43-M43 -> -719.76 | S43: =J43/L43 -> #DIV/0!
C44: Dielon - Superthotics - Highly Recommended | G44: =E44/F44 -> #DIV/0! | H44: =D44/E44 -> #DIV/0! | I44: =H44/G44 -> #DIV/0! | J44: 34.78 | K44: 6981 | M44: 59.95 | N44: =J44/M44 -> 0.58015013 | O44: =M44/J44 -> 1.7236918 | P44: =J44/D44 -> #DIV/0! | Q44: =M44/D44 -> #DIV/0! | R44: =D44-M44 -> -59.95 | S44: =J44/L44 -> #DIV/0!
C45: Dielon - AirDoctor Filter - Highly Recommended | G45: =E45/F45 -> #DIV/0! | H45: =D45/E45 -> #DIV/0! | I45: =H45/G45 -> #DIV/0! | J45: 769.05 | K45: 33201 | M45: 1987.46 | N45: =J45/M45 -> 0.38695118 | O45: =M45/J45 -> 2.5843053 | P45: =J45/D45 -> #DIV/0! | Q45: =M45/D45 -> #DIV/0! | R45: =D45-M45 -> -1987.46 | S45: =J45/L45 -> #DIV/0!
B46: to | C46: Dielon - AquaTru Filters- Highly Recommended | G46: =E46/F46 -> #DIV/0! | H46: =D46/E46 -> #DIV/0! | I46: =H46/G46 -> #DIV/0! | J46: 367.79 | K46: 12648 | M46: 880.74 | N46: =J46/M46 -> 0.41759202 | O46: =M46/J46 -> 2.3946817 | P46: =J46/D46 -> #DIV/0! | Q46: =M46/D46 -> #DIV/0! | R46: =D46-M46 -> -880.74 | S46: =J46/L46 -> #DIV/0!
C47: Dielon - AirDoctor Main - Highly Recommended | G47: =E47/F47 -> #DIV/0! | H47: =D47/E47 -> #DIV/0! | I47: =H47/G47 -> #DIV/0! | J47: 368.21 | K47: 38567 | M47: 0 | N47: =J47/M47 -> #DIV/0! | O47: =M47/J47 -> 0 | P47: =J47/D47 -> #DIV/0! | Q47: =M47/D47 -> #DIV/0! | R47: =D47-M47 -> 0 | S47: =J47/L47 -> #DIV/0!
C48: Dielon - Walkfit Platinum - Highly Recommended | G48: =E48/F48 -> #DIV/0! | H48: =D48/E48 -> #DIV/0! | I48: =H48/G48 -> #DIV/0! | J48: 129.94 | K48: 21209 | M48: 369.6 | N48: =J48/M48 -> 0.35156926 | O48: =M48/J48 -> 2.8443897 | P48: =J48/D48 -> #DIV/0! | Q48: =M48/D48 -> #DIV/0! | R48: =D48-M48 -> -369.6 | S48: =J48/L48 -> #DIV/0!
C49: Dielon - Ionic Pro - Highly Suggested | J49: 449.36 | K49: 44217 | M49: 1479.7 | N49: =J49/M49 -> 0.30368318 | O49: =M49/J49 -> 3.2929055 | P49: =J49/D49 -> #DIV/0! | Q49: =M49/D49 -> #DIV/0! | R49: =D49-M49 -> -1479.7 | S49: =J49/L49 -> #DIV/0!
A50: =iferror(if(B50>0,month(B50)&"-"&year(B50),B50),) -> 1-2026 | B50: 46032 | C50: Dielon - Grown American - Highly Recommended | G50: =E50/F50 -> #DIV/0! | H50: =D50/E50 -> #DIV/0! | I50: =H50/G50 -> #DIV/0! | J50: 0 | K50: 0 | M50: 0 | N50: =J50/M50 -> #DIV/0! | O50: =M50/J50 -> #DIV/0! | P50: =J50/D50 -> #DIV/0! | Q50: =M50/D50 -> #DIV/0! | R50: =D50-M50 -> 0 | S50: =J50/L50 -> #DIV/0!
A51: =iferror(if(B51>0,month(B51)&"-"&year(B51),B51),) | B51: 2026 - Week 2 | D51: =SUM(D39:D50) -> 0 | E51: =SUM(E39:E50) -> 0 | F51: =SUM(F39:F50) -> 0 | G51: =E51/F51 -> #DIV/0! | H51: =D51/E51 -> #DIV/0! | I51: =H51/G51 -> #DIV/0! | J51: =SUM(J39:J50) -> 3928.22 | K51: =SUM(K39:K50) -> 378860 | L51: =SUM(L39:L50) -> 0 | M51: =SUM(M39:M50) -> 9667.5 | N51: =J51/M51 -> 0.40633256 | O51: =M51/J51 -> 2.4610383 | P51: =J51/D51 -> #DIV/0! | Q51: =M51/D51 -> #DIV/0! | R51: =SUM(R39:R50) -> -9667.5 | S51: =J51/L51 -> #DIV/0! | T51: =IFERROR((D51-#REF!)/D51,) | U51: =IFERROR((E51-#REF!)/E51,) | V51: =IFERROR((D51-#REF!)/D51, ) | W51: =IFERROR((E51-#REF!)/E51, )
B52: 46033 | C52: Dielon - AquaTru - Highly Recommended | G52: =E52/F52 -> #DIV/0! | H52: =D52/E52 -> #DIV/0! | I52: =H52/G52 -> #DIV/0! | J52: 736.7 | K52: 80068 | M52: 156.9 | N52: =J52/M52 -> 4.6953474 | O52: =M52/J52 -> 0.21297679 | P52: =J52/D52 -> #DIV/0! | Q52: =M52/D52 -> #DIV/0! | R52: =D52-M52 -> -156.9 | S52: =J52/L52 -> #DIV/0!
C53: Dielon - Ideal Prostate - Highly Recommended | G53: =E53/F53 -> #DIV/0! | H53: =D53/E53 -> #DIV/0! | I53: =H53/G53 -> #DIV/0! | J53: 96.57 | K53: 12707 | M53: 489.6 | N53: =J53/M53 -> 0.19724265 | O53: =M53/J53 -> 5.0698975 | P53: =J53/D53 -> #DIV/0! | Q53: =M53/D53 -> #DIV/0! | R53: =D53-M53 -> -489.6 | S53: =J53/L53 -> #DIV/0!
C54: Dielon - Prosvent - Highly Recommended | G54: =E54/F54 -> #DIV/0! | H54: =D54/E54 -> #DIV/0! | I54: =H54/G54 -> #DIV/0! | J54: 320.23 | K54: 63070 | M54: 1010.85 | N54: =(J54/M54) -> 0.3167928 | O54: =M54/J54 -> 3.1566374 | P54: =J54/D54 -> #DIV/0! | Q54: =M54/D54 -> #DIV/0! | R54: =D54-M54 -> -1010.85 | S54: =J54/L54 -> #DIV/0!
C55: Dielon - Better Bladder - Highly Recommended | G55: =E55/F55 -> #DIV/0! | H55: =D55/E55 -> #DIV/0! | I55: =H55/G55 -> #DIV/0! | J55: 539.59 | K55: 59054 | M55: 608.5 | N55: =J55/M55 -> 0.88675431 | O55: =M55/J55 -> 1.1277081 | P55: =J55/D55 -> #DIV/0! | Q55: =M55/D55 -> #DIV/0! | R55: =D55-M55 -> -608.5 | S55: =J55/L55 -> #DIV/0!
C56: Dielon - Rotorazer - Highly Recommended | G56: =E56/F56 -> #DIV/0! | H56: =D56/E56 -> #DIV/0! | I56: =H56/G56 -> #DIV/0! | J56: 109.83 | K56: 9248 | M56: 599.8 | N56: =J56/M56 -> 0.18311104 | O56: =M56/J56 -> 5.4611673 | P56: =J56/D56 -> #DIV/0! | Q56: =M56/D56 -> #DIV/0! | R56: =D56-M56 -> -599.8 | S56: =J56/L56 -> #DIV/0!
C57: Dielon - Superthotics - Highly Recommended | G57: =E57/F57 -> #DIV/0! | H57: =D57/E57 -> #DIV/0! | I57: =H57/G57 -> #DIV/0! | J57: 102.44 | K57: 15319 | M57: 59.95 | N57: =J57/M57 -> 1.7087573 | O57: =M57/J57 -> 0.58522062 | P57: =J57/D57 -> #DIV/0! | Q57: =M57/D57 -> #DIV/0! | R57: =D57-M57 -> -59.95 | S57: =J57/L57 -> #DIV/0!
C58: Dielon - AirDoctor Filter - Highly Recommended | G58: =E58/F58 -> #DIV/0! | H58: =D58/E58 -> #DIV/0! | I58: =H58/G58 -> #DIV/0! | J58: 599.47 | K58: 30432 | M58: 1656.64 | N58: =J58/M58 -> 0.36185894 | O58: =M58/J58 -> 2.7635078 | P58: =J58/D58 -> #DIV/0! | Q58: =M58/D58 -> #DIV/0! | R58: =D58-M58 -> -1656.64 | S58: =J58/L58 -> #DIV/0!
B59: to | C59: Dielon - AquaTru Filters- Highly Recommended | G59: =E59/F59 -> #DIV/0! | H59: =D59/E59 -> #DIV/0! | I59: =H59/G59 -> #DIV/0! | J59: 490.26 | K59: 13467 | M59: 559.8 | N59: =J59/M59 -> 0.87577706 | O59: =M59/J59 -> 1.1418431 | P59: =J59/D59 -> #DIV/0! | Q59: =M59/D59 -> #DIV/0! | R59: =D59-M59 -> -559.8 | S59: =J59/L59 -> #DIV/0!
C60: Dielon - AirDoctor Main - Highly Recommended | G60: =E60/F60 -> #DIV/0! | H60: =D60/E60 -> #DIV/0! | I60: =H60/G60 -> #DIV/0! | J60: 142.95 | K60: 23662 | M60: 0 | N60: =J60/M60 -> #DIV/0! | O60: =M60/J60 -> 0 | P60: =J60/D60 -> #DIV/0! | Q60: =M60/D60 -> #DIV/0! | R60: =D60-M60 -> 0 | S60: =J60/L60 -> #DIV/0!
C61: Dielon - Walkfit Platinum - Highly Recommended | G61: =E61/F61 -> #DIV/0! | H61: =D61/E61 -> #DIV/0! | I61: =H61/G61 -> #DIV/0! | J61: 205.96 | K61: 29503 | M61: 290.33 | N61: =J61/M61 -> 0.70939965 | O61: =M61/J61 -> 1.4096426 | P61: =J61/D61 -> #DIV/0! | Q61: =M61/D61 -> #DIV/0! | R61: =D61-M61 -> -290.33 | S61: =J61/L61 -> #DIV/0!
C62: Dielon - Ionic Pro - Highly Suggested | J62: 460.72 | K62: 45334 | M62: 1279.7 | N62: =J62/M62 -> 0.36002188 | O62: =M62/J62 -> 2.777609 | P62: =J62/D62 -> #DIV/0! | Q62: =M62/D62 -> #DIV/0! | R62: =D62-M62 -> -1279.7 | S62: =J62/L62 -> #DIV/0!
A63: =iferror(if(B63>0,month(B63)&"-"&year(B63),B63),) -> 1-2026 | B63: 46039 | C63: Dielon - Grown American - Highly Recommended | G63: =E63/F63 -> #DIV/0! | H63: =D63/E63 -> #DIV/0! | I63: =H63/G63 -> #DIV/0! | J63: 0 | K63: 0 | M63: 0 | N63: =J63/M63 -> #DIV/0! | O63: =M63/J63 -> #DIV/0! | P63: =J63/D63 -> #DIV/0! | Q63: =M63/D63 -> #DIV/0! | R63: =D63-M63 -> 0 | S63: =J63/L63 -> #DIV/0!
A64: =iferror(if(B64>0,month(B64)&"-"&year(B64),B64),) | B64: 2026 - Week 3 | D64: =SUM(D52:D63) -> 0 | E64: =SUM(E52:E63) -> 0 | F64: =SUM(F52:F63) -> 0 | G64: =E64/F64 -> #DIV/0! | H64: =D64/E64 -> #DIV/0! | I64: =H64/G64 -> #DIV/0! | J64: =SUM(J52:J63) -> 3804.72 | K64: =SUM(K52:K63) -> 381864 | L64: =SUM(L52:L63) -> 0 | M64: =SUM(M52:M63) -> 6712.07 | N64: =J64/M64 -> 0.56684749 | O64: =M64/J64 -> 1.764143 | P64: =J64/D64 -> #DIV/0! | Q64: =M64/D64 -> #DIV/0! | R64: =SUM(R52:R63) -> -6712.07 | S64: =J64/L64 -> #DIV/0! | T64: =IFERROR((D64-#REF!)/D64,) | U64: =IFERROR((E64-#REF!)/E64,) | V64: =IFERROR((D64-#REF!)/D64, ) | W64: =IFERROR((E64-#REF!)/E64, )
B65: 46040 | C65: Dielon - AquaTru - Highly Recommended | G65: =E65/F65 -> #DIV/0! | H65: =D65/E65 -> #DIV/0! | I65: =H65/G65 -> #DIV/0! | J65: 446.66 | K65: 46700 | M65: 646.18 | N65: =J65/M65 -> 0.69123155 | O65: =M65/J65 -> 1.4466932 | P65: =J65/D65 -> #DIV/0! | Q65: =M65/D65 -> #DIV/0! | R65: =D65-M65 -> -646.18 | S65: =J65/L65 -> #DIV/0!
C66: Dielon - Ideal Prostate - Highly Recommended | G66: =E66/F66 -> #DIV/0! | H66: =D66/E66 -> #DIV/0! | I66: =H66/G66 -> #DIV/0! | J66: 168.32 | K66: 12644 | M66: 299.75 | N66: =J66/M66 -> 0.56153461 | O66: =M66/J66 -> 1.7808341 | P66: =J66/D66 -> #DIV/0! | Q66: =M66/D66 -> #DIV/0! | R66: =D66-M66 -> -299.75 | S66: =J66/L66 -> #DIV/0!
C67: Dielon - Prosvent - Highly Recommended | G67: =E67/F67 -> #DIV/0! | H67: =D67/E67 -> #DIV/0! | I67: =H67/G67 -> #DIV/0! | J67: 135.59 | K67: 19068 | M67: 704.39 | N67: =(J67/M67) -> 0.1924928 | O67: =M67/J67 -> 5.1949996 | P67: =J67/D67 -> #DIV/0! | Q67: =M67/D67 -> #DIV/0! | R67: =D67-M67 -> -704.39 | S67: =J67/L67 -> #DIV/0!
C68: Dielon - Better Bladder - Highly Recommended | G68: =E68/F68 -> #DIV/0! | H68: =D68/E68 -> #DIV/0! | I68: =H68/G68 -> #DIV/0! | J68: 214.88 | K68: 32075 | M68: 403.8 | N68: =J68/M68 -> 0.53214463 | O68: =M68/J68 -> 1.8791884 | P68: =J68/D68 -> #DIV/0! | Q68: =M68/D68 -> #DIV/0! | R68: =D68-M68 -> -403.8 | S68: =J68/L68 -> #DIV/0!
C69: Dielon - Rotorazer - Highly Recommended | G69: =E69/F69 -> #DIV/0! | H69: =D69/E69 -> #DIV/0! | I69: =H69/G69 -> #DIV/0! | J69: 347.76 | K69: 33993 | M69: 925.71 | N69: =J69/M69 -> 0.37566841 | O69: =M69/J69 -> 2.661922 | P69: =J69/D69 -> #DIV/0! | Q69: =M69/D69 -> #DIV/0! | R69: =D69-M69 -> -925.71 | S69: =J69/L69 -> #DIV/0!
C70: Dielon - Superthotics - Highly Recommended | G70: =E70/F70 -> #DIV/0! | H70: =D70/E70 -> #DIV/0! | I70: =H70/G70 -> #DIV/0! | J70: 37.7 | K70: 6261 | M70: 59.95 | N70: =J70/M70 -> 0.62885738 | O70: =M70/J70 -> 1.5901857 | P70: =J70/D70 -> #DIV/0! | Q70: =M70/D70 -> #DIV/0! | R70: =D70-M70 -> -59.95 | S70: =J70/L70 -> #DIV/0!
C71: Dielon - AirDoctor Filter - Highly Recommended | G71: =E71/F71 -> #DIV/0! | H71: =D71/E71 -> #DIV/0! | I71: =H71/G71 -> #DIV/0! | J71: 528.95 | K71: 31342 | M71: 2179.77 | N71: =J71/M71 -> 0.24266322 | O71: =M71/J71 -> 4.1209377 | P71: =J71/D71 -> #DIV/0! | Q71: =M71/D71 -> #DIV/0! | R71: =D71-M71 -> -2179.77 | S71: =J71/L71 -> #DIV/0!
B72: to | C72: Dielon - AquaTru Filters- Highly Recommended | G72: =E72/F72 -> #DIV/0! | H72: =D72/E72 -> #DIV/0! | I72: =H72/G72 -> #DIV/0! | J72: 221.65 | K72: 8512 | M72: 936.47 | N72: =J72/M72 -> 0.23668671 | O72: =M72/J72 -> 4.2249944 | P72: =J72/D72 -> #DIV/0! | Q72: =M72/D72 -> #DIV/0! | R72: =D72-M72 -> -936.47 | S72: =J72/L72 -> #DIV/0!
C73: Dielon - AirDoctor Main - Highly Recommended | G73: =E73/F73 -> #DIV/0! | H73: =D73/E73 -> #DIV/0! | I73: =H73/G73 -> #DIV/0! | J73: 94.64 | K73: 17161 | M73: 389 | N73: =J73/M73 -> 0.24329049 | O73: =M73/J73 -> 4.1103128 | P73: =J73/D73 -> #DIV/0! | Q73: =M73/D73 -> #DIV/0! | R73: =D73-M73 -> -389 | S73: =J73/L73 -> #DIV/0!
C74: Dielon - Walkfit Platinum - Highly Recommended | G74: =E74/F74 -> #DIV/0! | H74: =D74/E74 -> #DIV/0! | I74: =H74/G74 -> #DIV/0! | J74: 150.11 | K74: 27589 | M74: 609.3 | N74: =J74/M74 -> 0.24636468 | O74: =M74/J74 -> 4.0590234 | P74: =J74/D74 -> #DIV/0! | Q74: =M74/D74 -> #DIV/0! | R74: =D74-M74 -> -609.3 | S74: =J74/L74 -> #DIV/0!
C75: Dielon - Ionic Pro - Highly Suggested | G75: =E75/F75 -> #DIV/0! | H75: =D75/E75 -> #DIV/0! | I75: =H75/G75 -> #DIV/0! | J75: 389.08 | K75: 38193 | M75: 2759.4 | N75: =J75/M75 -> 0.14100167 | O75: =M75/J75 -> 7.0921147 | P75: =J75/D75 -> #DIV/0! | Q75: =M75/D75 -> #DIV/0! | R75: =D75-M75 -> -2759.4 | S75: =J75/L75 -> #DIV/0!
C76: Dielon - AirDoctor Main - Suggested | G76: =E76/F76 -> #DIV/0! | H76: =D76/E76 -> #DIV/0! | I76: =H76/G76 -> #DIV/0! | J76: 20.97 | K76: 2400 | M76: 197.3 | N76: =J76/M76 -> 0.10628485 | O76: =M76/J76 -> 9.4086791 | P76: =J76/D76 -> #DIV/0! | Q76: =M76/D76 -> #DIV/0! | R76: =D76-M76 -> -197.3 | S76: =J76/L76 -> #DIV/0!
C77: Dielon - Aquatru Main - Suggested | G77: =E77/F77 -> #DIV/0! | H77: =D77/E77 -> #DIV/0! | I77: =H77/G77 -> #DIV/0! | J77: 341.19 | K77: 14077 | M77: 1087.55 | N77: =J77/M77 -> 0.31372351 | O77: =M77/J77 -> 3.1875202 | P77: =J77/D77 -> #DIV/0! | Q77: =M77/D77 -> #DIV/0! | R77: =D77-M77 -> -1087.55 | S77: =J77/L77 -> #DIV/0!
A78: =iferror(if(B78>0,month(B78)&"-"&year(B78),B78),) -> 1-2026 | B78: 46046 | C78: Dielon - Grown American - Highly Recommended | G78: =E78/F78 -> #DIV/0! | H78: =D78/E78 -> #DIV/0! | I78: =H78/G78 -> #DIV/0! | J78: 0 | K78: 0 | M78: 0 | N78: =J78/M78 -> #DIV/0! | O78: =M78/J78 -> #DIV/0! | P78: =J78/D78 -> #DIV/0! | Q78: =M78/D78 -> #DIV/0! | R78: =D78-M78 -> 0 | S78: =J78/L78 -> #DIV/0!
A79: =iferror(if(B79>0,month(B79)&"-"&year(B79),B79),) | B79: 2026 - Week 4 | D79: =SUM(D65:D78) -> 0 | E79: =SUM(E65:E78) -> 0 | F79: =SUM(F65:F78) -> 0 | G79: =E79/F79 -> #DIV/0! | H79: =D79/E79 -> #DIV/0! | I79: =H79/G79 -> #DIV/0! | J79: =SUM(J65:J78) -> 3097.5 | K79: =SUM(K65:K78) -> 290015 | L79: =SUM(L65:L78) -> 0 | M79: =SUM(M65:M78) -> 11198.57 | N79: =J79/M79 -> 0.27659782 | O79: =M79/J79 -> 3.6153575 | P79: =J79/D79 -> #DIV/0! | Q79: =M79/D79 -> #DIV/0! | R79: =SUM(R65:R78) -> -11198.57 | S79: =J79/L79 -> #DIV/0! | T79: =IFERROR((D79-#REF!)/D79,) | U79: =IFERROR((E79-#REF!)/E79,) | V79: =IFERROR((D79-#REF!)/D79, ) | W79: =IFERROR((E79-#REF!)/E79, )
B80: 46047 | C80: Dielon - AquaTru - Highly Recommended | G80: =E80/F80 -> #DIV/0! | H80: =D80/E80 -> #DIV/0! | I80: =H80/G80 -> #DIV/0! | J80: 156.3 | K80: 19134 | M80: 434.95 | N80: =J80/M80 -> 0.35935165 | O80: =M80/J80 -> 2.7827895 | P80: =J80/D80 -> #DIV/0! | Q80: =M80/D80 -> #DIV/0! | R80: =D80-M80 -> -434.95 | S80: =J80/L80 -> #DIV/0!
C81: Dielon - Ideal Prostate - Highly Recommended | G81: =E81/F81 -> #DIV/0! | H81: =D81/E81 -> #DIV/0! | I81: =H81/G81 -> #DIV/0! | J81: 68.61 | K81: 9558 | M81: 149.88 | N81: =J81/M81 -> 0.45776621 | O81: =M81/J81 -> 2.1845212 | P81: =J81/D81 -> #DIV/0! | Q81: =M81/D81 -> #DIV/0! | R81: =D81-M81 -> -149.88 | S81: =J81/L81 -> #DIV/0!
C82: Dielon - Prosvent - Highly Recommended | G82: =E82/F82 -> #DIV/0! | H82: =D82/E82 -> #DIV/0! | I82: =H82/G82 -> #DIV/0! | J82: 62.37 | K82: 2490 | M82: 208.7 | N82: =(J82/M82) -> 0.29885002 | O82: =M82/J82 -> 3.34616 | P82: =J82/D82 -> #DIV/0! | Q82: =M82/D82 -> #DIV/0! | R82: =D82-M82 -> -208.7 | S82: =J82/L82 -> #DIV/0!
C83: Dielon - Better Bladder - Highly Recommended | G83: =E83/F83 -> #DIV/0! | H83: =D83/E83 -> #DIV/0! | I83: =H83/G83 -> #DIV/0! | J83: 119.92 | K83: 22981 | M83: 0 | N83: =J83/M83 -> #DIV/0! | O83: =M83/J83 -> 0 | P83: =J83/D83 -> #DIV/0! | Q83: =M83/D83 -> #DIV/0! | R83: =D83-M83 -> 0 | S83: =J83/L83 -> #DIV/0!
C84: Dielon - Rotorazer - Highly Recommended | G84: =E84/F84 -> #DIV/0! | H84: =D84/E84 -> #DIV/0! | I84: =H84/G84 -> #DIV/0! | J84: 252.05 | K84: 28527 | M84: 1045.67 | N84: =J84/M84 -> 0.24104163 | O84: =M84/J84 -> 4.148661 | P84: =J84/D84 -> #DIV/0! | Q84: =M84/D84 -> #DIV/0! | R84: =D84-M84 -> -1045.67 | S84: =J84/L84 -> #DIV/0!
C85: Dielon - Superthotics - Highly Recommended | G85: =E85/F85 -> #DIV/0! | H85: =D85/E85 -> #DIV/0! | I85: =H85/G85 -> #DIV/0! | J85: 27.62 | K85: 4096 | M85: 171.29 | N85: =J85/M85 -> 0.16124701 | O85: =M85/J85 -> 6.2016655 | P85: =J85/D85 -> #DIV/0! | Q85: =M85/D85 -> #DIV/0! | R85: =D85-M85 -> -171.29 | S85: =J85/L85 -> #DIV/0!
C86: Dielon - AirDoctor Filter - Highly Recommended | G86: =E86/F86 -> #DIV/0! | H86: =D86/E86 -> #DIV/0! | I86: =H86/G86 -> #DIV/0! | J86: 522.66 | K86: 27075 | M86: 1363.29 | N86: =J86/M86 -> 0.38338138 | O86: =M86/J86 -> 2.6083687 | P86: =J86/D86 -> #DIV/0! | Q86: =M86/D86 -> #DIV/0! | R86: =D86-M86 -> -1363.29 | S86: =J86/L86 -> #DIV/0!
B87: to | C87: Dielon - AquaTru Filters- Highly Recommended | G87: =E87/F87 -> #DIV/0! | H87: =D87/E87 -> #DIV/0! | I87: =H87/G87 -> #DIV/0! | J87: 111.53 | K87: 6787 | M87: 295.38 | N87: =J87/M87 -> 0.37758142 | O87: =M87/J87 -> 2.6484354 | P87: =J87/D87 -> #DIV/0! | Q87: =M87/D87 -> #DIV/0! | R87: =D87-M87 -> -295.38 | S87: =J87/L87 -> #DIV/0!
C88: Dielon - AirDoctor Main - Highly Recommended | G88: =E88/F88 -> #DIV/0! | H88: =D88/E88 -> #DIV/0! | I88: =H88/G88 -> #DIV/0! | J88: 78.75 | K88: 11989 | M88: 1177 | N88: =J88/M88 -> 0.066907392 | O88: =M88/J88 -> 14.946032 | P88: =J88/D88 -> #DIV/0! | Q88: =M88/D88 -> #DIV/0! | R88: =D88-M88 -> -1177 | S88: =J88/L88 -> #DIV/0!
C89: Dielon - Walkfit Platinum - Highly Recommended | G89: =E89/F89 -> #DIV/0! | H89: =D89/E89 -> #DIV/0! | I89: =H89/G89 -> #DIV/0! | J89: 119.54 | K89: 18801 | M89: 383.31 | N89: =J89/M89 -> 0.31186246 | O89: =M89/J89 -> 3.2065417 | P89: =J89/D89 -> #DIV/0! | Q89: =M89/D89 -> #DIV/0! | R89: =D89-M89 -> -383.31 | S89: =J89/L89 -> #DIV/0!
C90: Dielon - Ionic Pro - Highly Suggested | G90: =E90/F90 -> #DIV/0! | H90: =D90/E90 -> #DIV/0! | I90: =H90/G90 -> #DIV/0! | J90: 376.48 | K90: 36429 | M90: 739.85 | N90: =J90/M90 -> 0.5088599 | O90: =M90/J90 -> 1.9651774 | P90: =J90/D90 -> #DIV/0! | Q90: =M90/D90 -> #DIV/0! | R90: =D90-M90 -> -739.85 | S90: =J90/L90 -> #DIV/0!
C91: Dielon - AirDoctor Main - Suggested | G91: =E91/F91 -> #DIV/0! | H91: =D91/E91 -> #DIV/0! | I91: =H91/G91 -> #DIV/0! | J91: 117.28 | K91: 10425 | M91: 210.6 | N91: =J91/M91 -> 0.55688509 | O91: =M91/J91 -> 1.7957026 | P91: =J91/D91 -> #DIV/0! | Q91: =M91/D91 -> #DIV/0! | R91: =D91-M91 -> -210.6 | S91: =J91/L91 -> #DIV/0!
C92: Dielon - Aquatru Main - Suggested | G92: =E92/F92 -> #DIV/0! | H92: =D92/E92 -> #DIV/0! | I92: =H92/G92 -> #DIV/0! | J92: 1019.84 | K92: 65746 | M92: 3327.5 | N92: =J92/M92 -> 0.30648835 | O92: =M92/J92 -> 3.2627667 | P92: =J92/D92 -> #DIV/0! | Q92: =M92/D92 -> #DIV/0! | R92: =D92-M92 -> -3327.5 | S92: =J92/L92 -> #DIV/0!
A93: =iferror(if(B93>0,month(B93)&"-"&year(B93),B93),) -> 1-2026 | B93: 46053 | C93: Dielon - Grown American - Highly Recommended | G93: =E93/F93 -> #DIV/0! | H93: =D93/E93 -> #DIV/0! | I93: =H93/G93 -> #DIV/0! | J93: 0 | K93: 0 | M93: 0 | N93: =J93/M93 -> #DIV/0! | O93: =M93/J93 -> #DIV/0! | P93: =J93/D93 -> #DIV/0! | Q93: =M93/D93 -> #DIV/0! | R93: =D93-M93 -> 0 | S93: =J93/L93 -> #DIV/0!
A94: =iferror(if(B94>0,month(B94)&"-"&year(B94),B94),) | B94: 2026 - Week 5 | D94: =SUM(D80:D93) -> 0 | E94: =SUM(E80:E93) -> 0 | F94: =SUM(F80:F93) -> 0 | G94: =E94/F94 -> #DIV/0! | H94: =D94/E94 -> #DIV/0! | I94: =H94/G94 -> #DIV/0! | J94: =SUM(J80:J93) -> 3032.95 | K94: =SUM(K80:K93) -> 264038 | L94: =SUM(L80:L93) -> 0 | M94: =SUM(M80:M93) -> 9507.42 | N94: =J94/M94 -> 0.31900873 | O94: =M94/J94 -> 3.1347104 | P94: =J94/D94 -> #DIV/0! | Q94: =M94/D94 -> #DIV/0! | R94: =SUM(R80:R93) -> -9507.42 | S94: =J94/L94 -> #DIV/0! | T94: =IFERROR((D94-#REF!)/D94,) | U94: =IFERROR((E94-#REF!)/E94,) | V94: =IFERROR((D94-#REF!)/D94, ) | W94: =IFERROR((E94-#REF!)/E94, )
B95: 46054 | C95: Dielon - AquaTru - Highly Recommended | G95: =E95/F95 -> #DIV/0! | H95: =D95/E95 -> #DIV/0! | I95: =H95/G95 -> #DIV/0! | J95: 268.38 | K95: 39379 | M95: 613.28 | N95: =J95/M95 -> 0.43761414 | O95: =M95/J95 -> 2.2851181 | P95: =J95/D95 -> #DIV/0! | Q95: =M95/D95 -> #DIV/0! | R95: =D95-M95 -> -613.28 | S95: =J95/L95 -> #DIV/0!
C96: Dielon - Ideal Prostate - Highly Recommended | G96: =E96/F96 -> #DIV/0! | H96: =D96/E96 -> #DIV/0! | I96: =H96/G96 -> #DIV/0! | J96: 125.83 | K96: 15324 | M96: 224.83 | N96: =J96/M96 -> 0.5596673 | O96: =M96/J96 -> 1.7867758 | P96: =J96/D96 -> #DIV/0! | Q96: =M96/D96 -> #DIV/0! | R96: =D96-M96 -> -224.83 | S96: =J96/L96 -> #DIV/0!
C97: Dielon - Prosvent - Highly Recommended | G97: =E97/F97 -> #DIV/0! | H97: =D97/E97 -> #DIV/0! | I97: =H97/G97 -> #DIV/0! | J97: 92.39 | K97: 9366 | M97: 274.95 | N97: =(J97/M97) -> 0.33602473 | O97: =M97/J97 -> 2.9759714 | P97: =J97/D97 -> #DIV/0! | Q97: =M97/D97 -> #DIV/0! | R97: =D97-M97 -> -274.95 | S97: =J97/L97 -> #DIV/0!
C98: Dielon - Better Bladder - Highly Recommended | G98: =E98/F98 -> #DIV/0! | H98: =D98/E98 -> #DIV/0! | I98: =H98/G98 -> #DIV/0! | J98: 255.91 | K98: 30480 | M98: 362.7 | N98: =J98/M98 -> 0.70556934 | O98: =M98/J98 -> 1.4172951 | P98: =J98/D98 -> #DIV/0! | Q98: =M98/D98 -> #DIV/0! | R98: =D98-M98 -> -362.7 | S98: =J98/L98 -> #DIV/0!
C99: Dielon - Rotorazer - Highly Recommended | G99: =E99/F99 -> #DIV/0! | H99: =D99/E99 -> #DIV/0! | I99: =H99/G99 -> #DIV/0! | J99: 655.15 | K99: 51351 | M99: 1199.6 | N99: =J99/M99 -> 0.54614038 | O99: =M99/J99 -> 1.8310311 | P99: =J99/D99 -> #DIV/0! | Q99: =M99/D99 -> #DIV/0! | R99: =D99-M99 -> -1199.6 | S99: =J99/L99 -> #DIV/0!
C100: Dielon - Superthotics - Highly Recommended | G100: =E100/F100 -> #DIV/0! | H100: =D100/E100 -> #DIV/0! | I100: =H100/G100 -> #DIV/0! | J100: 80.02 | K100: 9372 | M100: 59.95 | N100: =J100/M100 -> 1.334779 | O100: =M100/J100 -> 0.7491877 | P100: =J100/D100 -> #DIV/0! | Q100: =M100/D100 -> #DIV/0! | R100: =D100-M100 -> -59.95 | S100: =J100/L100 -> #DIV/0!
C101: Dielon - AirDoctor Filter - Highly Recommended | G101: =E101/F101 -> #DIV/0! | H101: =D101/E101 -> #DIV/0! | I101: =H101/G101 -> #DIV/0! | J101: 592.69 | K101: 26681 | M101: 1284.19 | N101: =J101/M101 -> 0.46152828 | O101: =M101/J101 -> 2.1667145 | P101: =J101/D101 -> #DIV/0! | Q101: =M101/D101 -> #DIV/0! | R101: =D101-M101 -> -1284.19 | S101: =J101/L101 -> #DIV/0!
B102: to | C102: Dielon - AquaTru Filters- Highly Recommended | G102: =E102/F102 -> #DIV/0! | H102: =D102/E102 -> #DIV/0! | I102: =H102/G102 -> #DIV/0! | J102: 103.9 | K102: 4850 | M102: 634.71 | N102: =J102/M102 -> 0.16369681 | O102: =M102/J102 -> 6.1088547 | P102: =J102/D102 -> #DIV/0! | Q102: =M102/D102 -> #DIV/0! | R102: =D102-M102 -> -634.71 | S102: =J102/L102 -> #DIV/0!
...

Sheet WALMART_weekly_reporting_2025-B
A1: WALMART - DATA SOURCES: https://seller.walmart.com/analytics/overview/item-sale; https://seller.walmart.com/analytics/reports; And Intentwise
C2: WEEKLY PERFORMANCE | Y2: =(#REF!+#REF!+#REF!+#REF!)-(monthly_reporting_2021!E17+monthly_reporting_2021!E23+monthly_reporting_2021!E29+monthly_reporting_2021!E35) -> #REF! | Z2: =((#REF!+#REF!+#REF!+#REF!)-(monthly_reporting_2021!F17+monthly_reporting_2021!F23+monthly_reporting_2021!F29+monthly_reporting_2021!F35))/(#REF!+#REF!+#REF!+#REF!) -> #REF!
C3: Total Sales | G3: Total Orders | L3: Total Units Sold
C4: =VLOOKUP("Current Week",$B$11:$Y$982,match("SALES",$B$11:$Y$11,0),FALSE) -> 45850.88 | G4: =VLOOKUP("Current Week",$B$11:$Y$982,match("Units Sold",$B$11:$Y$11,0),FALSE) -> 342 | L4: =VLOOKUP("Current Week",$B$11:$Y$982,match("Ordered Items",$B$11:$Y$11,0),FALSE) -> 362
C5: =(C4-(VLOOKUP("Previous Week",$B$11:$Y$987,match("SALES",$B$11:$Y$11,0),FALSE)))/C4 -> 0.19141552 | G5: =(G4-(VLOOKUP("Previous Week",$B$11:$Y$987,match("Units Sold",$B$11:$Y$11,0),FALSE)))/G4 -> 0.28362573 | L5: =(L4-(VLOOKUP("Previous Week",$B$11:$Y$987,match("Ordered Items",$B$11:$Y$11,0),FALSE)))/L4 -> 0.26519337
C7: Advertising Sales | G7: Advertising Spend | L7: ACoS
C8: =VLOOKUP("Current Week",$B$11:$Y$982,match("AD SALES",$B$11:$Y$11,0),FALSE) -> 14363.4 | G8: =VLOOKUP("Current Week",$B$11:$Y$982,match("SP AD SPEND",$B$11:$Y$11,0),FALSE) -> 5806.71 | L8: =G8/C8 -> 0.40427127
C9: =(C8-(VLOOKUP("Previous Week",$B$11:$Y$987,match("AD SALES",$B$11:$Y$11,0),FALSE)))/C8 -> -0.08545052 | G9: =(G8-(VLOOKUP("Previous Week",$B$11:$Y$987,match("SP AD SPEND",$B$11:$Y$11,0),FALSE)))/G8 -> 0.12260127 | L9: =(L8-(VLOOKUP("Previous Week",$B$11:$Y$987,match("ACOS",$B$11:$Y$11,0),FALSE)))/L8 -> 0.19167321
D10: SALES METRICS | M10: ADVERTISING PERFORMANCE | W10: MoM | Y10: YoY
A11: Month-Code | B11: DATE | C11: BRAND | D11: SALES | E11: Average Sales Price by Brand | F11: UNITS SOLD | G11: ORDERED ITEMS | H11: UNITS PER ORDER | I11: SALES PER ORDER | J11: ASP | K11: SP AD SPEND | L11: IMPRESSIONS | M11: UNIT SALES | N11: AD SALES | O11: ACoS | P11: ROAS (return on ad send) | Q11: TACoS (Total Advertsing Cost of Sales) | R11: REVENUE PERCENTAGE OF AD SALES | S11: ORGANIC SALES | T11: CPO | U11: SALES | V11: UNITS | W11: SALES | X11: UNITS
B13: 45641 | C13: AirDoctor | D13: 10331.1 | F13: 29 | G13: 30 | H13: =F13/G13 -> 0.96666667 | I13: =D13/F13 -> 356.24483 | J13: =I13/H13 -> 368.52913 | K13: 93.48 | L13: 23980 | M13: 12 | N13: 2862.3 | O13: =K13/N13 -> 0.03265905 | P13: =N13/K13 -> 30.619384 | Q13: =K13/D13 -> 0.0090484072 | R13: =N13/D13 -> 0.27705665 | S13: =D13-N13 -> 7468.8 | T13: =K13/M13 -> 7.79
C14: AquaTru | D14: 8314.03 | F14: 39 | G14: 46 | H14: =F14/G14 -> 0.84782609 | I14: =D14/F14 -> 213.18026 | J14: =I14/H14 -> 251.44338 | K14: 174.95 | L14: 16451 | M14: 5 | N14: 654.9 | O14: =K14/N14 -> 0.26714002 | P14: =N14/K14 -> 3.7433552 | Q14: =K14/D14 -> 0.021042743 | R14: =N14/D14 -> 0.078770464 | S14: =D14-N14 -> 7659.13 | T14: =K14/M14 -> 34.99
C15: Beflexible | D15: 0 | F15: 0 | G15: 0 | H15: =F15/G15 -> #DIV/0! | I15: =D15/F15 -> #DIV/0! | J15: =I15/H15 -> #DIV/0! | K15: 0 | L15: 0 | M15: 0 | N15: 0 | O15: =K15/N15 -> #DIV/0! | P15: =N15/K15 -> #DIV/0! | Q15: =K15/D15 -> #DIV/0! | R15: =N15/D15 -> #DIV/0! | S15: =D15-N15 -> 0 | T15: =K15/M15 -> #DIV/0!
C16: Better Bladder | D16: 59.95 | F16: 1 | G16: 1 | H16: =F16/G16 -> 1 | I16: =D16/F16 -> 59.95 | J16: =I16/H16 -> 59.95 | K16: 58.66 | L16: 3967 | M16: 1 | N16: 59.95 | O16: =K16/N16 -> 0.97848207 | P16: =N16/K16 -> 1.0219911 | Q16: =K16/D16 -> 0.97848207 | R16: =N16/D16 -> 1 | S16: =D16-N16 -> 0 | T16: =K16/M16 -> 58.66
C17: Cebria | D17: 0 | F17: 0 | G17: 0 | H17: =F17/G17 -> #DIV/0! | I17: =D17/F17 -> #DIV/0! | J17: =I17/H17 -> #DIV/0! | K17: 0 | L17: 0 | M17: 0 | N17: 0 | O17: =K17/N17 -> #DIV/0! | P17: =N17/K17 -> #DIV/0! | Q17: =K17/D17 -> #DIV/0! | R17: =N17/D17 -> #DIV/0! | S17: =D17-N17 -> 0 | T17: =K17/M17 -> #DIV/0!
C18: GA Grown American | D18: 239.96 | F18: 4 | G18: 4 | H18: =F18/G18 -> 1 | I18: =D18/F18 -> 59.99 | J18: =I18/H18 -> 59.99 | K18: 41.79 | L18: 11511 | M18: 1 | N18: 59.99 | O18: =K18/N18 -> 0.6966161 | P18: =N18/K18 -> 1.4355109 | Q18: =K18/D18 -> 0.17415403 | R18: =N18/D18 -> 0.25 | S18: =D18-N18 -> 179.97 | T18: =K18/M18 -> 41.79
C19: Ideal Prostate | D19: 689.73 | F19: 11 | G19: 10 | H19: =F19/G19 -> 1.1 | I19: =D19/F19 -> 62.702727 | J19: =I19/H19 -> 57.002479 | K19: 160.43 | L19: 4358 | M19: 4 | N19: 279.8 | O19: =K19/N19 -> 0.57337384 | P19: =N19/K19 -> 1.7440628 | Q19: =K19/D19 -> 0.23259826 | R19: =N19/D19 -> 0.40566599 | S19: =D19-N19 -> 409.93 | T19: =K19/M19 -> 40.1075
B20: to | C20: Miracle Blade | D20: 162.73 | F20: 4 | G20: 7 | H20: =F20/G20 -> 0.57142857 | I20: =D20/F20 -> 40.6825 | J20: =I20/H20 -> 71.194375 | K20: 159.89 | L20: 17913 | M20: 0 | N20: 0 | O20: =K20/N20 -> #DIV/0! | P20: =N20/K20 -> 0 | Q20: =K20/D20 -> 0.98254778 | R20: =N20/D20 -> 0 | S20: =D20-N20 -> 162.73 | T20: =K20/M20 -> #DIV/0!
C21: Paint Zoom | D21: -4.96 | F21: -1 | G21: 1 | H21: =F21/G21 -> -1 | I21: =D21/F21 -> 4.96 | J21: =I21/H21 -> -4.96 | K21: 79.62 | L21: 182108 | M21: 1 | N21: 84.96 | O21: =K21/N21 -> 0.93714689 | P21: =N21/K21 -> 1.0670686 | Q21: =K21/D21 -> -16.052419 | R21: =N21/D21 -> -17.129032 | S21: =D21-N21 -> -89.92 | T21: =K21/M21 -> 79.62
C22: Profemin | D22: 274.75 | F22: 5 | G22: 4 | H22: =F22/G22 -> 1.25 | I22: =D22/F22 -> 54.95 | J22: =I22/H22 -> 43.96 | K22: 0 | L22: 0 | M22: 0 | N22: 0 | O22: =K22/N22 -> #DIV/0! | P22: =N22/K22 -> #DIV/0! | Q22: =K22/D22 -> 0 | R22: =N22/D22 -> 0 | S22: =D22-N22 -> 274.75 | T22: =K22/M22 -> #DIV/0!
C23: Prosvent | D23: 2437.8 | F23: 29 | G23: 24 | H23: =F23/G23 -> 1.2083333 | I23: =D23/F23 -> 84.062069 | J23: =I23/H23 -> 69.568609 | K23: 63.47 | L23: 12313 | M23: 6 | N23: 579.7 | O23: =K23/N23 -> 0.10948767 | P23: =N23/K23 -> 9.1334489 | Q23: =K23/D23 -> 0.02603577 | R23: =N23/D23 -> 0.23779637 | S23: =D23-N23 -> 1858.1 | T23: =K23/M23 -> 10.578333
C24: SaniTru | D24: 67.96 | F24: 1 | G24: 1 | H24: =F24/G24 -> 1 | I24: =D24/F24 -> 67.96 | J24: =I24/H24 -> 67.96 | K24: 2.14 | L24: 10943 | M24: 0 | N24: 0 | O24: =K24/N24 -> #DIV/0! | P24: =N24/K24 -> 0 | Q24: =K24/D24 -> 0.031489111 | R24: =N24/D24 -> 0 | S24: =D24-N24 -> 67.96 | T24: =K24/M24 -> #DIV/0!
C25: Rotorazer Saw | D25: -139.37 | F25: 0 | G25: 3 | H25: =F25/G25 -> 0 | I25: =D25/F25 -> #DIV/0! | J25: =I25/H25 -> #DIV/0! | K25: 21.79 | L25: 21569 | M25: 0 | N25: 0 | O25: =K25/N25 -> #DIV/0! | P25: =N25/K25 -> 0 | Q25: =K25/D25 -> -0.15634642 | R25: =N25/D25 -> 0 | S25: =D25-N25 -> -139.37 | T25: =K25/M25 -> #DIV/0!
C26: Superthotics | D26: 0 | F26: 0 | G26: 0 | H26: =F26/G26 -> #DIV/0! | I26: =D26/F26 -> #DIV/0! | J26: =I26/H26 -> #DIV/0! | K26: 3.1 | L26: 1684 | M26: 0 | N26: 0 | O26: =K26/N26 -> #DIV/0! | P26: =N26/K26 -> 0 | Q26: =K26/D26 -> #DIV/0! | R26: =N26/D26 -> #DIV/0! | S26: =D26-N26 -> 0 | T26: =K26/M26 -> #DIV/0!
C27: Therabotanics | D27: 0 | F27: 0 | G27: 0 | H27: =F27/G27 -> #DIV/0! | I27: =D27/F27 -> #DIV/0! | J27: =I27/H27 -> #DIV/0! | K27: 0 | L27: 0 | M27: 0 | N27: 0 | O27: =K27/N27 -> #DIV/0! | P27: =N27/K27 -> #DIV/0! | Q27: =K27/D27 -> #DIV/0! | R27: =N27/D27 -> #DIV/0! | S27: =D27-N27 -> 0 | T27: =K27/M27 -> #DIV/0!
C28: WALKFIT | D28: 900.09 | F28: 28 | G28: 26 | H28: =F28/G28 -> 1.0769231 | I28: =D28/F28 -> 32.146071 | J28: =I28/H28 -> 29.849923 | K28: 164.56 | L28: 45377 | M28: 18 | N28: 474.72 | O28: =K28/N28 -> 0.34664644 | P28: =N28/K28 -> 2.8847837 | Q28: =K28/D28 -> 0.18282616 | R28: =N28/D28 -> 0.52741393 | S28: =D28-N28 -> 425.37 | T28: =K28/M28 -> 9.1422222
A29: =iferror(if(B29>0,month(B29)&"-"&year(B29),B29),) -> 12-2024 | B29: 45647 | C29: AromaTru | D29: 9.8 | F29: 0 | G29: 1 | H29: =F29/G29 -> 0 | I29: =D29/F29 -> #DIV/0! | J29: =I29/H29 -> #DIV/0! | K29: 0 | L29: 12458 | M29: 0 | N29: 0 | O29: =K29/N29 -> #DIV/0! | P29: =N29/K29 -> #DIV/0! | Q29: =K29/D29 -> 0 | R29: =N29/D29 -> 0 | S29: =D29-N29 -> 9.8 | T29: =K29/M29 -> #DIV/0!
A30: =iferror(if(B30>0,month(B30)&"-"&year(B30),B30),) | B30: 2024 - Week 51 | D30: =SUM(D13:D29) -> 23343.57 | F30: =SUM(F13:F29) -> 150 | G30: =SUM(G13:G29) -> 158 | H30: =F30/G30 -> 0.94936709 | I30: =D30/F30 -> 155.6238 | J30: =I30/H30 -> 163.92374 | K30: =SUM(K13:K29) -> 1023.88 | L30: =SUM(L13:L29) -> 364632 | M30: =SUM(M13:M29) -> 48 | N30: =SUM(N13:N29) -> 5056.32 | O30: =K30/N30 -> 0.2024951 | P30: =N30/K30 -> 4.9383912 | Q30: =K30/D30 -> 0.043861329 | R30: =N30/D30 -> 0.2166044 | S30: =SUM(S13:S29) -> 18287.25 | T30: =K30/M30 -> 21.330833 | U30: =IFERROR((D30-#REF!)/D30,) | V30: =IFERROR((F30-#REF!)/F30,) | W30: =IFERROR((D30-monthly_reporting_2021!E49)/D30, ) | X30: =IFERROR((F30-monthly_reporting_2021!F49)/F30, )
B31: 45648 | C31: AirDoctor | D31: 12504.3 | F31: 32 | G31: 32 | H31: =F31/G31 -> 1 | I31: =D31/F31 -> 390.75937 | J31: =I31/H31 -> 390.75937 | K31: 106.38 | L31: 23406 | M31: 10 | N31: 4010.3 | O31: =K31/N31 -> 0.026526694 | P31: =N31/K31 -> 37.697876 | Q31: =K31/D31 -> 0.0085074734 | R31: =N31/D31 -> 0.32071367 | S31: =D31-N31 -> 8494 | T31: =K31/M31 -> 10.638
C32: AquaTru | D32: 5241.86 | F32: 31 | G32: 37 | H32: =F32/G32 -> 0.83783784 | I32: =D32/F32 -> 169.09226 | J32: =I32/H32 -> 201.81979 | K32: 104.84 | L32: 18706 | M32: 1 | N32: 79.95 | O32: =K32/N32 -> 1.3113196 | P32: =N32/K32 -> 0.76259061 | Q32: =K32/D32 -> 0.020000534 | R32: =N32/D32 -> 0.01525222 | S32: =D32-N32 -> 5161.91 | T32: =K32/M32 -> 104.84
C33: Beflexible | D33: 139.9 | F33: 2 | G33: 1 | H33: =F33/G33 -> 2 | I33: =D33/F33 -> 69.95 | J33: =I33/H33 -> 34.975 | K33: 0 | L33: 0 | M33: 0 | N33: 0 | O33: =K33/N33 -> #DIV/0! | P33: =N33/K33 -> #DIV/0! | Q33: =K33/D33 -> 0 | R33: =N33/D33 -> 0 | S33: =D33-N33 -> 139.9 | T33: =K33/M33 -> #DIV/0!
C34: Better Bladder | D34: 359.7 | F34: 6 | G34: 5 | H34: =F34/G34 -> 1.2 | I34: =D34/F34 -> 59.95 | J34: =I34/H34 -> 49.958333 | K34: 15.23 | L34: 1618 | M34: 0 | N34: 0 | O34: =K34/N34 -> #DIV/0! | P34: =N34/K34 -> 0 | Q34: =K34/D34 -> 0.04234084 | R34: =N34/D34 -> 0 | S34: =D34-N34 -> 359.7 | T34: =K34/M34 -> #DIV/0!
C35: Cebria | D35: 0 | F35: 0 | G35: 0 | H35: =F35/G35 -> #DIV/0! | I35: =D35/F35 -> #DIV/0! | J35: =I35/H35 -> #DIV/0! | K35: 0 | L35: 0 | M35: 0 | N35: 0 | O35: =K35/N35 -> #DIV/0! | P35: =N35/K35 -> #DIV/0! | Q35: =K35/D35 -> #DIV/0! | R35: =N35/D35 -> #DIV/0! | S35: =D35-N35 -> 0 | T35: =K35/M35 -> #DIV/0!
C36: GA Grown American | D36: 119.98 | F36: 2 | G36: 1 | H36: =F36/G36 -> 2 | I36: =D36/F36 -> 59.99 | J36: =I36/H36 -> 29.995 | K36: 41.55 | L36: 9951 | M36: 0 | N36: 0 | O36: =K36/N36 -> #DIV/0! | P36: =N36/K36 -> 0 | Q36: =K36/D36 -> 0.34630772 | R36: =N36/D36 -> 0 | S36: =D36-N36 -> 119.98 | T36: =K36/M36 -> #DIV/0!
C37: Ideal Prostate | D37: 849.35 | F37: 13 | G37: 8 | H37: =F37/G37 -> 1.625 | I37: =D37/F37 -> 65.334615 | J37: =I37/H37 -> 40.205917 | K37: 151.87 | L37: 3720 | M37: 1 | N37: 69.95 | O37: =K37/N37 -> 2.1711222 | P37: =N37/K37 -> 0.4605913 | Q37: =K37/D37 -> 0.17880732 | R37: =N37/D37 -> 0.082357097 | S37: =D37-N37 -> 779.4 | T37: =K37/M37 -> 151.87
B38: to | C38: Miracle Blade | D38: 765.75 | F38: 11 | G38: 14 | H38: =F38/G38 -> 0.78571429 | I38: =D38/F38 -> 69.613636 | J38: =I38/H38 -> 88.599174 | K38: 243.42 | L38: 28115 | M38: 4 | N38: 150.89 | O38: =K38/N38 -> 1.6132282 | P38: =N38/K38 -> 0.61987511 | Q38: =K38/D38 -> 0.31788443 | R38: =N38/D38 -> 0.19704865 | S38: =D38-N38 -> 614.86 | T38: =K38/M38 -> 60.855
C39: Paint Zoom | D39: 0 | F39: 0 | G39: 0 | H39: =F39/G39 -> #DIV/0! | I39: =D39/F39 -> #DIV/0! | J39: =I39/H39 -> #DIV/0! | K39: 53.92 | L39: 167085 | M39: 0 | N39: 0 | O39: =K39/N39 -> #DIV/0! | P39: =N39/K39 -> 0 | Q39: =K39/D39 -> #DIV/0! | R39: =N39/D39 -> #DIV/0! | S39: =D39-N39 -> 0 | T39: =K39/M39 -> #DIV/0!
C40: Profemin | D40: 0 | F40: 0 | G40: 1 | H40: =F40/G40 -> 0 | I40: =D40/F40 -> #DIV/0! | J40: =I40/H40 -> #DIV/0! | K40: 0 | L40: 0 | M40: 0 | N40: 0 | O40: =K40/N40 -> #DIV/0! | P40: =N40/K40 -> #DIV/0! | Q40: =K40/D40 -> #DIV/0! | R40: =N40/D40 -> #DIV/0! | S40: =D40-N40 -> 0 | T40: =K40/M40 -> #DIV/0!
C41: Prosvent | D41: 766.15 | F41: 15 | G41: 14 | H41: =F41/G41 -> 1.0714286 | I41: =D41/F41 -> 51.076667 | J41: =I41/H41 -> 47.671556 | K41: 56.99 | L41: 12059 | M41: 1 | N41: 67 | O41: =K41/N41 -> 0.85059701 | P41: =N41/K41 -> 1.1756449 | Q41: =K41/D41 -> 0.074384912 | R41: =N41/D41 -> 0.087450238 | S41: =D41-N41 -> 699.15 | T41: =K41/M41 -> 56.99
C42: SaniTru | D42: -10.91 | F42: 1 | G42: 1 | H42: =F42/G42 -> 1 | I42: =D42/F42 -> -10.91 | J42: =I42/H42 -> -10.91 | K42: 8.58 | L42: 10088 | M42: 1 | N42: 19.99 | O42: =K42/N42 -> 0.42921461 | P42: =N42/K42 -> 2.3298368 | Q42: =K42/D42 -> -0.78643446 | R42: =N42/D42 -> -1.832264 | S42: =D42-N42 -> -30.9 | T42: =K42/M42 -> 8.58
C43: Rotorazer Saw | D43: 299.9 | F43: 2 | G43: 3 | H43: =F43/G43 -> 0.66666667 | I43: =D43/F43 -> 149.95 | J43: =I43/H43 -> 224.925 | K43: 19.96 | L43: 26977 | M43: 0 | N43: 0 | O43: =K43/N43 -> #DIV/0! | P43: =N43/K43 -> 0 | Q43: =K43/D43 -> 0.066555519 | R43: =N43/D43 -> 0 | S43: =D43-N43 -> 299.9 | T43: =K43/M43 -> #DIV/0!
C44: Superthotics | D44: 0 | F44: 0 | G44: 0 | H44: =F44/G44 -> #DIV/0! | I44: =D44/F44 -> #DIV/0! | J44: =I44/H44 -> #DIV/0! | K44: 1.02 | L44: 12691 | M44: 0 | N44: 0 | O44: =K44/N44 -> #DIV/0! | P44: =N44/K44 -> 0 | Q44: =K44/D44 -> #DIV/0! | R44: =N44/D44 -> #DIV/0! | S44: =D44-N44 -> 0 | T44: =K44/M44 -> #DIV/0!
C45: Therabotanics | D45: 79.8 | F45: 4 | G45: 2 | H45: =F45/G45 -> 2 | I45: =D45/F45 -> 19.95 | J45: =I45/H45 -> 9.975 | K45: 0 | L45: 0 | M45: 0 | N45: 0 | O45: =K45/N45 -> #DIV/0! | P45: =N45/K45 -> #DIV/0! | Q45: =K45/D45 -> 0 | R45: =N45/D45 -> 0 | S45: =D45-N45 -> 79.8 | T45: =K45/M45 -> #DIV/0!
C46: WALKFIT | D46: 359.6 | F46: 10 | G46: 12 | H46: =F46/G46 -> 0.83333333 | I46: =D46/F46 -> 35.96 | J46: =I46/H46 -> 43.152 | K46: 98.1 | L46: 44788 | M46: 4 | N46: 143.84 | O46: =K46/N46 -> 0.68200779 | P46: =N46/K46 -> 1.4662589 | Q46: =K46/D46 -> 0.27280311 | R46: =N46/D46 -> 0.4 | S46: =D46-N46 -> 215.76 | T46: =K46/M46 -> 24.525
A47: =iferror(if(B47>0,month(B47)&"-"&year(B47),B47),) -> 12-2024 | B47: 45654 | C47: AromaTru | D47: 0 | F47: 0 | G47: 0 | H47: =F47/G47 -> #DIV/0! | I47: =D47/F47 -> #DIV/0! | J47: =I47/H47 -> #DIV/0! | K47: 0.62 | L47: 8458 | M47: 0 | N47: 0 | O47: =K47/N47 -> #DIV/0! | P47: =N47/K47 -> 0 | Q47: =K47/D47 -> #DIV/0! | R47: =N47/D47 -> #DIV/0! | S47: =D47-N47 -> 0 | T47: =K47/M47 -> #DIV/0!
A48: =iferror(if(B48>0,month(B48)&"-"&year(B48),B48),) | B48: 2024 - Week 52 | D48: =SUM(D31:D47) -> 21475.38 | F48: =SUM(F31:F47) -> 129 | G48: =SUM(G31:G47) -> 131 | H48: =F48/G48 -> 0.98473282 | I48: =D48/F48 -> 166.47581 | J48: =I48/H48 -> 169.05683 | K48: =SUM(K31:K47) -> 902.48 | L48: =SUM(L31:L47) -> 367662 | M48: =SUM(M31:M47) -> 22 | N48: =SUM(N31:N47) -> 4541.92 | O48: =K48/N48 -> 0.19870011 | P48: =N48/K48 -> 5.0327099 | Q48: =K48/D48 -> 0.042023936 | R48: =N48/D48 -> 0.21149428 | S48: =SUM(S31:S47) -> 16933.46 | T48: =K48/M48 -> 41.021818 | U48: =IFERROR((D48-#REF!)/D48,) | V48: =IFERROR((F48-#REF!)/F48,) | W48: =IFERROR((D48-monthly_reporting_2021!E49)/D48, ) | X48: =IFERROR((F48-monthly_reporting_2021!F49)/F48, )
B49: 45655 | C49: AirDoctor | D49: 8188.57 | F49: 27 | G49: 28 | H49: =F49/G49 -> 0.96428571 | I49: =D49/F49 -> 303.28037 | J49: =I49/H49 -> 314.51298 | K49: 129.44 | L49: 29413 | M49: 10 | N49: 1910.85 | O49: =K49/N49 -> 0.067739488 | P49: =N49/K49 -> 14.762438 | Q49: =K49/D49 -> 0.0158074 | R49: =N49/D49 -> 0.23335576 | S49: =D49-N49 -> 6277.72 | T49: =K49/M49 -> 12.944
C50: AquaTru | D50: 6119.25 | F50: 47 | G50: 52 | H50: =F50/G50 -> 0.90384615 | I50: =D50/F50 -> 130.19681 | J50: =I50/H50 -> 144.04753 | K50: 150.31 | L50: 24899 | M50: 2 | N50: 59.95 | O50: =K50/N50 -> 2.507256 | P50: =N50/K50 -> 0.39884239 | Q50: =K50/D50 -> 0.024563468 | R50: =N50/D50 -> 0.0097969522 | S50: =D50-N50 -> 6059.3 | T50: =K50/M50 -> 75.155
C51: Beflexible | D51: 0 | F51: 0 | G51: 0 | H51: =F51/G51 -> #DIV/0! | I51: =D51/F51 -> #DIV/0! | J51: =I51/H51 -> #DIV/0! | K51: 0 | L51: 0 | M51: 0 | N51: 0 | O51: =K51/N51 -> #DIV/0! | P51: =N51/K51 -> #DIV/0! | Q51: =K51/D51 -> #DIV/0! | R51: =N51/D51 -> #DIV/0! | S51: =D51-N51 -> 0 | T51: =K51/M51 -> #DIV/0!
C52: Better Bladder | D52: 0 | F52: 0 | G52: 0 | H52: =F52/G52 -> #DIV/0! | I52: =D52/F52 -> #DIV/0! | J52: =I52/H52 -> #DIV/0! | K52: 0 | L52: 0 | M52: 0 | N52: 0 | O52: =K52/N52 -> #DIV/0! | P52: =N52/K52 -> #DIV/0! | Q52: =K52/D52 -> #DIV/0! | R52: =N52/D52 -> #DIV/0! | S52: =D52-N52 -> 0 | T52: =K52/M52 -> #DIV/0!
C53: Cebria | D53: 39 | F53: 1 | G53: 1 | H53: =F53/G53 -> 1 | I53: =D53/F53 -> 39 | J53: =I53/H53 -> 39 | K53: 0 | L53: 0 | M53: 0 | N53: 0 | O53: =K53/N53 -> #DIV/0! | P53: =N53/K53 -> #DIV/0! | Q53: =K53/D53 -> 0 | R53: =N53/D53 -> 0 | S53: =D53-N53 -> 39 | T53: =K53/M53 -> #DIV/0!
C54: GA Grown American | D54: 0 | F54: 0 | G54: 0 | H54: =F54/G54 -> #DIV/0! | I54: =D54/F54 -> #DIV/0! | J54: =I54/H54 -> #DIV/0! | K54: 63.85 | L54: 9126 | M54: 0 | N54: 0 | O54: =K54/N54 -> #DIV/0! | P54: =N54/K54 -> 0 | Q54: =K54/D54 -> #DIV/0! | R54: =N54/D54 -> #DIV/0! | S54: =D54-N54 -> 0 | T54: =K54/M54 -> #DIV/0!
C55: Ideal Prostate | D55: 559.6 | F55: 8 | G55: 8 | H55: =F55/G55 -> 1 | I55: =D55/F55 -> 69.95 | J55: =I55/H55 -> 69.95 | K55: 109.95 | L55: 4948 | M55: 2 | N55: 139.9 | O55: =K55/N55 -> 0.78591851 | P55: =N55/K55 -> 1.2723965 | Q55: =K55/D55 -> 0.19647963 | R55: =N55/D55 -> 0.25 | S55: =D55-N55 -> 419.7 | T55: =K55/M55 -> 54.975
B56: to | C56: Miracle Blade | D56: 787.34 | F56: 15 | G56: 17 | H56: =F56/G56 -> 0.88235294 | I56: =D56/F56 -> 52.489333 | J56: =I56/H56 -> 59.487911 | K56: 181.4 | L56: 21748 | M56: 4 | N56: 86.24 | O56: =K56/N56 -> 2.1034323 | P56: =N56/K56 -> 0.47541345 | Q56: =K56/D56 -> 0.23039602 | R56: =N56/D56 -> 0.10953337 | S56: =D56-N56 -> 701.1 | T56: =K56/M56 -> 45.35
C57: Paint Zoom | D57: 0 | F57: 0 | G57: 0 | H57: =F57/G57 -> #DIV/0! | I57: =D57/F57 -> #DIV/0! | J57: =I57/H57 -> #DIV/0! | K57: 110.73 | L57: 148952 | M57: 0 | N57: 0 | O57: =K57/N57 -> #DIV/0! | P57: =N57/K57 -> 0 | Q57: =K57/D57 -> #DIV/0! | R57: =N57/D57 -> #DIV/0! | S57: =D57-N57 -> 0 | T57: =K57/M57 -> #DIV/0!
C58: Profemin | D58: 219.8 | F58: 4 | G58: 4 | H58: =F58/G58 -> 1 | I58: =D58/F58 -> 54.95 | J58: =I58/H58 -> 54.95 | K58: 0 | L58: 0 | M58: 0 | N58: 0 | O58: =K58/N58 -> #DIV/0! | P58: =N58/K58 -> #DIV/0! | Q58: =K58/D58 -> 0 | R58: =N58/D58 -> 0 | S58: =D58-N58 -> 219.8 | T58: =K58/M58 -> #DIV/0!
C59: Prosvent | D59: 2148.25 | F59: 30 | G59: 29 | H59: =F59/G59 -> 1.0344828 | I59: =D59/F59 -> 71.608333 | J59: =I59/H59 -> 69.221389 | K59: 95.12 | L59: 24865 | M59: 5 | N59: 381.85 | O59: =K59/N59 -> 0.24910305 | P59: =N59/K59 -> 4.0144029 | Q59: =K59/D59 -> 0.044277901 | R59: =N59/D59 -> 0.17774933 | S59: =D59-N59 -> 1766.4 | T59: =K59/M59 -> 19.024
C60: SaniTru | D60: 59.97 | F60: 3 | G60: 2 | H60: =F60/G60 -> 1.5 | I60: =D60/F60 -> 19.99 | J60: =I60/H60 -> 13.326667 | K60: 23.38 | L60: 15937 | M60: 4 | N60: 59.97 | O60: =K60/N60 -> 0.3898616 | P60: =N60/K60 -> 2.5650128 | Q60: =K60/D60 -> 0.3898616 | R60: =N60/D60 -> 1 | S60: =D60-N60 -> 0 | T60: =K60/M60 -> 5.845
C61: Rotorazer Saw | D61: 195 | F61: 1 | G61: 1 | H61: =F61/G61 -> 1 | I61: =D61/F61 -> 195 | J61: =I61/H61 -> 195 | K61: 27.6 | L61: 25799 | M61: 0 | N61: 0 | O61: =K61/N61 -> #DIV/0! | P61: =N61/K61 -> 0 | Q61: =K61/D61 -> 0.14153846 | R61: =N61/D61 -> 0 | S61: =D61-N61 -> 195 | T61: =K61/M61 -> #DIV/0!
C62: Superthotics | D62: 59.95 | F62: 1 | G62: 1 | H62: =F62/G62 -> 1 | I62: =D62/F62 -> 59.95 | J62: =I62/H62 -> 59.95 | K62: 4.81 | L62: 3791 | M62: 0 | N62: 0 | O62: =K62/N62 -> #DIV/0! | P62: =N62/K62 -> 0 | Q62: =K62/D62 -> 0.080233528 | R62: =N62/D62 -> 0 | S62: =D62-N62 -> 59.95 | T62: =K62/M62 -> #DIV/0!
C63: Therabotanics | D63: 679.4 | F63: 12 | G63: 9 | H63: =F63/G63 -> 1.3333333 | I63: =D63/F63 -> 56.616667 | J63: =I63/H63 -> 42.4625 | K63: 0 | L63: 0 | M63: 0 | N63: 0 | O63: =K63/N63 -> #DIV/0! | P63: =N63/K63 -> #DIV/0! | Q63: =K63/D63 -> 0 | R63: =N63/D63 -> 0 | S63: =D63-N63 -> 679.4 | T63: =K63/M63 -> #DIV/0!
C64: WALKFIT | D64: 303.85 | F64: 8 | G64: 15 | H64: =F64/G64 -> 0.53333333 | I64: =D64/F64 -> 37.98125 | J64: =I64/H64 -> 71.214844 | K64: 128.01 | L64: 45345 | M64: 8 | N64: 251.72 | O64: =K64/N64 -> 0.50854124 | P64: =N64/K64 -> 1.9664089 | Q64: =K64/D64 -> 0.4212934 | R64: =N64/D64 -> 0.82843508 | S64: =D64-N64 -> 52.13 | T64: =K64/M64 -> 16.00125
A65: =iferror(if(B65>0,month(B65)&"-"&year(B65),B65),) -> 1-2025 | B65: 45661 | C65: AromaTru | D65: 156.76 | F65: 1 | G65: 1 | H65: =F65/G65 -> 1 | I65: =D65/F65 -> 156.76 | J65: =I65/H65 -> 156.76 | K65: 2.28 | L65: 7662 | M65: 0 | N65: 0 | O65: =K65/N65 -> #DIV/0! | P65: =N65/K65 -> 0 | Q65: =K65/D65 -> 0.014544527 | R65: =N65/D65 -> 0 | S65: =D65-N65 -> 156.76 | T65: =K65/M65 -> #DIV/0!
A66: =iferror(if(B66>0,month(B66)&"-"&year(B66),B66),) | B66: 2025 - Week 1 | D66: =SUM(D49:D65) -> 19516.74 | F66: =SUM(F49:F65) -> 158 | G66: =SUM(G49:G65) -> 168 | H66: =F66/G66 -> 0.94047619 | I66: =D66/F66 -> 123.52367 | J66: =I66/H66 -> 131.34162 | K66: =SUM(K49:K65) -> 1026.88 | L66: =SUM(L49:L65) -> 362485 | M66: =SUM(M49:M65) -> 35 | N66: =SUM(N49:N65) -> 2890.48 | O66: =K66/N66 -> 0.35526279 | P66: =N66/K66 -> 2.8148177 | Q66: =K66/D66 -> 0.052615345 | R66: =N66/D66 -> 0.1481026 | S66: =SUM(S49:S65) -> 16626.26 | T66: =K66/M66 -> 29.339429 | U66: =IFERROR((D66-#REF!)/D66,) | V66: =IFERROR((F66-#REF!)/F66,) | W66: =IFERROR((D66-monthly_reporting_2021!E49)/D66, ) | X66: =IFERROR((F66-monthly_reporting_2021!F49)/F66, )
B67: 45662 | C67: AirDoctor | D67: 7753.96 | F67: 24 | G67: 26 | H67: =F67/G67 -> 0.92307692 | I67: =D67/F67 -> 323.08167 | J67: =I67/H67 -> 350.00514 | K67: 169.02 | L67: 44579 | M67: 16 | N67: 933.8 | O67: =K67/N67 -> 0.18100236 | P67: =N67/K67 -> 5.52479 | Q67: =K67/D67 -> 0.021797894 | R67: =N67/D67 -> 0.12042879 | S67: =D67-N67 -> 6820.16 | T67: =K67/M67 -> 10.56375
C68: AquaTru | D68: 1654.48 | F68: 21 | G68: 27 | H68: =F68/G68 -> 0.77777778 | I68: =D68/F68 -> 78.784762 | J68: =I68/H68 -> 101.29469 | K68: 104.29 | L68: 25301 | M68: 4 | N68: 951.9 | O68: =K68/N68 -> 0.10955983 | P68: =N68/K68 -> 9.1274331 | Q68: =K68/D68 -> 0.063034911 | R68: =N68/D68 -> 0.57534694 | S68: =D68-N68 -> 702.58 | T68: =K68/M68 -> 26.0725
C69: Beflexible | D69: 0 | F69: 0 | G69: 0 | H69: =F69/G69 -> #DIV/0! | I69: =D69/F69 -> #DIV/0! | J69: =I69/H69 -> #DIV/0! | K69: 0 | L69: 0 | M69: 0 | N69: 0 | O69: =K69/N69 -> #DIV/0! | P69: =N69/K69 -> #DIV/0! | Q69: =K69/D69 -> #DIV/0! | R69: =N69/D69 -> #DIV/0! | S69: =D69-N69 -> 0 | T69: =K69/M69 -> #DIV/0!
C70: Better Bladder | D70: 0 | F70: 0 | G70: 0 | H70: =F70/G70 -> #DIV/0! | I70: =D70/F70 -> #DIV/0! | J70: =I70/H70 -> #DIV/0! | K70: 0 | L70: 0 | M70: 0 | N70: 0 | O70: =K70/N70 -> #DIV/0! | P70: =N70/K70 -> #DIV/0! | Q70: =K70/D70 -> #DIV/0! | R70: =N70/D70 -> #DIV/0! | S70: =D70-N70 -> 0 | T70: =K70/M70 -> #DIV/0!
C71: Cebria | D71: 0 | F71: 0 | G71: 0 | H71: =F71/G71 -> #DIV/0! | I71: =D71/F71 -> #DIV/0! | J71: =I71/H71 -> #DIV/0! | K71: 0 | L71: 0 | M71: 0 | N71: 0 | O71: =K71/N71 -> #DIV/0! | P71: =N71/K71 -> #DIV/0! | Q71: =K71/D71 -> #DIV/0! | R71: =N71/D71 -> #DIV/0! | S71: =D71-N71 -> 0 | T71: =K71/M71 -> #DIV/0!
C72: GA Grown American | D72: 64.95 | F72: 1 | G72: 1 | H72: =F72/G72 -> 1 | I72: =D72/F72 -> 64.95 | J72: =I72/H72 -> 64.95 | K72: 42.63 | L72: 7041 | M72: 3 | N72: 184.93 | O72: =K72/N72 -> 0.23051966 | P72: =N72/K72 -> 4.3380249 | Q72: =K72/D72 -> 0.65635104 | R72: =N72/D72 -> 2.8472671 | S72: =D72-N72 -> -119.98 | T72: =K72/M72 -> 14.21
C73: Ideal Prostate | D73: 929.86 | F73: 14 | G73: 14 | H73: =F73/G73 -> 1 | I73: =D73/F73 -> 66.418571 | J73: =I73/H73 -> 66.418571 | K73: 123.76 | L73: 5860 | M73: 3 | N73: 199.85 | O73: =K73/N73 -> 0.61926445 | P73: =N73/K73 -> 1.614819 | Q73: =K73/D73 -> 0.1330953 | R73: =N73/D73 -> 0.21492483 | S73: =D73-N73 -> 730.01 | T73: =K73/M73 -> 41.253333
B74: to | C74: Miracle Blade | D74: 1117.44 | F74: 19 | G74: 20 | H74: =F74/G74 -> 0.95 | I74: =D74/F74 -> 58.812632 | J74: =I74/H74 -> 61.908033 | K74: 143.4 | L74: 20285 | M74: 7 | N74: 107.8 | O74: =K74/N74 -> 1.3302412 | P74: =N74/K74 -> 0.75174338 | Q74: =K74/D74 -> 0.12832904 | R74: =N74/D74 -> 0.096470504 | S74: =D74-N74 -> 1009.64 | T74: =K74/M74 -> 20.485714
C75: Paint Zoom | D75: 99.95 | F75: 1 | G75: 1 | H75: =F75/G75 -> 1 | I75: =D75/F75 -> 99.95 | J75: =I75/H75 -> 99.95 | K75: 108.68 | L75: 119332 | M75: 0 | N75: 0 | O75: =K75/N75 -> #DIV/0! | P75: =N75/K75 -> 0 | Q75: =K75/D75 -> 1.0873437 | R75: =N75/D75 -> 0 | S75: =D75-N75 -> 99.95 | T75: =K75/M75 -> #DIV/0!
C76: Profemin | D76: -54.95 | F76: -1 | G76: 0 | H76: =F76/G76 -> #DIV/0! | I76: =D76/F76 -> 54.95 | J76: =I76/H76 -> #DIV/0! | K76: 0 | L76: 0 | M76: 0 | N76: 0 | O76: =K76/N76 -> #DIV/0! | P76: =N76/K76 -> #DIV/0! | Q76: =K76/D76 -> 0 | R76: =N76/D76 -> 0 | S76: =D76-N76 -> -54.95 | T76: =K76/M76 -> #DIV/0!
C77: Prosvent | D77: 2116.55 | F77: 32 | G77: 29 | H77: =F77/G77 -> 1.1034483 | I77: =D77/F77 -> 66.142188 | J77: =I77/H77 -> 59.941357 | K77: 119.38 | L77: 28955 | M77: 12 | N77: 1170.25 | O77: =K77/N77 -> 0.10201239 | P77: =N77/K77 -> 9.8027308 | Q77: =K77/D77 -> 0.056403109 | R77: =N77/D77 -> 0.55290449 | S77: =D77-N77 -> 946.3 | T77: =K77/M77 -> 9.9483333
C78: SaniTru | D78: 29.98 | F78: 2 | G78: 2 | H78: =F78/G78 -> 1 | I78: =D78/F78 -> 14.99 | J78: =I78/H78 -> 14.99 | K78: 16.17 | L78: 22820 | M78: 0 | N78: 0 | O78: =K78/N78 -> #DIV/0! | P78: =N78/K78 -> 0 | Q78: =K78/D78 -> 0.53935957 | R78: =N78/D78 -> 0 | S78: =D78-N78 -> 29.98 | T78: =K78/M78 -> #DIV/0!
C79: Rotorazer Saw | D79: 39 | F79: 0 | G79: 1 | H79: =F79/G79 -> 0 | I79: =D79/F79 -> #DIV/0! | J79: =I79/H79 -> #DIV/0! | K79: 13.25 | L79: 21425 | M79: 0 | N79: 0 | O79: =K79/N79 -> #DIV/0! | P79: =N79/K79 -> 0 | Q79: =K79/D79 -> 0.33974359 | R79: =N79/D79 -> 0 | S79: =D79-N79 -> 39 | T79: =K79/M79 -> #DIV/0!
C80: Superthotics | D80: 59.95 | F80: 1 | G80: 1 | H80: =F80/G80 -> 1 | I80: =D80/F80 -> 59.95 | J80: =I80/H80 -> 59.95 | K80: 4.85 | L80: 1339 | M80: 1 | N80: 59.95 | O80: =K80/N80 -> 0.080900751 | P80: =N80/K80 -> 12.360825 | Q80: =K80/D80 -> 0.080900751 | R80: =N80/D80 -> 1 | S80: =D80-N80 -> 0 | T80: =K80/M80 -> 4.85
C81: Therabotanics | D81: 419.93 | F81: 7 | G81: 6 | H81: =F81/G81 -> 1.1666667 | I81: =D81/F81 -> 59.99 | J81: =I81/H81 -> 51.42 | K81: 0 | L81: 37401 | M81: 0 | N81: 251.72 | O81: =K81/N81 -> 0 | P81: =N81/K81 -> #DIV/0! | Q81: =K81/D81 -> 0 | R81: =N81/D81 -> 0.59943324 | S81: =D81-N81 -> 168.21 | T81: =K81/M81 -> #DIV/0!
C82: WALKFIT | D82: 472.87 | F82: 13 | G82: 13 | H82: =F82/G82 -> 1 | I82: =D82/F82 -> 36.374615 | J82: =I82/H82 -> 36.374615 | K82: 120.98 | L82: 0 | M82: 8 | N82: 0 | O82: =K82/N82 -> #DIV/0! | P82: =N82/K82 -> 0 | Q82: =K82/D82 -> 0.25584199 | R82: =N82/D82 -> 0 | S82: =D82-N82 -> 472.87 | T82: =K82/M82 -> 15.1225
A83: =iferror(if(B83>0,month(B83)&"-"&year(B83),B83),) -> 1-2025 | B83: 45668 | C83: AromaTru | D83: 0 | F83: 0 | G83: 0 | H83: =F83/G83 -> #DIV/0! | I83: =D83/F83 -> #DIV/0! | J83: =I83/H83 -> #DIV/0! | K83: 3.71 | L83: 6184 | M83: 0 | N83: 0 | O83: =K83/N83 -> #DIV/0! | P83: =N83/K83 -> 0 | Q83: =K83/D83 -> #DIV/0! | R83: =N83/D83 -> #DIV/0! | S83: =D83-N83 -> 0 | T83: =K83/M83 -> #DIV/0!
A84: =iferror(if(B84>0,month(B84)&"-"&year(B84),B84),) | B84: 2025 - Week 2 | D84: =SUM(D67:D83) -> 14703.97 | F84: =SUM(F67:F83) -> 134 | G84: =SUM(G67:G83) -> 141 | H84: =F84/G84 -> 0.95035461 | I84: =D84/F84 -> 109.73112 | J84: =I84/H84 -> 115.46334 | K84: =SUM(K67:K83) -> 970.12 | L84: =SUM(L67:L83) -> 340522 | M84: =SUM(M67:M83) -> 54 | N84: =SUM(N67:N83) -> 3860.2 | O84: =K84/N84 -> 0.2513134 | P84: =N84/K84 -> 3.9790954 | Q84: =K84/D84 -> 0.06597674 | R84: =N84/D84 -> 0.26252774 | S84: =SUM(S67:S83) -> 10843.77 | T84: =K84/M84 -> 17.965185 | U84: =IFERROR((D84-#REF!)/D84,) | V84: =IFERROR((F84-#REF!)/F84,) | W84: =IFERROR((D84-monthly_reporting_2021!E49)/D84, ) | X84: =IFERROR((F84-monthly_reporting_2021!F49)/F84, )
B85: 45669 | C85: AirDoctor | D85: 10610.64 | F85: 26 | G85: 31 | H85: =F85/G85 -> 0.83870968 | I85: =D85/F85 -> 408.10154 | J85: =I85/H85 -> 486.5826 | K85: 89.05 | L85: 25999 | M85: 10 | N85: 2795.9 | O85: =K85/N85 -> 0.031850209 | P85: =N85/K85 -> 31.396968 | Q85: =K85/D85 -> 0.0083925192 | R85: =N85/D85 -> 0.26349966 | S85: =D85-N85 -> 7814.74 | T85: =K85/M85 -> 8.905
C86: AquaTru | D86: -422.05 | F86: 14 | G86: 20 | H86: =F86/G86 -> 0.7 | I86: =D86/F86 -> -30.146429 | J86: =I86/H86 -> -43.066327 | K86: 129.86 | L86: 35081 | M86: 1 | N86: 0 | O86: =K86/N86 -> #DIV/0! | P86: =N86/K86 -> 0 | Q86: =K86/D86 -> -0.30768866 | R86: =N86/D86 -> 0 | S86: =D86-N86 -> -422.05 | T86: =K86/M86 -> 129.86
C87: Beflexible | D87: 0 | F87: 0 | G87: 0 | H87: =F87/G87 -> #DIV/0! | I87: =D87/F87 -> #DIV/0! | J87: =I87/H87 -> #DIV/0! | K87: 0 | L87: 0 | M87: 0 | N87: 0 | O87: =K87/N87 -> #DIV/0! | P87: =N87/K87 -> #DIV/0! | Q87: =K87/D87 -> #DIV/0! | R87: =N87/D87 -> #DIV/0! | S87: =D87-N87 -> 0 | T87: =K87/M87 -> #DIV/0!
C88: Better Bladder | D88: 251.8 | F88: 4 | G88: 2 | H88: =F88/G88 -> 2 | I88: =D88/F88 -> 62.95 | J88: =I88/H88 -> 31.475 | K88: 0 | L88: 0 | M88: 0 | N88: 0 | O88: =K88/N88 -> #DIV/0! | P88: =N88/K88 -> #DIV/0! | Q88: =K88/D88 -> 0 | R88: =N88/D88 -> 0 | S88: =D88-N88 -> 251.8 | T88: =K88/M88 -> #DIV/0!
C89: Cebria | D89: 0 | F89: 0 | G89: 0 | H89: =F89/G89 -> #DIV/0! | I89: =D89/F89 -> #DIV/0! | J89: =I89/H89 -> #DIV/0! | K89: 0 | L89: 0 | M89: 0 | N89: 0 | O89: =K89/N89 -> #DIV/0! | P89: =N89/K89 -> #DIV/0! | Q89: =K89/D89 -> #DIV/0! | R89: =N89/D89 -> #DIV/0! | S89: =D89-N89 -> 0 | T89: =K89/M89 -> #DIV/0!
C90: GA Grown American | D90: 0 | F90: 0 | G90: 0 | H90: =F90/G90 -> #DIV/0! | I90: =D90/F90 -> #DIV/0! | J90: =I90/H90 -> #DIV/0! | K90: 2.13 | L90: 1611 | M90: 0 | N90: 0 | O90: =K90/N90 -> #DIV/0! | P90: =N90/K90 -> 0 | Q90: =K90/D90 -> #DIV/0! | R90: =N90/D90 -> #DIV/0! | S90: =D90-N90 -> 0 | T90: =K90/M90 -> #DIV/0!
C91: Ideal Prostate | D91: 569.83 | F91: 9 | G91: 9 | H91: =F91/G91 -> 1 | I91: =D91/F91 -> 63.314444 | J91: =I91/H91 -> 63.314444 | K91: 302.46 | L91: 6203 | M91: 1 | N91: 69.95 | O91: =K91/N91 -> 4.3239457 | P91: =N91/K91 -> 0.23127025 | Q91: =K91/D91 -> 0.53078988 | R91: =N91/D91 -> 0.12275591 | S91: =D91-N91 -> 499.88 | T91: =K91/M91 -> 302.46
B92: to | C92: Miracle Blade | D92: 1344.93 | F92: 27 | G92: 26 | H92: =F92/G92 -> 1.0384615 | I92: =D92/F92 -> 49.812222 | J92: =I92/H92 -> 47.967325 | K92: 153.1 | L92: 17899 | M92: 8 | N92: 249.74 | O92: =K92/N92 -> 0.61303756 | P92: =N92/K92 -> 1.6312214 | Q92: =K92/D92 -> 0.11383492 | R92: =N92/D92 -> 0.18568996 | S92: =D92-N92 -> 1095.19 | T92: =K92/M92 -> 19.1375
C93: Paint Zoom | D93: 0 | F93: 0 | G93: 0 | H93: =F93/G93 -> #DIV/0! | I93: =D93/F93 -> #DIV/0! | J93: =I93/H93 -> #DIV/0! | K93: 73.57 | L93: 99519 | M93: 0 | N93: 0 | O93: =K93/N93 -> #DIV/0! | P93: =N93/K93 -> 0 | Q93: =K93/D93 -> #DIV/0! | R93: =N93/D93 -> #DIV/0! | S93: =D93-N93 -> 0 | T93: =K93/M93 -> #DIV/0!
C94: Profemin | D94: 54.95 | F94: 1 | G94: 1 | H94: =F94/G94 -> 1 | I94: =D94/F94 -> 54.95 | J94: =I94/H94 -> 54.95 | K94: 0 | L94: 0 | M94: 0 | N94: 0 | O94: =K94/N94 -> #DIV/0! | P94: =N94/K94 -> #DIV/0! | Q94: =K94/D94 -> 0 | R94: =N94/D94 -> 0 | S94: =D94-N94 -> 54.95 | T94: =K94/M94 -> #DIV/0!
C95: Prosvent | D95: 613.44 | F95: 15 | G95: 16 | H95: =F95/G95 -> 0.9375 | I95: =D95/F95 -> 40.896 | J95: =I95/H95 -> 43.6224 | K95: 39.18 | L95: 5351 | M95: 8 | N95: 524 | O95: =K95/N95 -> 0.074770992 | P95: =N95/K95 -> 13.37417 | Q95: =K95/D95 -> 0.063869327 | R95: =N95/D95 -> 0.85419927 | S95: =D95-N95 -> 89.44 | T95: =K95/M95 -> 4.8975
C96: SaniTru | D96: 49.95 | F96: 5 | G96: 4 | H96: =F96/G96 -> 1.25 | I96: =D96/F96 -> 9.99 | J96: =I96/H96 -> 7.992 | K96: 9.31 | L96: 24144 | M96: 2 | N96: 19.99 | O96: =K96/N96 -> 0.46573287 | P96: =N96/K96 -> 2.1471536 | Q96: =K96/D96 -> 0.18638639 | R96: =N96/D96 -> 0.4002002 | S96: =D96-N96 -> 29.96 | T96: =K96/M96 -> 4.655
C97: Rotorazer Saw | D97: 344 | F97: 2 | G97: 2 | H97: =F97/G97 -> 1 | I97: =D97/F97 -> 172 | J97: =I97/H97 -> 172 | K97: 16.25 | L97: 21537 | M97: 1 | N97: 195 | O97: =K97/N97 -> 0.083333333 | P97: =N97/K97 -> 12 | Q97: =K97/D97 -> 0.047238372 | R97: =N97/D97 -> 0.56686047 | S97: =D97-N97 -> 149 | T97: =K97/M97 -> 16.25
C98: Superthotics | D98: 0 | F98: 0 | G98: 0 | H98: =F98/G98 -> #DIV/0! | I98: =D98/F98 -> #DIV/0! | J98: =I98/H98 -> #DIV/0! | K98: 1.89 | L98: 1230 | M98: 0 | N98: 0 | O98: =K98/N98 -> #DIV/0! | P98: =N98/K98 -> 0 | Q98: =K98/D98 -> #DIV/0! | R98: =N98/D98 -> #DIV/0! | S98: =D98-N98 -> 0 | T98: =K98/M98 -> #DIV/0!
C99: Therabotanics | D99: 0 | F99: 0 | G99: 0 | H99: =F99/G99 -> #DIV/0! | I99: =D99/F99 -> #DIV/0! | J99: =I99/H99 -> #DIV/0! | K99: 0 | L99: 0 | M99: 0 | N99: 0 | O99: =K99/N99 -> #DIV/0! | P99: =N99/K99 -> #DIV/0! | Q99: =K99/D99 -> #DIV/0! | R99: =N99/D99 -> #DIV/0! | S99: =D99-N99 -> 0 | T99: =K99/M99 -> #DIV/0!
C100: WALKFIT | D100: 940.35 | F100: 26 | G100: 25 | H100: =F100/G100 -> 1.04 | I100: =D100/F100 -> 36.167308 | J100: =I100/H100 -> 34.776257 | K100: 111.95 | L100: 38466 | M100: 14 | N100: 323.64 | O100: =K100/N100 -> 0.34590903 | P100: =N100/K100 -> 2.8909335 | Q100: =K100/D100 -> 0.11905142 | R100: =N100/D100 -> 0.34416972 | S100: =D100-N100 -> 616.71 | T100: =K100/M100 -> 7.9964286
A101: =iferror(if(B101>0,month(B101)&"-"&year(B101),B101),) -> 1-2025 | B101: 45675 | C101: AromaTru | D101: 0 | F101: 0 | G101: 0 | H101: =F101/G101 -> #DIV/0! | I101: =D101/F101 -> #DIV/0! | J101: =I101/H101 -> #DIV/0! | K101: 5.13 | L101: 7342 | M101: 0 | N101: 0 | O101: =K101/N101 -> #DIV/0! | P101: =N101/K101 -> 0 | Q101: =K101/D101 -> #DIV/0! | R101: =N101/D101 -> #DIV/0! | S101: =D101-N101 -> 0 | T101: =K101/M101 -> #DIV/0!
A102: =iferror(if(B102>0,month(B102)&"-"&year(B102),B102),) | B102: 2025 - Week 3 | D102: =SUM(D85:D101) -> 14357.84 | F102: =SUM(F85:F101) -> 129 | G102: =SUM(G85:G101) -> 136 | H102: =F102/G102 -> 0.94852941 | I102: =D102/F102 -> 111.30109 | J102: =I102/H102 -> 117.34068 | K102: =SUM(K85:K101) -> 933.88 | L102: =SUM(L85:L101) -> 284382 | M102: =SUM(M85:M101) -> 45 | N102: =SUM(N85:N101) -> 4178.22 | O102: =K102/N102 -> 0.22351145 | P102: =N102/K102 -> 4.4740438 | Q102: =K102/D102 -> 0.06504321 | R102: =N102/D102 -> 0.29100617 | S102: =SUM(S85:S101) -> 10179.62 | T102: =K102/M102 -> 20.752889 | U102: =IFERROR((D102-#REF!)/D102,) | V102: =IFERROR((F102-#REF!)/F102,) | W102: =IFERROR((D102-monthly_reporting_2021!E49)/D102, ) | X102: =IFERROR((F102-monthly_reporting_2021!F49)/F102, )
...

Sheet Sheet4
A1: WALMART - DATA SOURCES: https://seller.walmart.com/analytics/overview/item-sale; https://seller.walmart.com/analytics/reports; And Intentwise
C2: WEEKLY PERFORMANCE | X2: =(#REF!+#REF!+#REF!+#REF!)-(monthly_reporting_2021!D17+monthly_reporting_2021!D23+monthly_reporting_2021!D29+monthly_reporting_2021!D35) -> #REF! | Y2: =((#REF!+#REF!+#REF!+#REF!)-(monthly_reporting_2021!E17+monthly_reporting_2021!E23+monthly_reporting_2021!E29+monthly_reporting_2021!E35))/(#REF!+#REF!+#REF!+#REF!) -> #REF!
C3: Total Sales | F3: Total Orders | K3: Total Units Sold
C4: =VLOOKUP("Current Week",$B$11:$X$847,match("SALES",$B$11:$X$11,0),FALSE) -> 45850.88 | F4: =VLOOKUP("Current Week",$B$11:$X$847,match("Units Sold",$B$11:$X$11,0),FALSE) -> 342 | K4: =VLOOKUP("Current Week",$B$11:$X$847,match("Ordered Items",$B$11:$X$11,0),FALSE) -> 362
C5: =(C4-(VLOOKUP("Previous Week",$B$11:$X$852,match("SALES",$B$11:$X$11,0),FALSE)))/C4 -> 0.19141552 | F5: =(F4-(VLOOKUP("Previous Week",$B$11:$X$852,match("Units Sold",$B$11:$X$11,0),FALSE)))/F4 -> 0.28362573 | K5: =(K4-(VLOOKUP("Previous Week",$B$11:$X$852,match("Ordered Items",$B$11:$X$11,0),FALSE)))/K4 -> 0.26519337
C7: Advertising Sales | F7: Advertising Spend | K7: ACoS
C8: =VLOOKUP("Current Week",$B$11:$X$847,match("AD SALES",$B$11:$X$11,0),FALSE) -> 32577.4 | F8: =VLOOKUP("Current Week",$B$11:$X$847,match("SP AD SPEND",$B$11:$X$11,0),FALSE) -> 10686.6 | K8: =F8/C8 -> 0.32803723
C9: =(C8-(VLOOKUP("Previous Week",$B$11:$X$852,match("AD SALES",$B$11:$X$11,0),FALSE)))/C8 -> -0.058414115 | F9: =(F8-(VLOOKUP("Previous Week",$B$11:$X$852,match("SP AD SPEND",$B$11:$X$11,0),FALSE)))/F8 -> -0.099436678 | K9: =(K8-(VLOOKUP("Previous Week",$B$11:$X$852,match("ACOS",$B$11:$X$11,0),FALSE)))/K8 -> -0.038758518
D10: SALES METRICS | L10: ADVERTISING PERFORMANCE | V10: MoM | X10: YoY
A11: Month-Code | B11: DATE | C11: BRAND | D11: SALES | E11: UNITS SOLD | F11: ORDERED ITEMS | G11: UNITS PER ORDER | H11: SALES PER ORDER | I11: ASP | J11: SP AD SPEND | K11: IMPRESSIONS | L11: UNIT SALES | M11: AD SALES | N11: ACoS | O11: ROAS (return on ad send) | P11: TACoS (Total Advertsing Cost of Sales) | Q11: REVENUE PERCENTAGE OF AD SALES | R11: ORGANIC SALES | S11: CPO | T11: SALES | U11: UNITS | V11: SALES | W11: UNITS
B13: 45711 | C13: AirDoctor | D13: 1138.6 | E13: 9 | F13: 10 | G13: =E13/F13 -> 0.9 | H13: =D13/E13 -> 126.51111 | I13: =H13/G13 -> 140.5679 | J13: 652.84 | K13: 91286 | L13: 5 | M13: 289.8 | N13: =J13/M13 -> 2.252726 | O13: =M13/J13 -> 0.44390662 | P13: =J13/D13 -> 0.57337081 | Q13: =M13/D13 -> 0.2545231 | R13: =D13-M13 -> 848.8 | S13: =J13/L13 -> 130.568
C14: AquaTru | D14: 7251.12 | E14: 45 | F14: 47 | G14: =E14/F14 -> 0.95744681 | H14: =D14/E14 -> 161.136 | I14: =H14/G14 -> 168.2976 | J14: 325.06 | K14: 109626 | L14: 10 | M14: 1276.85 | N14: =J14/M14 -> 0.25457963 | O14: =M14/J14 -> 3.9280441 | P14: =J14/D14 -> 0.044828937 | Q14: =M14/D14 -> 0.17609004 | R14: =D14-M14 -> 5974.27 | S14: =J14/L14 -> 32.506
C15: Beflexible | D15: 0 | E15: 0 | F15: 0 | G15: =E15/F15 -> #DIV/0! | H15: =D15/E15 -> #DIV/0! | I15: =H15/G15 -> #DIV/0! | J15: 17.22 | K15: 128 | L15: 0 | M15: 0 | N15: =(J15/M15) -> #DIV/0! | O15: =M15/J15 -> 0 | P15: =J15/D15 -> #DIV/0! | Q15: =M15/D15 -> #DIV/0! | R15: =D15-M15 -> 0 | S15: =J15/L15 -> #DIV/0!
C16: Better Bladder | D16: 269.75 | E16: 5 | F16: 3 | G16: =E16/F16 -> 1.6666667 | H16: =D16/E16 -> 53.95 | I16: =H16/G16 -> 32.37 | J16: 163.92 | K16: 9083 | L16: 0 | M16: 0 | N16: =J16/M16 -> #DIV/0! | O16: =M16/J16 -> 0 | P16: =J16/D16 -> 0.60767377 | Q16: =M16/D16 -> 0 | R16: =D16-M16 -> 269.75 | S16: =J16/L16 -> #DIV/0!
C17: Cebria | D17: 0 | E17: 0 | F17: 0 | G17: =E17/F17 -> #DIV/0! | H17: =D17/E17 -> #DIV/0! | I17: =H17/G17 -> #DIV/0! | J17: 0 | K17: 0 | L17: 0 | M17: 0 | N17: =J17/M17 -> #DIV/0! | O17: =M17/J17 -> #DIV/0! | P17: =J17/D17 -> #DIV/0! | Q17: =M17/D17 -> #DIV/0! | R17: =D17-M17 -> 0 | S17: =J17/L17 -> #DIV/0!
C18: GA Grown American | D18: 455.81 | E18: 7 | F18: 6 | G18: =E18/F18 -> 1.1666667 | H18: =D18/E18 -> 65.115714 | I18: =H18/G18 -> 55.813469 | J18: 49.89 | K18: 6245 | L18: 2 | M18: 124.94 | N18: =J18/M18 -> 0.39931167 | O18: =M18/J18 -> 2.5043095 | P18: =J18/D18 -> 0.1094535 | Q18: =M18/D18 -> 0.27410544 | R18: =D18-M18 -> 330.87 | S18: =J18/L18 -> 24.945
C19: Ideal Prostate | D19: 500.16 | E19: 8 | F19: 8 | G19: =E19/F19 -> 1 | H19: =D19/E19 -> 62.52 | I19: =H19/G19 -> 62.52 | J19: 67.81 | K19: 6402 | L19: 1 | M19: 59.95 | N19: =J19/M19 -> 1.1311093 | O19: =M19/J19 -> 0.88408789 | P19: =J19/D19 -> 0.13557662 | Q19: =M19/D19 -> 0.11986164 | R19: =D19-M19 -> 440.21 | S19: =J19/L19 -> 67.81
B20: to | C20: Miracle Blade | D20: 614.92 | E20: 13 | F20: 12 | G20: =E20/F20 -> 1.0833333 | H20: =D20/E20 -> 47.301538 | I20: =H20/G20 -> 43.662959 | J20: 123.69 | K20: 14424 | L20: 5 | M20: 107.8 | N20: =J20/M20 -> 1.1474026 | O20: =M20/J20 -> 0.87153367 | P20: =J20/D20 -> 0.20114812 | Q20: =M20/D20 -> 0.17530736 | R20: =D20-M20 -> 507.12 | S20: =J20/L20 -> 24.738
C21: Paint Zoom | D21: 0 | E21: 0 | F21: 0 | G21: =E21/F21 -> #DIV/0! | H21: =D21/E21 -> #DIV/0! | I21: =H21/G21 -> #DIV/0! | J21: 61.54 | K21: 58340 | L21: 2 | M21: 199.9 | N21: =J21/M21 -> 0.30785393 | O21: =M21/J21 -> 3.2482938 | P21: =J21/D21 -> #DIV/0! | Q21: =M21/D21 -> #DIV/0! | R21: =D21-M21 -> -199.9 | S21: =J21/L21 -> 30.77
C22: Profemin | D22: 54.95 | E22: 1 | F22: 1 | G22: =E22/F22 -> 1 | H22: =D22/E22 -> 54.95 | I22: =H22/G22 -> 54.95 | J22: 0 | K22: 0 | L22: 0 | M22: 0 | N22: =J22/M22 -> #DIV/0! | O22: =M22/J22 -> #DIV/0! | P22: =J22/D22 -> 0 | Q22: =M22/D22 -> 0 | R22: =D22-M22 -> 54.95 | S22: =J22/L22 -> #DIV/0!
C23: Prosvent | D23: 201 | E23: 3 | F23: 3 | G23: =E23/F23 -> 1 | H23: =D23/E23 -> 67 | I23: =H23/G23 -> 67 | J23: 52.07 | K23: 7101 | L23: 1 | M23: 67 | N23: =J23/M23 -> 0.77716418 | O23: =M23/J23 -> 1.2867294 | P23: =J23/D23 -> 0.25905473 | Q23: =M23/D23 -> 0.33333333 | R23: =D23-M23 -> 134 | S23: =J23/L23 -> 52.07
C24: SaniTru | D24: 39.98 | E24: 2 | F24: 2 | G24: =E24/F24 -> 1 | H24: =D24/E24 -> 19.99 | I24: =H24/G24 -> 19.99 | J24: 7.73 | K24: 17629 | L24: 0 | M24: 0 | N24: =J24/M24 -> #DIV/0! | O24: =M24/J24 -> 0 | P24: =J24/D24 -> 0.19334667 | Q24: =M24/D24 -> 0 | R24: =D24-M24 -> 39.98 | S24: =J24/L24 -> #DIV/0!
C25: Rotorazer Saw | D25: -195 | E25: -1 | F25: 0 | G25: =E25/F25 -> #DIV/0! | H25: =D25/E25 -> 195 | I25: =H25/G25 -> #DIV/0! | J25: 27.44 | K25: 30342 | L25: 0 | M25: 0 | N25: =J25/M25 -> #DIV/0! | O25: =M25/J25 -> 0 | P25: =J25/D25 -> -0.14071795 | Q25: =M25/D25 -> 0 | R25: =D25-M25 -> -195 | S25: =J25/L25 -> #DIV/0!
C26: Superthotics | D26: 119.9 | E26: 2 | F26: 2 | G26: =E26/F26 -> 1 | H26: =D26/E26 -> 59.95 | I26: =H26/G26 -> 59.95 | J26: 46.2 | K26: 8233 | L26: 0 | M26: 0 | N26: =J26/M26 -> #DIV/0! | O26: =M26/J26 -> 0 | P26: =J26/D26 -> 0.3853211 | Q26: =M26/D26 -> 0 | R26: =D26-M26 -> 119.9 | S26: =J26/L26 -> #DIV/0!
C27: Therabotanics | D27: 620.91 | E27: 11 | F27: 10 | G27: =E27/F27 -> 1.1 | H27: =D27/E27 -> 56.446364 | I27: =H27/G27 -> 51.314876 | J27: 0 | K27: 0 | L27: 0 | M27: 0 | N27: =J27/M27 -> #DIV/0! | O27: =M27/J27 -> #DIV/0! | P27: =J27/D27 -> 0 | Q27: =M27/D27 -> 0 | R27: =D27-M27 -> 620.91 | S27: =J27/L27 -> #DIV/0!
C28: WALKFIT | D28: 834.27 | E28: 23 | F28: 23 | G28: =E28/F28 -> 1 | H28: =D28/E28 -> 36.272609 | I28: =H28/G28 -> 36.272609 | J28: 88.12 | K28: 33459 | L28: 11 | M28: 395.56 | N28: =J28/M28 -> 0.22277278 | O28: =M28/J28 -> 4.4888788 | P28: =J28/D28 -> 0.10562528 | Q28: =M28/D28 -> 0.47413907 | R28: =D28-M28 -> 438.71 | S28: =J28/L28 -> 8.0109091
C29: AromaTru | D29: 0 | E29: 0 | F29: 0 | G29: =E29/F29 -> #DIV/0! | H29: =D29/E29 -> #DIV/0! | I29: =H29/G29 -> #DIV/0! | J29: 3.31 | K29: 10850 | L29: 0 | M29: 0 | N29: =J29/M29 -> #DIV/0! | O29: =M29/J29 -> 0 | P29: =J29/D29 -> #DIV/0! | Q29: =M29/D29 -> #DIV/0! | R29: =D29-M29 -> 0 | S29: =J29/L29 -> #DIV/0!
A30: =iferror(if(B30>0,month(B30)&"-"&year(B30),B30),) -> 3-2025 | B30: 45717 | C30: SEM Campaigns | D30: 0 | E30: 0 | F30: 0 | G30: =E30/F30 -> #DIV/0! | H30: =D30/E30 -> #DIV/0! | I30: =H30/G30 -> #DIV/0! | J30: 22.48 | K30: 3411 | L30: 0 | M30: 0 | N30: =J30/M30 -> #DIV/0! | O30: =M30/J30 -> 0 | P30: =J30/D30 -> #DIV/0! | Q30: =M30/D30 -> #DIV/0! | R30: =D30-M30 -> 0 | S30: =J30/L30 -> #DIV/0!
A31: =iferror(if(B31>0,month(B31)&"-"&year(B31),B31),) | B31: 2025 - Week 9 | D31: =SUM(D13:D30) -> 11906.37 | E31: =SUM(E13:E30) -> 128 | F31: =SUM(F13:F30) -> 127 | G31: =E31/F31 -> 1.007874 | H31: =D31/E31 -> 93.018516 | I31: =H31/G31 -> 92.291808 | J31: =SUM(J13:J30) -> 1709.32 | K31: =SUM(K13:K30) -> 406559 | L31: =SUM(L13:L30) -> 37 | M31: =SUM(M13:M30) -> 2521.8 | N31: =J31/M31 -> 0.67781743 | O31: =M31/J31 -> 1.4753235 | P31: =J31/D31 -> 0.14356349 | Q31: =M31/D31 -> 0.21180259 | R31: =SUM(R13:R30) -> 9384.57 | S31: =J31/L31 -> 46.197838 | T31: =IFERROR((D31-#REF!)/D31,) | U31: =IFERROR((E31-#REF!)/E31,) | V31: =IFERROR((D31-#REF!)/D31, ) | W31: =IFERROR((E31-#REF!)/E31, )
B32: 45718 | C32: AirDoctor | D32: 2124.65 | E32: 10 | F32: 12 | G32: =E32/F32 -> 0.83333333 | H32: =D32/E32 -> 212.465 | I32: =H32/G32 -> 254.958 | J32: 305.72 | K32: 56518 | L32: 0 | M32: 0 | N32: =J32/M32 -> #DIV/0! | O32: =M32/J32 -> 0 | P32: =J32/D32 -> 0.14389194 | Q32: =M32/D32 -> 0 | R32: =D32-M32 -> 2124.65 | S32: =J32/L32 -> #DIV/0!
C33: AquaTru | D33: 1062.04 | E33: 26 | F33: 31 | G33: =E33/F33 -> 0.83870968 | H33: =D33/E33 -> 40.847692 | I33: =H33/G33 -> 48.703018 | J33: 321.68 | K33: 121286 | L33: 8 | M33: 313.65 | N33: =J33/M33 -> 1.0256018 | O33: =M33/J33 -> 0.9750373 | P33: =J33/D33 -> 0.30288878 | Q33: =M33/D33 -> 0.29532786 | R33: =D33-M33 -> 748.39 | S33: =J33/L33 -> 40.21
C34: Beflexible | D34: 0 | E34: 0 | F34: 0 | G34: =E34/F34 -> #DIV/0! | H34: =D34/E34 -> #DIV/0! | I34: =H34/G34 -> #DIV/0! | J34: 12.86 | K34: 129 | L34: 0 | M34: 0 | N34: =(J34/M34) -> #DIV/0! | O34: =M34/J34 -> 0 | P34: =J34/D34 -> #DIV/0! | Q34: =M34/D34 -> #DIV/0! | R34: =D34-M34 -> 0 | S34: =J34/L34 -> #DIV/0!
C35: Better Bladder | D35: 485.55 | E35: 9 | F35: 10 | G35: =E35/F35 -> 0.9 | H35: =D35/E35 -> 53.95 | I35: =H35/G35 -> 59.944444 | J35: 97.44 | K35: 10370 | L35: 8 | M35: 431.6 | N35: =J35/M35 -> 0.2257646 | O35: =M35/J35 -> 4.4293924 | P35: =J35/D35 -> 0.20067964 | Q35: =M35/D35 -> 0.88888889 | R35: =D35-M35 -> 53.95 | S35: =J35/L35 -> 12.18
C36: Cebria | D36: 312 | E36: 8 | F36: 4 | G36: =E36/F36 -> 2 | H36: =D36/E36 -> 39 | I36: =H36/G36 -> 19.5 | J36: 0 | K36: 0 | L36: 0 | M36: 0 | N36: =J36/M36 -> #DIV/0! | O36: =M36/J36 -> #DIV/0! | P36: =J36/D36 -> 0 | Q36: =M36/D36 -> 0 | R36: =D36-M36 -> 312 | S36: =J36/L36 -> #DIV/0!
C37: GA Grown American | D37: 844.35 | E37: 13 | F37: 8 | G37: =E37/F37 -> 1.625 | H37: =D37/E37 -> 64.95 | I37: =H37/G37 -> 39.969231 | J37: 20.46 | K37: 1753 | L37: 8 | M37: 519.6 | N37: =J37/M37 -> 0.039376443 | O37: =M37/J37 -> 25.395894 | P37: =J37/D37 -> 0.024231657 | Q37: =M37/D37 -> 0.61538462 | R37: =D37-M37 -> 324.75 | S37: =J37/L37 -> 2.5575
C38: Ideal Prostate | D38: 479.65 | E38: 7 | F38: 7 | G38: =E38/F38 -> 1 | H38: =D38/E38 -> 68.521429 | I38: =H38/G38 -> 68.521429 | J38: 74.83 | K38: 7026 | L38: 5 | M38: 349.75 | N38: =J38/M38 -> 0.21395282 | O38: =M38/J38 -> 4.6739276 | P38: =J38/D38 -> 0.15600959 | Q38: =M38/D38 -> 0.72917753 | R38: =D38-M38 -> 129.9 | S38: =J38/L38 -> 14.966
B39: to | C39: Miracle Blade | D39: 729.76 | E39: 14 | F39: 14 | G39: =E39/F39 -> 1 | H39: =D39/E39 -> 52.125714 | I39: =H39/G39 -> 52.125714 | J39: 180.09 | K39: 16568 | L39: 6 | M39: 194.01 | N39: =J39/M39 -> 0.92825112 | O39: =M39/J39 -> 1.0772947 | P39: =J39/D39 -> 0.24677976 | Q39: =M39/D39 -> 0.26585453 | R39: =D39-M39 -> 535.75 | S39: =J39/L39 -> 30.015
C40: Paint Zoom | D40: 399.8 | E40: 4 | F40: 4 | G40: =E40/F40 -> 1 | H40: =D40/E40 -> 99.95 | I40: =H40/G40 -> 99.95 | J40: 109.23 | K40: 38575 | L40: 0 | M40: 0 | N40: =J40/M40 -> #DIV/0! | O40: =M40/J40 -> 0 | P40: =J40/D40 -> 0.27321161 | Q40: =M40/D40 -> 0 | R40: =D40-M40 -> 399.8 | S40: =J40/L40 -> #DIV/0!
C41: Profemin | D41: 54.95 | E41: 1 | F41: 1 | G41: =E41/F41 -> 1 | H41: =D41/E41 -> 54.95 | I41: =H41/G41 -> 54.95 | J41: 0 | K41: 0 | L41: 0 | M41: 0 | N41: =J41/M41 -> #DIV/0! | O41: =M41/J41 -> #DIV/0! | P41: =J41/D41 -> 0 | Q41: =M41/D41 -> 0 | R41: =D41-M41 -> 54.95 | S41: =J41/L41 -> #DIV/0!
C42: Prosvent | D42: 122 | E42: 2 | F42: 1 | G42: =E42/F42 -> 2 | H42: =D42/E42 -> 61 | I42: =H42/G42 -> 30.5 | J42: 8.81 | K42: 1185 | L42: 1 | M42: 67 | N42: =J42/M42 -> 0.13149254 | O42: =M42/J42 -> 7.6049943 | P42: =J42/D42 -> 0.072213115 | Q42: =M42/D42 -> 0.54918033 | R42: =D42-M42 -> 55 | S42: =J42/L42 -> 8.81
C43: SaniTru | D43: 19.99 | E43: 1 | F43: 1 | G43: =E43/F43 -> 1 | H43: =D43/E43 -> 19.99 | I43: =H43/G43 -> 19.99 | J43: 9.5 | K43: 18007 | L43: 2 | M43: 39.98 | N43: =J43/M43 -> 0.23761881 | O43: =M43/J43 -> 4.2084211 | P43: =J43/D43 -> 0.47523762 | Q43: =M43/D43 -> 2 | R43: =D43-M43 -> -19.99 | S43: =J43/L43 -> 4.75
C44: Rotorazer Saw | D44: 0 | E44: 0 | F44: 0 | G44: =E44/F44 -> #DIV/0! | H44: =D44/E44 -> #DIV/0! | I44: =H44/G44 -> #DIV/0! | J44: 22.1 | K44: 25445 | L44: 0 | M44: 0 | N44: =J44/M44 -> #DIV/0! | O44: =M44/J44 -> 0 | P44: =J44/D44 -> #DIV/0! | Q44: =M44/D44 -> #DIV/0! | R44: =D44-M44 -> 0 | S44: =J44/L44 -> #DIV/0!
C45: Superthotics | D45: 59.95 | E45: 1 | F45: 1 | G45: =E45/F45 -> 1 | H45: =D45/E45 -> 59.95 | I45: =H45/G45 -> 59.95 | J45: 21.31 | K45: 8535 | L45: 0 | M45: 0 | N45: =J45/M45 -> #DIV/0! | O45: =M45/J45 -> 0 | P45: =J45/D45 -> 0.35546289 | Q45: =M45/D45 -> 0 | R45: =D45-M45 -> 59.95 | S45: =J45/L45 -> #DIV/0!
C46: Therabotanics | D46: 19.95 | E46: 1 | F46: 1 | G46: =E46/F46 -> 1 | H46: =D46/E46 -> 19.95 | I46: =H46/G46 -> 19.95 | J46: 0 | K46: 0 | L46: 0 | M46: 0 | N46: =J46/M46 -> #DIV/0! | O46: =M46/J46 -> #DIV/0! | P46: =J46/D46 -> 0 | Q46: =M46/D46 -> 0 | R46: =D46-M46 -> 19.95 | S46: =J46/L46 -> #DIV/0!
C47: WALKFIT | D47: 655.86 | E47: 20 | F47: 20 | G47: =E47/F47 -> 1 | H47: =D47/E47 -> 32.793 | I47: =H47/G47 -> 32.793 | J47: 77.16 | K47: 34502 | L47: 7 | M47: 251.72 | N47: =J47/M47 -> 0.30653107 | O47: =M47/J47 -> 3.2623121 | P47: =J47/D47 -> 0.11764706 | Q47: =M47/D47 -> 0.38380142 | R47: =D47-M47 -> 404.14 | S47: =J47/L47 -> 11.022857
C48: AromaTru | D48: 0 | E48: 0 | F48: 0 | G48: =E48/F48 -> #DIV/0! | H48: =D48/E48 -> #DIV/0! | I48: =H48/G48 -> #DIV/0! | J48: 3.67 | K48: 7711 | L48: 0 | M48: 0 | N48: =J48/M48 -> #DIV/0! | O48: =M48/J48 -> 0 | P48: =J48/D48 -> #DIV/0! | Q48: =M48/D48 -> #DIV/0! | R48: =D48-M48 -> 0 | S48: =J48/L48 -> #DIV/0!
A49: =iferror(if(B49>0,month(B49)&"-"&year(B49),B49),) -> 3-2025 | B49: 45724 | C49: SEM Campaigns | D49: 0 | E49: 0 | F49: 0 | G49: =E49/F49 -> #DIV/0! | H49: =D49/E49 -> #DIV/0! | I49: =H49/G49 -> #DIV/0! | J49: 114.69 | K49: 16911 | M49: 54.79 | N49: =J49/M49 -> 2.0932652 | O49: =M49/J49 -> 0.47772256 | P49: =J49/D49 -> #DIV/0! | Q49: =M49/D49 -> #DIV/0! | R49: =D49-M49 -> -54.79 | S49: =J49/L49 -> #DIV/0!
A50: =iferror(if(B50>0,month(B50)&"-"&year(B50),B50),) | B50: Week 10 | D50: =SUM(D32:D49) -> 7370.5 | E50: =SUM(E32:E49) -> 117 | F50: =SUM(F32:F49) -> 115 | G50: =E50/F50 -> 1.0173913 | H50: =D50/E50 -> 62.995727 | I50: =H50/G50 -> 61.918876 | J50: =SUM(J32:J49) -> 1379.55 | K50: =SUM(K32:K49) -> 364521 | L50: =SUM(L32:L49) -> 45 | M50: =SUM(M32:M49) -> 2222.1 | N50: =J50/M50 -> 0.62083165 | O50: =M50/J50 -> 1.6107426 | P50: =J50/D50 -> 0.18717183 | Q50: =M50/D50 -> 0.30148565 | R50: =SUM(R32:R49) -> 5148.4 | S50: =J50/L50 -> 30.656667 | T50: =IFERROR((D50-#REF!)/D50,) | U50: =IFERROR((E50-#REF!)/E50,) | V50: =IFERROR((D50-#REF!)/D50, ) | W50: =IFERROR((E50-#REF!)/E50, )
B51: 45725 | C51: AirDoctor | D51: 1856.83 | E51: 7 | F51: 8 | G51: =E51/F51 -> 0.875 | H51: =D51/E51 -> 265.26143 | I51: =H51/G51 -> 303.15592 | J51: 251.1 | K51: 41312 | L51: 2 | M51: 968.95 | N51: =J51/M51 -> 0.2591465 | O51: =M51/J51 -> 3.8588212 | P51: =J51/D51 -> 0.13523047 | Q51: =M51/D51 -> 0.52183022 | R51: =D51-M51 -> 887.88 | S51: =J51/L51 -> 125.55
C52: AquaTru | D52: 3258.7 | E52: 35 | F52: 35 | G52: =E52/F52 -> 1 | H52: =D52/E52 -> 93.105714 | I52: =H52/G52 -> 93.105714 | J52: 326.98 | K52: 112697 | L52: 14 | M52: 804.55 | N52: =J52/M52 -> 0.40641352 | O52: =M52/J52 -> 2.460548 | P52: =J52/D52 -> 0.10034063 | Q52: =M52/D52 -> 0.24689293 | R52: =D52-M52 -> 2454.15 | S52: =J52/L52 -> 23.355714
C53: Beflexible | D53: 0 | E53: 0 | F53: 0 | G53: =E53/F53 -> #DIV/0! | H53: =D53/E53 -> #DIV/0! | I53: =H53/G53 -> #DIV/0! | J53: 24.27 | K53: 151 | L53: 0 | M53: 0 | N53: =(J53/M53) -> #DIV/0! | O53: =M53/J53 -> 0 | P53: =J53/D53 -> #DIV/0! | Q53: =M53/D53 -> #DIV/0! | R53: =D53-M53 -> 0 | S53: =J53/L53 -> #DIV/0!
C54: Better Bladder | D54: 506.55 | E54: 9 | F54: 8 | G54: =E54/F54 -> 1.125 | H54: =D54/E54 -> 56.283333 | I54: =H54/G54 -> 50.02963 | J54: 102.35 | K54: 9361 | L54: 3 | M54: 161.85 | N54: =J54/M54 -> 0.63237566 | O54: =M54/J54 -> 1.5813385 | P54: =J54/D54 -> 0.2020531 | Q54: =M54/D54 -> 0.31951436 | R54: =D54-M54 -> 344.7 | S54: =J54/L54 -> 34.116667
C55: Cebria | D55: 78 | E55: 2 | F55: 1 | G55: =E55/F55 -> 2 | H55: =D55/E55 -> 39 | I55: =H55/G55 -> 19.5 | J55: 0 | K55: 0 | L55: 0 | M55: 0 | N55: =J55/M55 -> #DIV/0! | O55: =M55/J55 -> #DIV/0! | P55: =J55/D55 -> 0 | Q55: =M55/D55 -> 0 | R55: =D55-M55 -> 78 | S55: =J55/L55 -> #DIV/0!
C56: GA Grown American | D56: 0 | E56: 0 | F56: 0 | G56: =E56/F56 -> #DIV/0! | H56: =D56/E56 -> #DIV/0! | I56: =H56/G56 -> #DIV/0! | J56: 0 | K56: 0 | L56: 0 | M56: 0 | N56: =J56/M56 -> #DIV/0! | O56: =M56/J56 -> #DIV/0! | P56: =J56/D56 -> #DIV/0! | Q56: =M56/D56 -> #DIV/0! | R56: =D56-M56 -> 0 | S56: =J56/L56 -> #DIV/0!
C57: Ideal Prostate | D57: 399.7 | E57: 6 | F57: 6 | G57: =E57/F57 -> 1 | H57: =D57/E57 -> 66.616667 | I57: =H57/G57 -> 66.616667 | J57: 75.5 | K57: 10703 | L57: 3 | M57: 209.85 | N57: =J57/M57 -> 0.3597808 | O57: =M57/J57 -> 2.7794702 | P57: =J57/D57 -> 0.18889167 | Q57: =M57/D57 -> 0.52501876 | R57: =D57-M57 -> 189.85 | S57: =J57/L57 -> 25.166667
B58: to | C58: Miracle Blade | D58: 851.99 | E58: 15 | F58: 16 | G58: =E58/F58 -> 0.9375 | H58: =D58/E58 -> 56.799333 | I58: =H58/G58 -> 60.585956 | J58: 111.82 | K58: 18230 | L58: 3 | M58: 193.98 | N58: =J58/M58 -> 0.57645118 | O58: =M58/J58 -> 1.7347523 | P58: =J58/D58 -> 0.13124567 | Q58: =M58/D58 -> 0.22767873 | R58: =D58-M58 -> 658.01 | S58: =J58/L58 -> 37.273333
C59: Paint Zoom | D59: -299.85 | E59: -3 | F59: 0 | G59: =E59/F59 -> #DIV/0! | H59: =D59/E59 -> 99.95 | I59: =H59/G59 -> #DIV/0! | J59: 132.53 | K59: 23977 | L59: 1 | M59: 0 | N59: =J59/M59 -> #DIV/0! | O59: =M59/J59 -> 0 | P59: =J59/D59 -> -0.44198766 | Q59: =M59/D59 -> 0 | R59: =D59-M59 -> -299.85 | S59: =J59/L59 -> 132.53
C60: Profemin | D60: 439.6 | E60: 8 | F60: 6 | G60: =E60/F60 -> 1.3333333 | H60: =D60/E60 -> 54.95 | I60: =H60/G60 -> 41.2125 | J60: 0 | K60: 0 | L60: 0 | M60: 0 | N60: =J60/M60 -> #DIV/0! | O60: =M60/J60 -> #DIV/0! | P60: =J60/D60 -> 0 | Q60: =M60/D60 -> 0 | R60: =D60-M60 -> 439.6 | S60: =J60/L60 -> #DIV/0!
C61: Prosvent | D61: 109.98 | E61: 2 | F61: 1 | G61: =E61/F61 -> 2 | H61: =D61/E61 -> 54.99 | I61: =H61/G61 -> 27.495 | J61: 0 | K61: 0 | L61: 0 | M61: 0 | N61: =J61/M61 -> #DIV/0! | O61: =M61/J61 -> #DIV/0! | P61: =J61/D61 -> 0 | Q61: =M61/D61 -> 0 | R61: =D61-M61 -> 109.98 | S61: =J61/L61 -> #DIV/0!
C62: SaniTru | D62: -38.89 | E62: 2 | F62: 3 | G62: =E62/F62 -> 0.66666667 | H62: =D62/E62 -> -19.445 | I62: =H62/G62 -> -29.1675 | J62: 5.88 | K62: 10967 | L62: 2 | M62: 39.98 | N62: =J62/M62 -> 0.14707354 | O62: =M62/J62 -> 6.7993197 | P62: =J62/D62 -> -0.15119568 | Q62: =M62/D62 -> -1.0280278 | R62: =D62-M62 -> -78.87 | S62: =J62/L62 -> 2.94
C63: Rotorazer Saw | D63: 0 | E63: 0 | F63: 0 | G63: =E63/F63 -> #DIV/0! | H63: =D63/E63 -> #DIV/0! | I63: =H63/G63 -> #DIV/0! | J63: 14.6 | K63: 23765 | L63: 0 | M63: 0 | N63: =J63/M63 -> #DIV/0! | O63: =M63/J63 -> 0 | P63: =J63/D63 -> #DIV/0! | Q63: =M63/D63 -> #DIV/0! | R63: =D63-M63 -> 0 | S63: =J63/L63 -> #DIV/0!
C64: Superthotics | D64: 119.9 | E64: 2 | F64: 2 | G64: =E64/F64 -> 1 | H64: =D64/E64 -> 59.95 | I64: =H64/G64 -> 59.95 | J64: 11.24 | K64: 7724 | L64: 1 | M64: 59.95 | N64: =J64/M64 -> 0.18748957 | O64: =M64/J64 -> 5.3336299 | P64: =J64/D64 -> 0.093744787 | Q64: =M64/D64 -> 0.5 | R64: =D64-M64 -> 59.95 | S64: =J64/L64 -> 11.24
C65: Therabotanics | D65: 39.9 | E65: 2 | F65: 1 | G65: =E65/F65 -> 2 | H65: =D65/E65 -> 19.95 | I65: =H65/G65 -> 9.975 | J65: 0 | K65: 0 | L65: 0 | M65: 0 | N65: =J65/M65 -> #DIV/0! | O65: =M65/J65 -> #DIV/0! | P65: =J65/D65 -> 0 | Q65: =M65/D65 -> 0 | R65: =D65-M65 -> 39.9 | S65: =J65/L65 -> #DIV/0!
C66: WALKFIT | D66: 258.91 | E66: 7 | F66: 8 | G66: =E66/F66 -> 0.875 | H66: =D66/E66 -> 36.987143 | I66: =H66/G66 -> 42.27102 | J66: 72.21 | K66: 29832 | L66: 1 | M66: 35.96 | N66: =J66/M66 -> 2.0080645 | O66: =M66/J66 -> 0.49799197 | P66: =J66/D66 -> 0.2789 | Q66: =M66/D66 -> 0.13888996 | R66: =D66-M66 -> 222.95 | S66: =J66/L66 -> 72.21
C67: AromaTru | D67: 0 | E67: 0 | F67: 0 | G67: =E67/F67 -> #DIV/0! | H67: =D67/E67 -> #DIV/0! | I67: =H67/G67 -> #DIV/0! | J67: 2.24 | K67: 7193 | L67: 0 | M67: 0 | N67: =J67/M67 -> #DIV/0! | O67: =M67/J67 -> 0 | P67: =J67/D67 -> #DIV/0! | Q67: =M67/D67 -> #DIV/0! | R67: =D67-M67 -> 0 | S67: =J67/L67 -> #DIV/0!
A68: =iferror(if(B68>0,month(B68)&"-"&year(B68),B68),) -> 3-2025 | B68: 45731 | C68: SEM Campaigns | D68: 0 | E68: 0 | F68: 0 | G68: =E68/F68 -> #DIV/0! | H68: =D68/E68 -> #DIV/0! | I68: =H68/G68 -> #DIV/0! | J68: 92.74 | K68: 14061 | M68: 1018.9 | N68: =J68/M68 -> 0.091019727 | O68: =M68/J68 -> 10.986629 | P68: =J68/D68 -> #DIV/0! | Q68: =M68/D68 -> #DIV/0! | R68: =D68-M68 -> -1018.9 | S68: =J68/L68 -> #DIV/0!
A69: =iferror(if(B69>0,month(B69)&"-"&year(B69),B69),) | B69: Week 11 | D69: =SUM(D51:D68) -> 7581.32 | E69: =SUM(E51:E68) -> 94 | F69: =SUM(F51:F68) -> 95 | G69: =E69/F69 -> 0.98947368 | H69: =D69/E69 -> 80.65234 | I69: =H69/G69 -> 81.510344 | J69: =SUM(J51:J68) -> 1223.46 | K69: =SUM(K51:K68) -> 309973 | L69: =SUM(L51:L68) -> 30 | M69: =SUM(M51:M68) -> 3493.97 | N69: =J69/M69 -> 0.35016328 | O69: =M69/J69 -> 2.8558106 | P69: =J69/D69 -> 0.16137823 | Q69: =M69/D69 -> 0.46086565 | R69: =SUM(R51:R68) -> 4087.35 | S69: =J69/L69 -> 40.782 | T69: =IFERROR((D69-D50)/D69,) -> 0.027807822 | U69: =IFERROR((E69-E50)/E69,) -> -0.24468085 | V69: =IFERROR((D69-#REF!)/D69, ) | W69: =IFERROR((E69-#REF!)/E69, )
B70: 45732 | C70: AirDoctor | D70: 2285.01 | E70: 10 | F70: 9 | G70: =E70/F70 -> 1.1111111 | H70: =D70/E70 -> 228.501 | I70: =H70/G70 -> 205.6509 | J70: 367.43 | K70: 88929 | L70: 5 | M70: 1609.38 | N70: =J70/M70 -> 0.22830531 | O70: =M70/J70 -> 4.3800996 | P70: =J70/D70 -> 0.16080017 | Q70: =M70/D70 -> 0.70432077 | R70: =D70-M70 -> 675.63 | S70: =J70/L70 -> 73.486
C71: AquaTru | D71: 4824.6 | E71: 37 | F71: 41 | G71: =E71/F71 -> 0.90243902 | H71: =D71/E71 -> 130.39459 | I71: =H71/G71 -> 144.49131 | J71: 273.04 | K71: 85647 | L71: 9 | M71: 624.7 | N71: =J71/M71 -> 0.4370738 | O71: =M71/J71 -> 2.2879432 | P71: =J71/D71 -> 0.056593293 | Q71: =M71/D71 -> 0.12948224 | R71: =D71-M71 -> 4199.9 | S71: =J71/L71 -> 30.337778
C72: Beflexible | D72: 0 | E72: 0 | F72: 0 | G72: =E72/F72 -> #DIV/0! | H72: =D72/E72 -> #DIV/0! | I72: =H72/G72 -> #DIV/0! | J72: 0 | K72: 85 | L72: 0 | M72: 0 | N72: =(J72/M72) -> #DIV/0! | O72: =M72/J72 -> #DIV/0! | P72: =J72/D72 -> #DIV/0! | Q72: =M72/D72 -> #DIV/0! | R72: =D72-M72 -> 0 | S72: =J72/L72 -> #DIV/0!
C73: Better Bladder | D73: 659.45 | E73: 11 | F73: 6 | G73: =E73/F73 -> 1.8333333 | H73: =D73/E73 -> 59.95 | I73: =H73/G73 -> 32.7 | J73: 104.48 | K73: 7437 | L73: 6 | M73: 359.7 | N73: =J73/M73 -> 0.29046428 | O73: =M73/J73 -> 3.4427642 | P73: =J73/D73 -> 0.15843506 | Q73: =M73/D73 -> 0.54545455 | R73: =D73-M73 -> 299.75 | S73: =J73/L73 -> 17.413333
C74: Cebria | D74: 117 | E74: 3 | F74: 2 | G74: =E74/F74 -> 1.5 | H74: =D74/E74 -> 39 | I74: =H74/G74 -> 26 | J74: 0 | K74: 0 | L74: 0 | M74: 0 | N74: =J74/M74 -> #DIV/0! | O74: =M74/J74 -> #DIV/0! | P74: =J74/D74 -> 0 | Q74: =M74/D74 -> 0 | R74: =D74-M74 -> 117 | S74: =J74/L74 -> #DIV/0!
C75: GA Grown American | D75: -64.95 | E75: -1 | F75: 1 | G75: =E75/F75 -> -1 | H75: =D75/E75 -> 64.95 | I75: =H75/G75 -> -64.95 | J75: 42.1 | K75: 1937 | L75: 0 | M75: 0 | N75: =J75/M75 -> #DIV/0! | O75: =M75/J75 -> 0 | P75: =J75/D75 -> -0.64819092 | Q75: =M75/D75 -> 0 | R75: =D75-M75 -> -64.95 | S75: =J75/L75 -> #DIV/0!
C76: Ideal Prostate | D76: 319.75 | E76: 5 | F76: 6 | G76: =E76/F76 -> 0.83333333 | H76: =D76/E76 -> 63.95 | I76: =H76/G76 -> 76.74 | J76: 54.36 | K76: 9417 | L76: 2 | M76: 119.9 | N76: =J76/M76 -> 0.45337781 | O76: =M76/J76 -> 2.2056659 | P76: =J76/D76 -> 0.17000782 | Q76: =M76/D76 -> 0.37498045 | R76: =D76-M76 -> 199.85 | S76: =J76/L76 -> 27.18
B77: to | C77: Miracle Blade | D77: 640.36 | E77: 12 | F77: 13 | G77: =E77/F77 -> 0.92307692 | H77: =D77/E77 -> 53.363333 | I77: =H77/G77 -> 57.810278 | J77: 116.03 | K77: 14400 | L77: 2 | M77: 101.51 | N77: =J77/M77 -> 1.1430401 | O77: =M77/J77 -> 0.87485995 | P77: =J77/D77 -> 0.18119495 | Q77: =M77/D77 -> 0.15852021 | R77: =D77-M77 -> 538.85 | S77: =J77/L77 -> 58.015
C78: Paint Zoom | D78: 99.95 | E78: 1 | F78: 1 | G78: =E78/F78 -> 1 | H78: =D78/E78 -> 99.95 | I78: =H78/G78 -> 99.95 | J78: 0 | K78: 0 | L78: 0 | M78: 0 | N78: =J78/M78 -> #DIV/0! | O78: =M78/J78 -> #DIV/0! | P78: =J78/D78 -> 0 | Q78: =M78/D78 -> 0 | R78: =D78-M78 -> 99.95 | S78: =J78/L78 -> #DIV/0!
C79: Profemin | D79: 265.71 | E79: 5 | F79: 4 | G79: =E79/F79 -> 1.25 | H79: =D79/E79 -> 53.142 | I79: =H79/G79 -> 42.5136 | J79: 0 | K79: 0 | L79: 0 | M79: 0 | N79: =J79/M79 -> #DIV/0! | O79: =M79/J79 -> #DIV/0! | P79: =J79/D79 -> 0 | Q79: =M79/D79 -> 0 | R79: =D79-M79 -> 265.71 | S79: =J79/L79 -> #DIV/0!
C80: Prosvent | D80: 66.99 | E80: 1 | F80: 1 | G80: =E80/F80 -> 1 | H80: =D80/E80 -> 66.99 | I80: =H80/G80 -> 66.99 | J80: 0 | K80: 6 | L80: 0 | M80: 0 | N80: =J80/M80 -> #DIV/0! | O80: =M80/J80 -> #DIV/0! | P80: =J80/D80 -> 0 | Q80: =M80/D80 -> 0 | R80: =D80-M80 -> 66.99 | S80: =J80/L80 -> #DIV/0!
C81: SaniTru | D81: 139.93 | E81: 7 | F81: 6 | G81: =E81/F81 -> 1.1666667 | H81: =D81/E81 -> 19.99 | I81: =H81/G81 -> 17.134286 | J81: 3 | K81: 10710 | L81: 0 | M81: 0 | N81: =J81/M81 -> #DIV/0! | O81: =M81/J81 -> 0 | P81: =J81/D81 -> 0.021439291 | Q81: =M81/D81 -> 0 | R81: =D81-M81 -> 139.93 | S81: =J81/L81 -> #DIV/0!
C82: Rotorazer Saw | D82: 0 | E82: 0 | F82: 0 | G82: =E82/F82 -> #DIV/0! | H82: =D82/E82 -> #DIV/0! | I82: =H82/G82 -> #DIV/0! | J82: 19.95 | K82: 20397 | L82: 0 | M82: 0 | N82: =J82/M82 -> #DIV/0! | O82: =M82/J82 -> 0 | P82: =J82/D82 -> #DIV/0! | Q82: =M82/D82 -> #DIV/0! | R82: =D82-M82 -> 0 | S82: =J82/L82 -> #DIV/0!
C83: Superthotics | D83: 59.95 | E83: 1 | F83: 1 | G83: =E83/F83 -> 1 | H83: =D83/E83 -> 59.95 | I83: =H83/G83 -> 59.95 | J83: 19.46 | K83: 7147 | L83: 0 | M83: 0 | N83: =J83/M83 -> #DIV/0! | O83: =M83/J83 -> 0 | P83: =J83/D83 -> 0.32460384 | Q83: =M83/D83 -> 0 | R83: =D83-M83 -> 59.95 | S83: =J83/L83 -> #DIV/0!
C84: Therabotanics | D84: 0 | E84: 0 | F84: 0 | G84: =E84/F84 -> #DIV/0! | H84: =D84/E84 -> #DIV/0! | I84: =H84/G84 -> #DIV/0! | J84: 0 | K84: 0 | L84: 0 | M84: 0 | N84: =J84/M84 -> #DIV/0! | O84: =M84/J84 -> #DIV/0! | P84: =J84/D84 -> #DIV/0! | Q84: =M84/D84 -> #DIV/0! | R84: =D84-M84 -> 0 | S84: =J84/L84 -> #DIV/0!
C85: WALKFIT | D85: 318.24 | E85: 9 | F85: 11 | G85: =E85/F85 -> 0.81818182 | H85: =D85/E85 -> 35.36 | I85: =H85/G85 -> 43.217778 | J85: 75.23 | K85: 22887 | L85: 4 | M85: 142.04 | N85: =J85/M85 -> 0.52963954 | O85: =M85/J85 -> 1.8880766 | P85: =J85/D85 -> 0.23639392 | Q85: =M85/D85 -> 0.44632981 | R85: =D85-M85 -> 176.2 | S85: =J85/L85 -> 18.8075
C86: AromaTru | D86: 0 | E86: 0 | F86: 0 | G86: =E86/F86 -> #DIV/0! | H86: =D86/E86 -> #DIV/0! | I86: =H86/G86 -> #DIV/0! | J86: 5.99 | K86: 6262 | L86: 0 | M86: 0 | N86: =J86/M86 -> #DIV/0! | O86: =M86/J86 -> 0 | P86: =J86/D86 -> #DIV/0! | Q86: =M86/D86 -> #DIV/0! | R86: =D86-M86 -> 0 | S86: =J86/L86 -> #DIV/0!
A87: =iferror(if(B87>0,month(B87)&"-"&year(B87),B87),) -> 3-2025 | B87: 45738 | C87: SEM Campaigns | D87: 0 | E87: 0 | F87: 0 | G87: =E87/F87 -> #DIV/0! | H87: =D87/E87 -> #DIV/0! | I87: =H87/G87 -> #DIV/0! | J87: 128.25 | K87: 20661 | M87: 64.01 | N87: =J87/M87 -> 2.0035932 | O87: =M87/J87 -> 0.49910331 | P87: =J87/D87 -> #DIV/0! | Q87: =M87/D87 -> #DIV/0! | R87: =D87-M87 -> -64.01 | S87: =J87/L87 -> #DIV/0!
A88: =iferror(if(B88>0,month(B88)&"-"&year(B88),B88),) | B88: Week 12 | D88: =SUM(D70:D87) -> 9731.99 | E88: =SUM(E70:E87) -> 101 | F88: =SUM(F70:F87) -> 102 | G88: =E88/F88 -> 0.99019608 | H88: =D88/E88 -> 96.356337 | I88: =H88/G88 -> 97.31036 | J88: =SUM(J70:J87) -> 1209.32 | K88: =SUM(K70:K87) -> 295922 | L88: =SUM(L70:L87) -> 28 | M88: =SUM(M70:M87) -> 3021.24 | N88: =J88/M88 -> 0.40027274 | O88: =M88/J88 -> 2.4982966 | P88: =J88/D88 -> 0.12426236 | Q88: =M88/D88 -> 0.31044422 | R88: =SUM(R70:R87) -> 6710.75 | S88: =J88/L88 -> 43.19 | T88: =IFERROR((D88-D69)/D88,) -> 0.22098975 | U88: =IFERROR((E88-E69)/E88,) -> 0.069306931 | V88: =IFERROR((D88-#REF!)/D88, ) | W88: =IFERROR((E88-#REF!)/E88, )
B89: 45739 | C89: AirDoctor | D89: 8096.74 | E89: 23 | F89: 25 | G89: =E89/F89 -> 0.92 | H89: =D89/E89 -> 352.03217 | I89: =H89/G89 -> 382.64367 | J89: 508.84 | K89: 99126 | L89: 5 | M89: 900.33 | N89: =J89/M89 -> 0.56517055 | O89: =M89/J89 -> 1.7693774 | P89: =J89/D89 -> 0.062845046 | Q89: =M89/D89 -> 0.11119661 | R89: =D89-M89 -> 7196.41 | S89: =J89/L89 -> 101.768
C90: AquaTru | D90: 9235.01 | E90: 47 | F90: 46 | G90: =E90/F90 -> 1.0217391 | H90: =D90/E90 -> 196.48957 | I90: =H90/G90 -> 192.30895 | J90: 217.32 | K90: 91243 | L90: 7 | M90: 1471.02 | N90: =J90/M90 -> 0.14773423 | O90: =M90/J90 -> 6.7689122 | P90: =J90/D90 -> 0.023532189 | Q90: =M90/D90 -> 0.15928732 | R90: =D90-M90 -> 7763.99 | S90: =J90/L90 -> 31.045714
C91: Beflexible | D91: 139.9 | E91: 2 | F91: 1 | G91: =E91/F91 -> 2 | H91: =D91/E91 -> 69.95 | I91: =H91/G91 -> 34.975 | J91: 0 | K91: 0 | L91: 0 | M91: 0 | N91: =(J91/M91) -> #DIV/0! | O91: =M91/J91 -> #DIV/0! | P91: =J91/D91 -> 0 | Q91: =M91/D91 -> 0 | R91: =D91-M91 -> 139.9 | S91: =J91/L91 -> #DIV/0!
C92: Better Bladder | D92: 530.55 | E92: 9 | F92: 6 | G92: =E92/F92 -> 1.5 | H92: =D92/E92 -> 58.95 | I92: =H92/G92 -> 39.3 | J92: 88.02 | K92: 7631 | L92: 2 | M92: 119.9 | N92: =J92/M92 -> 0.73411176 | O92: =M92/J92 -> 1.3621904 | P92: =J92/D92 -> 0.16590331 | Q92: =M92/D92 -> 0.2259919 | R92: =D92-M92 -> 410.65 | S92: =J92/L92 -> 44.01
C93: Cebria | D93: 456 | E93: 12 | F93: 8 | G93: =E93/F93 -> 1.5 | H93: =D93/E93 -> 38 | I93: =H93/G93 -> 25.333333 | J93: 0 | K93: 0 | L93: 0 | M93: 0 | N93: =J93/M93 -> #DIV/0! | O93: =M93/J93 -> #DIV/0! | P93: =J93/D93 -> 0 | Q93: =M93/D93 -> 0 | R93: =D93-M93 -> 456 | S93: =J93/L93 -> #DIV/0!
C94: GA Grown American | D94: -64.95 | E94: -1 | F94: 1 | G94: =E94/F94 -> -1 | H94: =D94/E94 -> 64.95 | I94: =H94/G94 -> -64.95 | J94: 3.3 | K94: 128 | L94: 0 | M94: 0 | N94: =J94/M94 -> #DIV/0! | O94: =M94/J94 -> 0 | P94: =J94/D94 -> -0.050808314 | Q94: =M94/D94 -> 0 | R94: =D94-M94 -> -64.95 | S94: =J94/L94 -> #DIV/0!
C95: Ideal Prostate | D95: 419.7 | E95: 6 | F95: 6 | G95: =E95/F95 -> 1 | H95: =D95/E95 -> 69.95 | I95: =H95/G95 -> 69.95 | J95: 38.65 | K95: 4191 | L95: 3 | M95: 209.85 | N95: =J95/M95 -> 0.18417918 | O95: =M95/J95 -> 5.4294955 | P95: =J95/D95 -> 0.092089588 | Q95: =M95/D95 -> 0.5 | R95: =D95-M95 -> 209.85 | S95: =J95/L95 -> 12.883333
B96: to | C96: Miracle Blade | D96: 21.59 | E96: 4 | F96: 4 | G96: =E96/F96 -> 1 | H96: =D96/E96 -> 5.3975 | I96: =H96/G96 -> 5.3975 | J96: 119.39 | K96: 10084 | L96: 4 | M96: 86.24 | N96: =J96/M96 -> 1.3843924 | O96: =M96/J96 -> 0.72233855 | P96: =J96/D96 -> 5.5298749 | Q96: =M96/D96 -> 3.9944419 | R96: =D96-M96 -> -64.65 | S96: =J96/L96 -> 29.8475
C97: Paint Zoom | D97: 359.89 | E97: 3 | F97: 3 | G97: =E97/F97 -> 1 | H97: =D97/E97 -> 119.96333 | I97: =H97/G97 -> 119.96333 | J97: 0 | K97: 0 | L97: 0 | M97: 0 | N97: =J97/M97 -> #DIV/0! | O97: =M97/J97 -> #DIV/0! | P97: =J97/D97 -> 0 | Q97: =M97/D97 -> 0 | R97: =D97-M97 -> 359.89 | S97: =J97/L97 -> #DIV/0!
C98: Profemin | D98: 1327.09 | E98: 27 | F98: 13 | G98: =E98/F98 -> 2.0769231 | H98: =D98/E98 -> 49.151481 | I98: =H98/G98 -> 23.665528 | J98: 0 | K98: 0 | L98: 0 | M98: 0 | N98: =J98/M98 -> #DIV/0! | O98: =M98/J98 -> #DIV/0! | P98: =J98/D98 -> 0 | Q98: =M98/D98 -> 0 | R98: =D98-M98 -> 1327.09 | S98: =J98/L98 -> #DIV/0!
C99: Prosvent | D99: 66.99 | E99: 1 | F99: 1 | G99: =E99/F99 -> 1 | H99: =D99/E99 -> 66.99 | I99: =H99/G99 -> 66.99 | J99: 0 | K99: 0 | L99: 0 | M99: 0 | N99: =J99/M99 -> #DIV/0! | O99: =M99/J99 -> #DIV/0! | P99: =J99/D99 -> 0 | Q99: =M99/D99 -> 0 | R99: =D99-M99 -> 66.99 | S99: =J99/L99 -> #DIV/0!
C100: SaniTru | D100: 159.92 | E100: 8 | F100: 6 | G100: =E100/F100 -> 1.3333333 | H100: =D100/E100 -> 19.99 | I100: =H100/G100 -> 14.9925 | J100: 3 | K100: 10792 | L100: 1 | M100: 19.99 | N100: =J100/M100 -> 0.15007504 | O100: =M100/J100 -> 6.6633333 | P100: =J100/D100 -> 0.01875938 | Q100: =M100/D100 -> 0.125 | R100: =D100-M100 -> 139.93 | S100: =J100/L100 -> 3
C101: Rotorazer Saw | D101: 344 | E101: 2 | F101: 2 | G101: =E101/F101 -> 1 | H101: =D101/E101 -> 172 | I101: =H101/G101 -> 172 | J101: 8.25 | K101: 18913 | L101: 0 | M101: 0 | N101: =J101/M101 -> #DIV/0! | O101: =M101/J101 -> 0 | P101: =J101/D101 -> 0.023982558 | Q101: =M101/D101 -> 0 | R101: =D101-M101 -> 344 | S101: =J101/L101 -> #DIV/0!
C102: Superthotics | D102: 50.96 | E102: 1 | F102: 1 | G102: =E102/F102 -> 1 | H102: =D102/E102 -> 50.96 | I102: =H102/G102 -> 50.96 | J102: 26.57 | K102: 7414 | L102: 0 | M102: 0 | N102: =J102/M102 -> #DIV/0! | O102: =M102/J102 -> 0 | P102: =J102/D102 -> 0.52138933 | Q102: =M102/D102 -> 0 | R102: =D102-M102 -> 50.96 | S102: =J102/L102 -> #DIV/0!
...

Sheet SEM Campaigns Data 2025
A1: WALMART - DATA SOURCES: https://seller.walmart.com/advertising/search-engine-marketing/
C2: WEEKLY PERFORMANCE | X2: =(#REF!+#REF!+#REF!+#REF!)-(monthly_reporting_2021!D17+monthly_reporting_2021!D23+monthly_reporting_2021!D29+monthly_reporting_2021!D35) -> #REF! | Y2: =((#REF!+#REF!+#REF!+#REF!)-(monthly_reporting_2021!E17+monthly_reporting_2021!E23+monthly_reporting_2021!E29+monthly_reporting_2021!E35))/(#REF!+#REF!+#REF!+#REF!) -> #REF!
K3: Total Sales | N3: Total Orders | S3: Total Units Sold
K4: =VLOOKUP("Current Week",$B$11:$X$570,match("SALES",$B$11:$X$11,0),FALSE) -> 0 | N4: =VLOOKUP("Current Week",$B$11:$X$570,match("Units Sold",$B$11:$X$11,0),FALSE) -> 0 | S4: =VLOOKUP("Current Week",$B$11:$X$570,match("Ordered Items",$B$11:$X$11,0),FALSE) -> 0
K5: =(K4-(VLOOKUP("Previous Week",$B$11:$X$575,match("SALES",$B$11:$X$11,0),FALSE)))/K4 -> #DIV/0! | N5: =(N4-(VLOOKUP("Previous Week",$B$11:$X$575,match("Units Sold",$B$11:$X$11,0),FALSE)))/N4 -> #DIV/0! | S5: =(S4-(VLOOKUP("Previous Week",$B$11:$X$575,match("Ordered Items",$B$11:$X$11,0),FALSE)))/S4 -> #DIV/0!
K7: Advertising Sales | N7: Advertising Spend | S7: ACoS
K8: =VLOOKUP("Current Week",$B$11:$X$570,match("AD SALES",$B$11:$X$11,0),FALSE) -> 18214 | N8: =VLOOKUP("Current Week",$B$11:$X$570,match("SP AD SPEND",$B$11:$X$11,0),FALSE) -> 4879.89 | S8: =N8/K8 -> 0.26791973
K9: =(K8-(VLOOKUP("Previous Week",$B$11:$X$575,match("AD SALES",$B$11:$X$11,0),FALSE)))/K8 -> -0.037093445 | N9: =(N8-(VLOOKUP("Previous Week",$B$11:$X$575,match("SP AD SPEND",$B$11:$X$11,0),FALSE)))/N8 -> -0.36364549 | S9: =(S8-(VLOOKUP("Previous Week",$B$11:$X$575,match("ACOS",$B$11:$X$11,0),FALSE)))/S8 -> -0.31487235
D10: SALES METRICS | L10: ADVERTISING PERFORMANCE | V10: MoM | X10: YoY
A11: Month-Code | B11: DATE | C11: Campaign Name | D11: SALES | E11: UNITS SOLD | F11: ORDERED ITEMS | G11: UNITS PER ORDER | H11: SALES PER ORDER | I11: ASP | J11: SP AD SPEND | K11: IMPRESSIONS | L11: UNIT SALES | M11: AD SALES | N11: ACoS | O11: ROAS (return on ad send) | P11: TACoS (Total Advertsing Cost of Sales) | Q11: REVENUE PERCENTAGE OF AD SALES | R11: ORGANIC SALES | S11: CPO | T11: SALES | U11: UNITS | V11: SALES | W11: UNITS
B13: 45711 | C13: Dielon - AquaTru - Highly Recommended | G13: =E13/F13 -> #DIV/0! | H13: =D13/E13 -> #DIV/0! | I13: =H13/G13 -> #DIV/0! | J13: 0 | K13: 0 | M13: 0 | N13: =J13/M13 -> #DIV/0! | O13: =M13/J13 -> #DIV/0! | P13: =J13/D13 -> #DIV/0! | Q13: =M13/D13 -> #DIV/0! | R13: =D13-M13 -> 0 | S13: =J13/L13 -> #DIV/0!
C14: Dielon - Ideal Prostate - Highly Recommended | G14: =E14/F14 -> #DIV/0! | H14: =D14/E14 -> #DIV/0! | I14: =H14/G14 -> #DIV/0! | J14: 0 | K14: 0 | M14: 0 | N14: =J14/M14 -> #DIV/0! | O14: =M14/J14 -> #DIV/0! | P14: =J14/D14 -> #DIV/0! | Q14: =M14/D14 -> #DIV/0! | R14: =D14-M14 -> 0 | S14: =J14/L14 -> #DIV/0!
C15: Dielon - Prosvent - Highly Recommended | G15: =E15/F15 -> #DIV/0! | H15: =D15/E15 -> #DIV/0! | I15: =H15/G15 -> #DIV/0! | J15: 5.26 | K15: 1761 | M15: 0 | N15: =(J15/M15) -> #DIV/0! | O15: =M15/J15 -> 0 | P15: =J15/D15 -> #DIV/0! | Q15: =M15/D15 -> #DIV/0! | R15: =D15-M15 -> 0 | S15: =J15/L15 -> #DIV/0!
C16: Dielon - Better Bladder - Highly Recommended | G16: =E16/F16 -> #DIV/0! | H16: =D16/E16 -> #DIV/0! | I16: =H16/G16 -> #DIV/0! | J16: 0 | K16: 0 | M16: 0 | N16: =J16/M16 -> #DIV/0! | O16: =M16/J16 -> #DIV/0! | P16: =J16/D16 -> #DIV/0! | Q16: =M16/D16 -> #DIV/0! | R16: =D16-M16 -> 0 | S16: =J16/L16 -> #DIV/0!
C17: Dielon - Rotorazer - Highly Recommended | G17: =E17/F17 -> #DIV/0! | H17: =D17/E17 -> #DIV/0! | I17: =H17/G17 -> #DIV/0! | J17: 14.46 | K17: 1394 | M17: 0 | N17: =J17/M17 -> #DIV/0! | O17: =M17/J17 -> 0 | P17: =J17/D17 -> #DIV/0! | Q17: =M17/D17 -> #DIV/0! | R17: =D17-M17 -> 0 | S17: =J17/L17 -> #DIV/0!
C18: Dielon - Superthotics - Highly Recommended | G18: =E18/F18 -> #DIV/0! | H18: =D18/E18 -> #DIV/0! | I18: =H18/G18 -> #DIV/0! | J18: 0 | K18: 0 | M18: 0 | N18: =J18/M18 -> #DIV/0! | O18: =M18/J18 -> #DIV/0! | P18: =J18/D18 -> #DIV/0! | Q18: =M18/D18 -> #DIV/0! | R18: =D18-M18 -> 0 | S18: =J18/L18 -> #DIV/0!
C19: Dielon - AirDoctor Filter - Highly Recommended | G19: =E19/F19 -> #DIV/0! | H19: =D19/E19 -> #DIV/0! | I19: =H19/G19 -> #DIV/0! | J19: 0 | K19: 0 | M19: 0 | N19: =J19/M19 -> #DIV/0! | O19: =M19/J19 -> #DIV/0! | P19: =J19/D19 -> #DIV/0! | Q19: =M19/D19 -> #DIV/0! | R19: =D19-M19 -> 0 | S19: =J19/L19 -> #DIV/0!
B20: to | C20: Dielon - AquaTru Filters- Highly Recommended | G20: =E20/F20 -> #DIV/0! | H20: =D20/E20 -> #DIV/0! | I20: =H20/G20 -> #DIV/0! | J20: 0 | K20: 0 | M20: 0 | N20: =J20/M20 -> #DIV/0! | O20: =M20/J20 -> #DIV/0! | P20: =J20/D20 -> #DIV/0! | Q20: =M20/D20 -> #DIV/0! | R20: =D20-M20 -> 0 | S20: =J20/L20 -> #DIV/0!
C21: Dielon - AirDoctor Main - Highly Recommended | G21: =E21/F21 -> #DIV/0! | H21: =D21/E21 -> #DIV/0! | I21: =H21/G21 -> #DIV/0! | J21: 0 | K21: 0 | M21: 0 | N21: =J21/M21 -> #DIV/0! | O21: =M21/J21 -> #DIV/0! | P21: =J21/D21 -> #DIV/0! | Q21: =M21/D21 -> #DIV/0! | R21: =D21-M21 -> 0 | S21: =J21/L21 -> #DIV/0!
C22: Dielon - Walkfit Platinum - Highly Recommended | G22: =E22/F22 -> #DIV/0! | H22: =D22/E22 -> #DIV/0! | I22: =H22/G22 -> #DIV/0! | J22: 2.76 | K22: 256 | M22: 0 | N22: =J22/M22 -> #DIV/0! | O22: =M22/J22 -> 0 | P22: =J22/D22 -> #DIV/0! | Q22: =M22/D22 -> #DIV/0! | R22: =D22-M22 -> 0 | S22: =J22/L22 -> #DIV/0!
A23: =iferror(if(B23>0,month(B23)&"-"&year(B23),B23),) -> 3-2025 | B23: 45717 | C23: Dielon - Grown American - Highly Recommended | G23: =E23/F23 -> #DIV/0! | H23: =D23/E23 -> #DIV/0! | I23: =H23/G23 -> #DIV/0! | J23: 0 | K23: 0 | M23: 0 | N23: =J23/M23 -> #DIV/0! | O23: =M23/J23 -> #DIV/0! | P23: =J23/D23 -> #DIV/0! | Q23: =M23/D23 -> #DIV/0! | R23: =D23-M23 -> 0 | S23: =J23/L23 -> #DIV/0!
A24: =iferror(if(B24>0,month(B24)&"-"&year(B24),B24),) | B24: 2025 - Week 9 | D24: =SUM(D13:D23) -> 0 | E24: =SUM(E13:E23) -> 0 | F24: =SUM(F13:F23) -> 0 | G24: =E24/F24 -> #DIV/0! | H24: =D24/E24 -> #DIV/0! | I24: =H24/G24 -> #DIV/0! | J24: =SUM(J13:J23) -> 22.48 | K24: =SUM(K13:K23) -> 3411 | L24: =SUM(L13:L23) -> 0 | M24: =SUM(M13:M23) -> 0 | N24: =J24/M24 -> #DIV/0! | O24: =M24/J24 -> 0 | P24: =J24/D24 -> #DIV/0! | Q24: =M24/D24 -> #DIV/0! | R24: =SUM(R13:R23) -> 0 | S24: =J24/L24 -> #DIV/0! | T24: =IFERROR((D24-#REF!)/D24,) | U24: =IFERROR((E24-#REF!)/E24,) | V24: =IFERROR((D24-#REF!)/D24, ) | W24: =IFERROR((E24-#REF!)/E24, )
B25: 45718 | C25: Dielon - AquaTru - Highly Recommended | G25: =E25/F25 -> #DIV/0! | H25: =D25/E25 -> #DIV/0! | I25: =H25/G25 -> #DIV/0! | J25: 0 | K25: 0 | M25: 0 | N25: =J25/M25 -> #DIV/0! | O25: =M25/J25 -> #DIV/0! | P25: =J25/D25 -> #DIV/0! | Q25: =M25/D25 -> #DIV/0! | R25: =D25-M25 -> 0 | S25: =J25/L25 -> #DIV/0!
C26: Dielon - Ideal Prostate - Highly Recommended | G26: =E26/F26 -> #DIV/0! | H26: =D26/E26 -> #DIV/0! | I26: =H26/G26 -> #DIV/0! | J26: 3.12 | K26: 1138 | M26: 0 | N26: =J26/M26 -> #DIV/0! | O26: =M26/J26 -> 0 | P26: =J26/D26 -> #DIV/0! | Q26: =M26/D26 -> #DIV/0! | R26: =D26-M26 -> 0 | S26: =J26/L26 -> #DIV/0!
C27: Dielon - Prosvent - Highly Recommended | G27: =E27/F27 -> #DIV/0! | H27: =D27/E27 -> #DIV/0! | I27: =H27/G27 -> #DIV/0! | J27: 6.03 | K27: 2153 | M27: 0 | N27: =(J27/M27) -> #DIV/0! | O27: =M27/J27 -> 0 | P27: =J27/D27 -> #DIV/0! | Q27: =M27/D27 -> #DIV/0! | R27: =D27-M27 -> 0 | S27: =J27/L27 -> #DIV/0!
C28: Dielon - Better Bladder - Highly Recommended | G28: =E28/F28 -> #DIV/0! | H28: =D28/E28 -> #DIV/0! | I28: =H28/G28 -> #DIV/0! | J28: 0 | K28: 0 | M28: 0 | N28: =J28/M28 -> #DIV/0! | O28: =M28/J28 -> #DIV/0! | P28: =J28/D28 -> #DIV/0! | Q28: =M28/D28 -> #DIV/0! | R28: =D28-M28 -> 0 | S28: =J28/L28 -> #DIV/0!
C29: Dielon - Rotorazer - Highly Recommended | G29: =E29/F29 -> #DIV/0! | H29: =D29/E29 -> #DIV/0! | I29: =H29/G29 -> #DIV/0! | J29: 0 | K29: 0 | M29: 0 | N29: =J29/M29 -> #DIV/0! | O29: =M29/J29 -> #DIV/0! | P29: =J29/D29 -> #DIV/0! | Q29: =M29/D29 -> #DIV/0! | R29: =D29-M29 -> 0 | S29: =J29/L29 -> #DIV/0!
C30: Dielon - Superthotics - Highly Recommended | G30: =E30/F30 -> #DIV/0! | H30: =D30/E30 -> #DIV/0! | I30: =H30/G30 -> #DIV/0! | J30: 0 | K30: 0 | M30: 0 | N30: =J30/M30 -> #DIV/0! | O30: =M30/J30 -> #DIV/0! | P30: =J30/D30 -> #DIV/0! | Q30: =M30/D30 -> #DIV/0! | R30: =D30-M30 -> 0 | S30: =J30/L30 -> #DIV/0!
C31: Dielon - AirDoctor Filter - Highly Recommended | G31: =E31/F31 -> #DIV/0! | H31: =D31/E31 -> #DIV/0! | I31: =H31/G31 -> #DIV/0! | J31: 65.17 | K31: 8142 | M31: 0 | N31: =J31/M31 -> #DIV/0! | O31: =M31/J31 -> 0 | P31: =J31/D31 -> #DIV/0! | Q31: =M31/D31 -> #DIV/0! | R31: =D31-M31 -> 0 | S31: =J31/L31 -> #DIV/0!
B32: to | C32: Dielon - AquaTru Filters- Highly Recommended | G32: =E32/F32 -> #DIV/0! | H32: =D32/E32 -> #DIV/0! | I32: =H32/G32 -> #DIV/0! | J32: 0 | K32: 0 | M32: 0 | N32: =J32/M32 -> #DIV/0! | O32: =M32/J32 -> #DIV/0! | P32: =J32/D32 -> #DIV/0! | Q32: =M32/D32 -> #DIV/0! | R32: =D32-M32 -> 0 | S32: =J32/L32 -> #DIV/0!
C33: Dielon - AirDoctor Main - Highly Recommended | G33: =E33/F33 -> #DIV/0! | H33: =D33/E33 -> #DIV/0! | I33: =H33/G33 -> #DIV/0! | J33: 0 | K33: 0 | M33: 0 | N33: =J33/M33 -> #DIV/0! | O33: =M33/J33 -> #DIV/0! | P33: =J33/D33 -> #DIV/0! | Q33: =M33/D33 -> #DIV/0! | R33: =D33-M33 -> 0 | S33: =J33/L33 -> #DIV/0!
C34: Dielon - Walkfit Platinum - Highly Recommended | G34: =E34/F34 -> #DIV/0! | H34: =D34/E34 -> #DIV/0! | I34: =H34/G34 -> #DIV/0! | J34: 40.37 | K34: 5478 | M34: 54.79 | N34: =J34/M34 -> 0.73681329 | O34: =M34/J34 -> 1.3571959 | P34: =J34/D34 -> #DIV/0! | Q34: =M34/D34 -> #DIV/0! | R34: =D34-M34 -> -54.79 | S34: =J34/L34 -> #DIV/0!
A35: =iferror(if(B35>0,month(B35)&"-"&year(B35),B35),) -> 3-2025 | B35: 45724 | C35: Dielon - Grown American - Highly Recommended | G35: =E35/F35 -> #DIV/0! | H35: =D35/E35 -> #DIV/0! | I35: =H35/G35 -> #DIV/0! | J35: 0 | K35: 0 | M35: 0 | N35: =J35/M35 -> #DIV/0! | O35: =M35/J35 -> #DIV/0! | P35: =J35/D35 -> #DIV/0! | Q35: =M35/D35 -> #DIV/0! | R35: =D35-M35 -> 0 | S35: =J35/L35 -> #DIV/0!
A36: =iferror(if(B36>0,month(B36)&"-"&year(B36),B36),) | B36: Week 10 | D36: =SUM(D25:D35) -> 0 | E36: =SUM(E25:E35) -> 0 | F36: =SUM(F25:F35) -> 0 | G36: =E36/F36 -> #DIV/0! | H36: =D36/E36 -> #DIV/0! | I36: =H36/G36 -> #DIV/0! | J36: =SUM(J25:J35) -> 114.69 | K36: =SUM(K25:K35) -> 16911 | L36: =SUM(L25:L35) -> 0 | M36: =SUM(M25:M35) -> 54.79 | N36: =J36/M36 -> 2.0932652 | O36: =M36/J36 -> 0.47772256 | P36: =J36/D36 -> #DIV/0! | Q36: =M36/D36 -> #DIV/0! | R36: =SUM(R25:R35) -> -54.79 | S36: =J36/L36 -> #DIV/0! | T36: =IFERROR((D36-#REF!)/D36,) | U36: =IFERROR((E36-#REF!)/E36,) | V36: =IFERROR((D36-#REF!)/D36, ) | W36: =IFERROR((E36-#REF!)/E36, )
B37: 45725 | C37: Dielon - AquaTru - Highly Recommended | G37: =E37/F37 -> #DIV/0! | H37: =D37/E37 -> #DIV/0! | I37: =H37/G37 -> #DIV/0! | J37: 50 | K37: 4272 | M37: 0 | N37: =J37/M37 -> #DIV/0! | O37: =M37/J37 -> 0 | P37: =J37/D37 -> #DIV/0! | Q37: =M37/D37 -> #DIV/0! | R37: =D37-M37 -> 0 | S37: =J37/L37 -> #DIV/0!
C38: Dielon - Ideal Prostate - Highly Recommended | G38: =E38/F38 -> #DIV/0! | H38: =D38/E38 -> #DIV/0! | I38: =H38/G38 -> #DIV/0! | J38: 4.24 | K38: 1961 | M38: 59.95 | N38: =J38/M38 -> 0.070725605 | O38: =M38/J38 -> 14.139151 | P38: =J38/D38 -> #DIV/0! | Q38: =M38/D38 -> #DIV/0! | R38: =D38-M38 -> -59.95 | S38: =J38/L38 -> #DIV/0!
C39: Dielon - Prosvent - Highly Recommended | G39: =E39/F39 -> #DIV/0! | H39: =D39/E39 -> #DIV/0! | I39: =H39/G39 -> #DIV/0! | J39: 6.99 | K39: 1978 | M39: 0 | N39: =(J39/M39) -> #DIV/0! | O39: =M39/J39 -> 0 | P39: =J39/D39 -> #DIV/0! | Q39: =M39/D39 -> #DIV/0! | R39: =D39-M39 -> 0 | S39: =J39/L39 -> #DIV/0!
C40: Dielon - Better Bladder - Highly Recommended | G40: =E40/F40 -> #DIV/0! | H40: =D40/E40 -> #DIV/0! | I40: =H40/G40 -> #DIV/0! | J40: 4.27 | K40: 1321 | M40: 59.95 | N40: =J40/M40 -> 0.071226022 | O40: =M40/J40 -> 14.039813 | P40: =J40/D40 -> #DIV/0! | Q40: =M40/D40 -> #DIV/0! | R40: =D40-M40 -> -59.95 | S40: =J40/L40 -> #DIV/0!
C41: Dielon - Rotorazer - Highly Recommended | G41: =E41/F41 -> #DIV/0! | H41: =D41/E41 -> #DIV/0! | I41: =H41/G41 -> #DIV/0! | J41: 0 | K41: 0 | M41: 0 | N41: =J41/M41 -> #DIV/0! | O41: =M41/J41 -> #DIV/0! | P41: =J41/D41 -> #DIV/0! | Q41: =M41/D41 -> #DIV/0! | R41: =D41-M41 -> 0 | S41: =J41/L41 -> #DIV/0!
C42: Dielon - Superthotics - Highly Recommended | G42: =E42/F42 -> #DIV/0! | H42: =D42/E42 -> #DIV/0! | I42: =H42/G42 -> #DIV/0! | J42: 0 | K42: 0 | M42: 0 | N42: =J42/M42 -> #DIV/0! | O42: =M42/J42 -> #DIV/0! | P42: =J42/D42 -> #DIV/0! | Q42: =M42/D42 -> #DIV/0! | R42: =D42-M42 -> 0 | S42: =J42/L42 -> #DIV/0!
C43: Dielon - AirDoctor Filter - Highly Recommended | G43: =E43/F43 -> #DIV/0! | H43: =D43/E43 -> #DIV/0! | I43: =H43/G43 -> #DIV/0! | J43: 20.37 | K43: 3504 | M43: 899 | N43: =J43/M43 -> 0.022658509 | O43: =M43/J43 -> 44.13353 | P43: =J43/D43 -> #DIV/0! | Q43: =M43/D43 -> #DIV/0! | R43: =D43-M43 -> -899 | S43: =J43/L43 -> #DIV/0!
B44: to | C44: Dielon - AquaTru Filters- Highly Recommended | G44: =E44/F44 -> #DIV/0! | H44: =D44/E44 -> #DIV/0! | I44: =H44/G44 -> #DIV/0! | J44: 0 | K44: 0 | M44: 0 | N44: =J44/M44 -> #DIV/0! | O44: =M44/J44 -> #DIV/0! | P44: =J44/D44 -> #DIV/0! | Q44: =M44/D44 -> #DIV/0! | R44: =D44-M44 -> 0 | S44: =J44/L44 -> #DIV/0!
C45: Dielon - AirDoctor Main - Highly Recommended | G45: =E45/F45 -> #DIV/0! | H45: =D45/E45 -> #DIV/0! | I45: =H45/G45 -> #DIV/0! | J45: 0 | K45: 0 | M45: 0 | N45: =J45/M45 -> #DIV/0! | O45: =M45/J45 -> #DIV/0! | P45: =J45/D45 -> #DIV/0! | Q45: =M45/D45 -> #DIV/0! | R45: =D45-M45 -> 0 | S45: =J45/L45 -> #DIV/0!
C46: Dielon - Walkfit Platinum - Highly Recommended | G46: =E46/F46 -> #DIV/0! | H46: =D46/E46 -> #DIV/0! | I46: =H46/G46 -> #DIV/0! | J46: 6.87 | K46: 1025 | M46: 0 | N46: =J46/M46 -> #DIV/0! | O46: =M46/J46 -> 0 | P46: =J46/D46 -> #DIV/0! | Q46: =M46/D46 -> #DIV/0! | R46: =D46-M46 -> 0 | S46: =J46/L46 -> #DIV/0!
A47: =iferror(if(B47>0,month(B47)&"-"&year(B47),B47),) -> 3-2025 | B47: 45731 | C47: Dielon - Grown American - Highly Recommended | G47: =E47/F47 -> #DIV/0! | H47: =D47/E47 -> #DIV/0! | I47: =H47/G47 -> #DIV/0! | J47: 0 | K47: 0 | M47: 0 | N47: =J47/M47 -> #DIV/0! | O47: =M47/J47 -> #DIV/0! | P47: =J47/D47 -> #DIV/0! | Q47: =M47/D47 -> #DIV/0! | R47: =D47-M47 -> 0 | S47: =J47/L47 -> #DIV/0!
A48: =iferror(if(B48>0,month(B48)&"-"&year(B48),B48),) | B48: Week 11 | D48: =SUM(D37:D47) -> 0 | E48: =SUM(E37:E47) -> 0 | F48: =SUM(F37:F47) -> 0 | G48: =E48/F48 -> #DIV/0! | H48: =D48/E48 -> #DIV/0! | I48: =H48/G48 -> #DIV/0! | J48: =SUM(J37:J47) -> 92.74 | K48: =SUM(K37:K47) -> 14061 | L48: =SUM(L37:L47) -> 0 | M48: =SUM(M37:M47) -> 1018.9 | N48: =J48/M48 -> 0.091019727 | O48: =M48/J48 -> 10.986629 | P48: =J48/D48 -> #DIV/0! | Q48: =M48/D48 -> #DIV/0! | R48: =SUM(R37:R47) -> -1018.9 | S48: =J48/L48 -> #DIV/0! | T48: =IFERROR((D48-D36)/D48,) | U48: =IFERROR((E48-E36)/E48,) | V48: =IFERROR((D48-#REF!)/D48, ) | W48: =IFERROR((E48-#REF!)/E48, )
B49: 45732 | C49: Dielon - AquaTru - Highly Recommended | G49: =E49/F49 -> #DIV/0! | H49: =D49/E49 -> #DIV/0! | I49: =H49/G49 -> #DIV/0! | J49: 9.53 | K49: 4368 | M49: 0 | N49: =J49/M49 -> #DIV/0! | O49: =M49/J49 -> 0 | P49: =J49/D49 -> #DIV/0! | Q49: =M49/D49 -> #DIV/0! | R49: =D49-M49 -> 0 | S49: =J49/L49 -> #DIV/0!
C50: Dielon - Ideal Prostate - Highly Recommended | G50: =E50/F50 -> #DIV/0! | H50: =D50/E50 -> #DIV/0! | I50: =H50/G50 -> #DIV/0! | J50: 6.77 | K50: 1236 | M50: 59.95 | N50: =J50/M50 -> 0.11292744 | O50: =M50/J50 -> 8.8552437 | P50: =J50/D50 -> #DIV/0! | Q50: =M50/D50 -> #DIV/0! | R50: =D50-M50 -> -59.95 | S50: =J50/L50 -> #DIV/0!
C51: Dielon - Prosvent - Highly Recommended | G51: =E51/F51 -> #DIV/0! | H51: =D51/E51 -> #DIV/0! | I51: =H51/G51 -> #DIV/0! | J51: 31.72 | K51: 3015 | M51: 4.06 | N51: =(J51/M51) -> 7.8128079 | O51: =M51/J51 -> 0.12799496 | P51: =J51/D51 -> #DIV/0! | Q51: =M51/D51 -> #DIV/0! | R51: =D51-M51 -> -4.06 | S51: =J51/L51 -> #DIV/0!
C52: Dielon - Better Bladder - Highly Recommended | G52: =E52/F52 -> #DIV/0! | H52: =D52/E52 -> #DIV/0! | I52: =H52/G52 -> #DIV/0! | J52: 20.73 | K52: 4270 | M52: 0 | N52: =J52/M52 -> #DIV/0! | O52: =M52/J52 -> 0 | P52: =J52/D52 -> #DIV/0! | Q52: =M52/D52 -> #DIV/0! | R52: =D52-M52 -> 0 | S52: =J52/L52 -> #DIV/0!
C53: Dielon - Rotorazer - Highly Recommended | G53: =E53/F53 -> #DIV/0! | H53: =D53/E53 -> #DIV/0! | I53: =H53/G53 -> #DIV/0! | J53: 0 | K53: 0 | M53: 0 | N53: =J53/M53 -> #DIV/0! | O53: =M53/J53 -> #DIV/0! | P53: =J53/D53 -> #DIV/0! | Q53: =M53/D53 -> #DIV/0! | R53: =D53-M53 -> 0 | S53: =J53/L53 -> #DIV/0!
C54: Dielon - Superthotics - Highly Recommended | G54: =E54/F54 -> #DIV/0! | H54: =D54/E54 -> #DIV/0! | I54: =H54/G54 -> #DIV/0! | J54: 0.04 | K54: 10 | M54: 0 | N54: =J54/M54 -> #DIV/0! | O54: =M54/J54 -> 0 | P54: =J54/D54 -> #DIV/0! | Q54: =M54/D54 -> #DIV/0! | R54: =D54-M54 -> 0 | S54: =J54/L54 -> #DIV/0!
C55: Dielon - AirDoctor Filter - Highly Recommended | G55: =E55/F55 -> #DIV/0! | H55: =D55/E55 -> #DIV/0! | I55: =H55/G55 -> #DIV/0! | J55: 3.03 | K55: 344 | M55: 0 | N55: =J55/M55 -> #DIV/0! | O55: =M55/J55 -> 0 | P55: =J55/D55 -> #DIV/0! | Q55: =M55/D55 -> #DIV/0! | R55: =D55-M55 -> 0 | S55: =J55/L55 -> #DIV/0!
B56: to | C56: Dielon - AquaTru Filters- Highly Recommended | G56: =E56/F56 -> #DIV/0! | H56: =D56/E56 -> #DIV/0! | I56: =H56/G56 -> #DIV/0! | J56: 0.69 | K56: 79 | M56: 0 | N56: =J56/M56 -> #DIV/0! | O56: =M56/J56 -> 0 | P56: =J56/D56 -> #DIV/0! | Q56: =M56/D56 -> #DIV/0! | R56: =D56-M56 -> 0 | S56: =J56/L56 -> #DIV/0!
C57: Dielon - AirDoctor Main - Highly Recommended | G57: =E57/F57 -> #DIV/0! | H57: =D57/E57 -> #DIV/0! | I57: =H57/G57 -> #DIV/0! | J57: 20.21 | K57: 3545 | M57: 0 | N57: =J57/M57 -> #DIV/0! | O57: =M57/J57 -> 0 | P57: =J57/D57 -> #DIV/0! | Q57: =M57/D57 -> #DIV/0! | R57: =D57-M57 -> 0 | S57: =J57/L57 -> #DIV/0!
C58: Dielon - Walkfit Platinum - Highly Recommended | G58: =E58/F58 -> #DIV/0! | H58: =D58/E58 -> #DIV/0! | I58: =H58/G58 -> #DIV/0! | J58: 35.53 | K58: 3794 | M58: 0 | N58: =J58/M58 -> #DIV/0! | O58: =M58/J58 -> 0 | P58: =J58/D58 -> #DIV/0! | Q58: =M58/D58 -> #DIV/0! | R58: =D58-M58 -> 0 | S58: =J58/L58 -> #DIV/0!
A59: =iferror(if(B59>0,month(B59)&"-"&year(B59),B59),) -> 3-2025 | B59: 45738 | C59: Dielon - Grown American - Highly Recommended | G59: =E59/F59 -> #DIV/0! | H59: =D59/E59 -> #DIV/0! | I59: =H59/G59 -> #DIV/0! | J59: 0 | K59: 0 | M59: 0 | N59: =J59/M59 -> #DIV/0! | O59: =M59/J59 -> #DIV/0! | P59: =J59/D59 -> #DIV/0! | Q59: =M59/D59 -> #DIV/0! | R59: =D59-M59 -> 0 | S59: =J59/L59 -> #DIV/0!
A60: =iferror(if(B60>0,month(B60)&"-"&year(B60),B60),) | B60: Week 12 | D60: =SUM(D49:D59) -> 0 | E60: =SUM(E49:E59) -> 0 | F60: =SUM(F49:F59) -> 0 | G60: =E60/F60 -> #DIV/0! | H60: =D60/E60 -> #DIV/0! | I60: =H60/G60 -> #DIV/0! | J60: =SUM(J49:J59) -> 128.25 | K60: =SUM(K49:K59) -> 20661 | L60: =SUM(L49:L59) -> 0 | M60: =SUM(M49:M59) -> 64.01 | N60: =J60/M60 -> 2.0035932 | O60: =M60/J60 -> 0.49910331 | P60: =J60/D60 -> #DIV/0! | Q60: =M60/D60 -> #DIV/0! | R60: =SUM(R49:R59) -> -64.01 | S60: =J60/L60 -> #DIV/0! | T60: =IFERROR((D60-D48)/D60,) | U60: =IFERROR((E60-E48)/E60,) | V60: =IFERROR((D60-#REF!)/D60, ) | W60: =IFERROR((E60-#REF!)/E60, )
B61: 45739 | C61: Dielon - AquaTru - Highly Recommended | G61: =E61/F61 -> #DIV/0! | H61: =D61/E61 -> #DIV/0! | I61: =H61/G61 -> #DIV/0! | J61: 10.74 | K61: 4424 | M61: 610.28 | N61: =J61/M61 -> 0.017598479 | O61: =M61/J61 -> 56.823091 | P61: =J61/D61 -> #DIV/0! | Q61: =M61/D61 -> #DIV/0! | R61: =D61-M61 -> -610.28 | S61: =J61/L61 -> #DIV/0!
C62: Dielon - Ideal Prostate - Highly Recommended | G62: =E62/F62 -> #DIV/0! | H62: =D62/E62 -> #DIV/0! | I62: =H62/G62 -> #DIV/0! | J62: 35.87 | K62: 6713 | M62: 69.95 | N62: =J62/M62 -> 0.51279485 | O62: =M62/J62 -> 1.9500976 | P62: =J62/D62 -> #DIV/0! | Q62: =M62/D62 -> #DIV/0! | R62: =D62-M62 -> -69.95 | S62: =J62/L62 -> #DIV/0!
C63: Dielon - Prosvent - Highly Recommended | G63: =E63/F63 -> #DIV/0! | H63: =D63/E63 -> #DIV/0! | I63: =H63/G63 -> #DIV/0! | J63: 0.15 | K63: 85 | M63: 0 | N63: =(J63/M63) -> #DIV/0! | O63: =M63/J63 -> 0 | P63: =J63/D63 -> #DIV/0! | Q63: =M63/D63 -> #DIV/0! | R63: =D63-M63 -> 0 | S63: =J63/L63 -> #DIV/0!
C64: Dielon - Better Bladder - Highly Recommended | G64: =E64/F64 -> #DIV/0! | H64: =D64/E64 -> #DIV/0! | I64: =H64/G64 -> #DIV/0! | J64: 4.03 | K64: 963 | M64: 0 | N64: =J64/M64 -> #DIV/0! | O64: =M64/J64 -> 0 | P64: =J64/D64 -> #DIV/0! | Q64: =M64/D64 -> #DIV/0! | R64: =D64-M64 -> 0 | S64: =J64/L64 -> #DIV/0!
C65: Dielon - Rotorazer - Highly Recommended | G65: =E65/F65 -> #DIV/0! | H65: =D65/E65 -> #DIV/0! | I65: =H65/G65 -> #DIV/0! | J65: 0 | K65: 0 | M65: 0 | N65: =J65/M65 -> #DIV/0! | O65: =M65/J65 -> #DIV/0! | P65: =J65/D65 -> #DIV/0! | Q65: =M65/D65 -> #DIV/0! | R65: =D65-M65 -> 0 | S65: =J65/L65 -> #DIV/0!
C66: Dielon - Superthotics - Highly Recommended | G66: =E66/F66 -> #DIV/0! | H66: =D66/E66 -> #DIV/0! | I66: =H66/G66 -> #DIV/0! | J66: 15.27 | K66: 1222 | M66: 50.96 | N66: =J66/M66 -> 0.29964678 | O66: =M66/J66 -> 3.3372626 | P66: =J66/D66 -> #DIV/0! | Q66: =M66/D66 -> #DIV/0! | R66: =D66-M66 -> -50.96 | S66: =J66/L66 -> #DIV/0!
C67: Dielon - AirDoctor Filter - Highly Recommended | G67: =E67/F67 -> #DIV/0! | H67: =D67/E67 -> #DIV/0! | I67: =H67/G67 -> #DIV/0! | J67: 32.5 | K67: 3674 | M67: 89.95 | N67: =J67/M67 -> 0.36131184 | O67: =M67/J67 -> 2.7676923 | P67: =J67/D67 -> #DIV/0! | Q67: =M67/D67 -> #DIV/0! | R67: =D67-M67 -> -89.95 | S67: =J67/L67 -> #DIV/0!
B68: to | C68: Dielon - AquaTru Filters- Highly Recommended | G68: =E68/F68 -> #DIV/0! | H68: =D68/E68 -> #DIV/0! | I68: =H68/G68 -> #DIV/0! | J68: 1.58 | K68: 54 | M68: 0 | N68: =J68/M68 -> #DIV/0! | O68: =M68/J68 -> 0 | P68: =J68/D68 -> #DIV/0! | Q68: =M68/D68 -> #DIV/0! | R68: =D68-M68 -> 0 | S68: =J68/L68 -> #DIV/0!
C69: Dielon - AirDoctor Main - Highly Recommended | G69: =E69/F69 -> #DIV/0! | H69: =D69/E69 -> #DIV/0! | I69: =H69/G69 -> #DIV/0! | J69: 112.2 | K69: 22894 | M69: 0 | N69: =J69/M69 -> #DIV/0! | O69: =M69/J69 -> 0 | P69: =J69/D69 -> #DIV/0! | Q69: =M69/D69 -> #DIV/0! | R69: =D69-M69 -> 0 | S69: =J69/L69 -> #DIV/0!
C70: Dielon - Walkfit Platinum - Highly Recommended | G70: =E70/F70 -> #DIV/0! | H70: =D70/E70 -> #DIV/0! | I70: =H70/G70 -> #DIV/0! | J70: 20.85 | K70: 4350 | M70: 0 | N70: =J70/M70 -> #DIV/0! | O70: =M70/J70 -> 0 | P70: =J70/D70 -> #DIV/0! | Q70: =M70/D70 -> #DIV/0! | R70: =D70-M70 -> 0 | S70: =J70/L70 -> #DIV/0!
A71: =iferror(if(B71>0,month(B71)&"-"&year(B71),B71),) -> 3-2025 | B71: 45745 | C71: Dielon - Grown American - Highly Recommended | G71: =E71/F71 -> #DIV/0! | H71: =D71/E71 -> #DIV/0! | I71: =H71/G71 -> #DIV/0! | J71: 0 | K71: 0 | M71: 0 | N71: =J71/M71 -> #DIV/0! | O71: =M71/J71 -> #DIV/0! | P71: =J71/D71 -> #DIV/0! | Q71: =M71/D71 -> #DIV/0! | R71: =D71-M71 -> 0 | S71: =J71/L71 -> #DIV/0!
A72: =iferror(if(B72>0,month(B72)&"-"&year(B72),B72),) | B72: Week 13 | D72: =SUM(D61:D71) -> 0 | E72: =SUM(E61:E71) -> 0 | F72: =SUM(F61:F71) -> 0 | G72: =E72/F72 -> #DIV/0! | H72: =D72/E72 -> #DIV/0! | I72: =H72/G72 -> #DIV/0! | J72: =SUM(J61:J71) -> 233.19 | K72: =SUM(K61:K71) -> 44379 | L72: =SUM(L61:L71) -> 0 | M72: =SUM(M61:M71) -> 821.14 | N72: =J72/M72 -> 0.28398324 | O72: =M72/J72 -> 3.5213345 | P72: =J72/D72 -> #DIV/0! | Q72: =M72/D72 -> #DIV/0! | R72: =SUM(R61:R71) -> -821.14 | S72: =J72/L72 -> #DIV/0! | T72: =IFERROR((D72-D48)/D72,) | U72: =IFERROR((E72-E48)/E72,) | V72: =IFERROR((D72-#REF!)/D72, ) | W72: =IFERROR((E72-#REF!)/E72, )
B73: 45746 | C73: Dielon - AquaTru - Highly Recommended | G73: =E73/F73 -> #DIV/0! | H73: =D73/E73 -> #DIV/0! | I73: =H73/G73 -> #DIV/0! | J73: 112.81 | K73: 40548 | M73: 718.38 | N73: =J73/M73 -> 0.15703388 | O73: =M73/J73 -> 6.3680525 | P73: =J73/D73 -> #DIV/0! | Q73: =M73/D73 -> #DIV/0! | R73: =D73-M73 -> -718.38 | S73: =J73/L73 -> #DIV/0!
C74: Dielon - Ideal Prostate - Highly Recommended | G74: =E74/F74 -> #DIV/0! | H74: =D74/E74 -> #DIV/0! | I74: =H74/G74 -> #DIV/0! | J74: 5.81 | K74: 1003 | M74: 0 | N74: =J74/M74 -> #DIV/0! | O74: =M74/J74 -> 0 | P74: =J74/D74 -> #DIV/0! | Q74: =M74/D74 -> #DIV/0! | R74: =D74-M74 -> 0 | S74: =J74/L74 -> #DIV/0!
C75: Dielon - Prosvent - Highly Recommended | G75: =E75/F75 -> #DIV/0! | H75: =D75/E75 -> #DIV/0! | I75: =H75/G75 -> #DIV/0! | J75: 23.66 | K75: 7758 | M75: 133.98 | N75: =(J75/M75) -> 0.17659352 | O75: =M75/J75 -> 5.6627219 | P75: =J75/D75 -> #DIV/0! | Q75: =M75/D75 -> #DIV/0! | R75: =D75-M75 -> -133.98 | S75: =J75/L75 -> #DIV/0!
C76: Dielon - Better Bladder - Highly Recommended | G76: =E76/F76 -> #DIV/0! | H76: =D76/E76 -> #DIV/0! | I76: =H76/G76 -> #DIV/0! | J76: 11.77 | K76: 3610 | M76: 0 | N76: =J76/M76 -> #DIV/0! | O76: =M76/J76 -> 0 | P76: =J76/D76 -> #DIV/0! | Q76: =M76/D76 -> #DIV/0! | R76: =D76-M76 -> 0 | S76: =J76/L76 -> #DIV/0!
C77: Dielon - Rotorazer - Highly Recommended | G77: =E77/F77 -> #DIV/0! | H77: =D77/E77 -> #DIV/0! | I77: =H77/G77 -> #DIV/0! | J77: 0 | K77: 0 | M77: 0 | N77: =J77/M77 -> #DIV/0! | O77: =M77/J77 -> #DIV/0! | P77: =J77/D77 -> #DIV/0! | Q77: =M77/D77 -> #DIV/0! | R77: =D77-M77 -> 0 | S77: =J77/L77 -> #DIV/0!
C78: Dielon - Superthotics - Highly Recommended | G78: =E78/F78 -> #DIV/0! | H78: =D78/E78 -> #DIV/0! | I78: =H78/G78 -> #DIV/0! | J78: 24.6 | K78: 3042 | M78: 50.96 | N78: =J78/M78 -> 0.48273155 | O78: =M78/J78 -> 2.0715447 | P78: =J78/D78 -> #DIV/0! | Q78: =M78/D78 -> #DIV/0! | R78: =D78-M78 -> -50.96 | S78: =J78/L78 -> #DIV/0!
C79: Dielon - AirDoctor Filter - Highly Recommended | G79: =E79/F79 -> #DIV/0! | H79: =D79/E79 -> #DIV/0! | I79: =H79/G79 -> #DIV/0! | J79: 67.98 | K79: 8098 | M79: 178 | N79: =J79/M79 -> 0.38191011 | O79: =M79/J79 -> 2.6184172 | P79: =J79/D79 -> #DIV/0! | Q79: =M79/D79 -> #DIV/0! | R79: =D79-M79 -> -178 | S79: =J79/L79 -> #DIV/0!
B80: to | C80: Dielon - AquaTru Filters- Highly Recommended | G80: =E80/F80 -> #DIV/0! | H80: =D80/E80 -> #DIV/0! | I80: =H80/G80 -> #DIV/0! | J80: 0.58 | K80: 106 | M80: 0 | N80: =J80/M80 -> #DIV/0! | O80: =M80/J80 -> 0 | P80: =J80/D80 -> #DIV/0! | Q80: =M80/D80 -> #DIV/0! | R80: =D80-M80 -> 0 | S80: =J80/L80 -> #DIV/0!
C81: Dielon - AirDoctor Main - Highly Recommended | G81: =E81/F81 -> #DIV/0! | H81: =D81/E81 -> #DIV/0! | I81: =H81/G81 -> #DIV/0! | J81: 14.19 | K81: 3583 | M81: 0 | N81: =J81/M81 -> #DIV/0! | O81: =M81/J81 -> 0 | P81: =J81/D81 -> #DIV/0! | Q81: =M81/D81 -> #DIV/0! | R81: =D81-M81 -> 0 | S81: =J81/L81 -> #DIV/0!
C82: Dielon - Walkfit Platinum - Highly Recommended | G82: =E82/F82 -> #DIV/0! | H82: =D82/E82 -> #DIV/0! | I82: =H82/G82 -> #DIV/0! | J82: 37.85 | K82: 6765 | M82: 204.96 | N82: =J82/M82 -> 0.18467018 | O82: =M82/J82 -> 5.4150594 | P82: =J82/D82 -> #DIV/0! | Q82: =M82/D82 -> #DIV/0! | R82: =D82-M82 -> -204.96 | S82: =J82/L82 -> #DIV/0!
A83: =iferror(if(B83>0,month(B83)&"-"&year(B83),B83),) -> 4-2025 | B83: 45752 | C83: Dielon - Grown American - Highly Recommended | G83: =E83/F83 -> #DIV/0! | H83: =D83/E83 -> #DIV/0! | I83: =H83/G83 -> #DIV/0! | J83: 0 | K83: 0 | M83: 0 | N83: =J83/M83 -> #DIV/0! | O83: =M83/J83 -> #DIV/0! | P83: =J83/D83 -> #DIV/0! | Q83: =M83/D83 -> #DIV/0! | R83: =D83-M83 -> 0 | S83: =J83/L83 -> #DIV/0!
